Workbook
Name \a: [1]CPK!$Y$1:$Z$2
Name __A1: #N/A
Name __hdd1: #REF!
Name __Q3: [6]YSS31!#REF!
Name __stv1: [7]DataIn!$P$9
Name _1: #REF!
Name _10._Sensitive_Customer_Information_?__Y_N: [8]InformationAssetInventory!#REF!
Name _2: #REF!
Name _3: #REF!
Name _５８期: #REF!
Name _５９期: #REF!
Name _６０期: #REF!
Name _６１期: #REF!
Name _６２期: #REF!
Name _６３期: #REF!
Name _６４期: #REF!
Name _６５期: #REF!
Name _６６期: #REF!
Name _６７期: #REF!
Name _６８期: #REF!
Name _６９期: #REF!
Name _７０期: #REF!
Name _７１期: #REF!
Name _７２期: #REF!
Name _７３期: #REF!
Name _A1: #N/A
Name _hdd1: #REF!
Name _Ｍ１: #REF!
Name _Ｍ２: #REF!
Name _Ｍ３: #REF!
Name _Q3: [10]YSS31!#REF!
Name _stv1: [7]DataIn!$P$9
Name A: #N/A
Name ａａ: #REF!
Name aaa: [11]受注台帳!#REF!
Name Adua: #REF!
Name AI: #N/A
Name AIR: #REF!
Name and: [12]総合価格!$B$565:$K$673
Name asd: #N/A
Name atas3sigma: #REF!
Name AVG: [7]DataIn!$P$7
Name AVG_B: [13]DataInB!$P$7
Name B: #REF!
Name batasbawahx: #REF!
Name bawah3sigma: #REF!
Name bb: #REF!
Name bbb: [11]受注台帳!#REF!
Name BRCONC: #REF!
Name BRCONCJUDGE: #REF!
Name BRCOUNT: #REF!
Name BRCOUNTERROR: #REF!
Name BRERROR: #REF!
Name BRERRORJUDGE: #REF!
Name C.point: #REF!
Name C_1_CURRENT: #REF!
Name C_1_DEADTIME: #REF!
Name C_1_EFFECTIVETIME: #REF!
Name C_1_FILTER: #REF!
Name C_1_MEASTIME: #REF!

Sheet AUDIT KMC
D1: LIST CONTROL PC | U1: INFORMASI PEMBELIAN
A2: UPDATE | D2: : NOVEMBER 2025
A3: User | I3: IP ADDRESS MAIN | J3: IP ADDRESS BACKUP | K3: Tahun | N3: Status | O3: KLASIFIKASI | P3: LISENSI
A4: NO | B4: NO.ASSET | C4: TYPE | D4: DIVISI | E4: DEPT | F4: NAMA | G4: NIK | H4: HOSTNAME | K4: Pembelian | L4: Batas Depresiasi (5 Tahun) | M4: Batas Extend (+1 Tahun) | P4: 2025 | Q4: 2026 | R4: 2027 | S4: Trend Micro (Max PC & Svr 265) | T4: Cybereason (Max PC & Svr 245) | U4: SUPPLIER | V4: NO PO | W4: TGL AKUISISI | X4: PIC SUPPLIER | Y4: KONTAK SUPPLIER
A5: 1 | B5: FI-00936 | C5: LAPTOP | D5: EXECUTIVE BOARD | E5: - | F5: KANTO SHIBATANI (X1 Carbon) | G5: 110501 | H5: PIK1COM049 | I5: 172.17.12.19 | J5: DHCP | K5: 2024 | L5: 2029 | M5: 2030 | N5: Active | O5: LAPTOP MANAGERIAL | P5: E3 INTUNE | Q5: E3 INTUNE | R5: E3 INTUNE | S5: 1 | T5: 1
A6: 2 | B6: FI-00639 | C6: LAPTOP | D6: EXECUTIVE BOARD | E6: - | F6: MUTSUHIKO UCHIYAMA | G6: 1007001 | H6: PIKPC116 | I6: 172.17.12.16 | J6: DHCP | K6: 2021 | L6: 2026 | M6: 2027 | N6: Active | O6: LAPTOP MANAGERIAL | P6: E3 INTUNE | Q6: E3 INTUNE | R6: E3 INTUNE | S6: 1 | T6: 1 | Z6: OFFICER ADMIN | AA6: OHB | AB6: OHB | AC6: OHB | AD6: OHB
A7: 3 | B7: FI-00640 | C7: LAPTOP | D7: EXECUTIVE BOARD | E7: - | F7: SHIBATANI KANTO | G7: 110501 | H7: PIKPC106 | I7: 172.17.12.18 | J7: DHCP | K7: 2021 | L7: 2026 | M7: 2027 | N7: Active | O7: LAPTOP MANAGERIAL | P7: E3 INTUNE | Q7: E3 INTUNE | R7: E3 INTUNE | S7: 1 | T7: 1 | Z7: TEKNIKAL | AA7: OHB | AB7: OHB | AC7: OHB | AD7: OHB
A8: 4 | B8: FI-00641 | C8: LAPTOP | D8: EXECUTIVE BOARD | E8: - | F8: ERMA PURNAMA WIDA PANE | G8: 1008001 | H8: PIKPC107 | I8: 172.17.12.31 | J8: DHCP | K8: 2021 | L8: 2026 | M8: 2027 | N8: Active | O8: LAPTOP MANAGERIAL | P8: E3 INTUNE | Q8: E3 INTUNE | R8: E3 INTUNE | S8: 1 | T8: 1 | Z8: OPERATOR | AA8: OHB | AB8: OHB | AC8: OHB | AD8: OHB
A9: 5 | B9: FI-01114 | C9: ALL IN ONE | D9: FINANCE DIV | E9: FA | F9: MAUDICA FAMELA AGISTY PUTERI | G9: 2508023 | H9: PIK1COM160 | I9: 172.17.12.192 | J9: 172.17.128.8 | K9: 2025 | L9: 2030 | M9: 2031 | N9: Active | O9: OFFICER ADMIN | P9: OHB | Q9: - | R9: - | S9: 1 | T9: 1 | U9: SBTELECOM | V9: 023/PO/HR&GA/GA/VII/2025 | X9: ASTRI | Y9: 0811-1067-925
A10: 6 | B10: FI-01115 | C10: ALL IN ONE | D10: FINANCE DIV | E10: FA | F10: DEVARA RADITYA FAJRIAWAN | G10: 2203039 | H10: PIK1COM161 | I10: 172.17.12.197 | J10: 172.17.128.7 | K10: 2025 | L10: 2030 | M10: 2031 | N10: Active | O10: OFFICER ADMIN | P10: OHB | Q10: - | R10: - | S10: 1 | T10: 1 | U10: SBTELECOM | V10: 023/PO/HR&GA/GA/VII/2025 | X10: ASTRI | Y10: 0811-1067-925
A11: 7 | B11: FI-01026 | C11: ALL IN ONE | D11: FINANCE DIV | E11: FA | F11: ASTIANI PEBRIANA | G11: 2203040 | H11: PIK1COM120 | I11: 172.17.12.199 | J11: 172.17.128.6 | K11: 2024 | L11: 2029 | M11: 2030 | N11: Active | O11: OFFICER ADMIN | P11: OHB Apr | Q11: - | R11: - | S11: 1 | T11: 1 | U11: TETRANET | V11: 039/PO/HR&GA/GA/X/2024 | W11: 1 Dec 2024 | X11: AFDAL | Z11: APLIKASI WMS | AA11: OHB | AB11: OHB | AC11: OHB | AD11: OHB
A12: 8 | B12: FI-00767 | C12: LAPTOP | D12: FINANCE DIV | E12: FA | F12: YAYAH ROHIYAH | G12: 1307002 | H12: PIK1COM023 | I12: 172.17.12.189 | J12: DHCP | K12: 2023 | L12: 2028 | M12: 2029 | N12: Active | O12: LAPTOP MANAGERIAL | P12: E3 | Q12: E3 | R12: E3 | S12: 1 | T12: 1
A13: 9 | B13: FI-00775 | C13: ALL IN ONE | D13: FINANCE DIV | E13: FA | F13: FANI YULIANI | G13: 1505006 | H13: PIK1COM016 | I13: 172.17.12.191 | J13: 172.17.128.5 | K13: 2023 | L13: 2028 | M13: 2029 | N13: Active | O13: OFFICER ADMIN | P13: OHB Apr | Q13: - | R13: - | S13: 1 | T13: 1
A14: 10 | B14: FI-00927 | C14: ALL IN ONE | D14: FINANCE DIV | E14: FA | F14: FERA PEBRIANA | G14: 1403005 | H14: PIK1COM044 | I14: 172.17.12.190 | J14: 172.17.128.4 | K14: 2023 | L14: 2028 | M14: 2029 | N14: Active | O14: OFFICER ADMIN | P14: OHB Apr | Q14: - | R14: - | S14: 1 | T14: 1
A15: 11 | B15: FI-00670 | C15: ALL IN ONE | D15: FINANCE DIV | E15: FA | F15: STEVE FANNIE | G15: 1011032 | H15: PIKPC132 | I15: 172.17.12.188 | J15: 172.17.128.3 | K15: 2022 | L15: 2027 | M15: 2028 | N15: Active | O15: AKTIVITAS KHUSUS | P15: AFB | Q15: AFB Jul | R15: AFB Jul | S15: 1 | T15: 1
A16: 12 | B16: FI-00607 | C16: LAPTOP | D16: FINANCE DIV | E16: FA | F16: IMAN KOESTIAMAN | G16: 1112021 | H16: PIKLT004 | I16: 172.17.12.186 | J16: DHCP | K16: 2021 | L16: 2026 | M16: 2027 | N16: Active | O16: LAPTOP MANAGERIAL | P16: E3 INTUNE | Q16: E3 Jun | R16: E3 Jun | S16: 1 | T16: 1
A17: 13 | B17: FI-01104 | C17: ALL IN ONE | D17: GENERAL AFFAIR DIV | E17: HRGA | F17: ASHRI DANIELLI | G17: 1402007 | H17: PIK1COM149 | I17: 172.17.12.76 | J17: 172.17.128.27 | K17: 2025 | L17: 2030 | M17: 2031 | N17: Active | O17: OPERATOR | P17: OHB | Q17: - | R17: - | S17: 1 | T17: 1 | U17: SBTELECOM | V17: 032/PO/HR&GA/GA/VI/2025 | W17: 1 Sep 2025 | X17: ASTRI | Y17: 0811-1067-925
A18: 14 | B18: FI-01094 | C18: LAPTOP | D18: GENERAL AFFAIR DIV | E18: HR GA | F18: PAYROLL (AYUNG YUANSAH) | G18: 1205001 | H18: PIK1COM152 | I18: 172.17.12.37 | J18: DHCP | K18: 2025 | L18: 2030 | M18: 2031 | N18: Active | O18: LAPTOP MANAGERIAL | P18: E3 | Q18: E3 | R18: E3 | S18: 1 | T18: 1 | U18: SBTELECOM | V18: 034/PO/HR&GA/GA/VI/2025 | W18: 1 Sep 2025 | X18: ASTRI | Y18: 0811-1067-925
A19: 15 | B19: FI-01019 | C19: ALL IN ONE | D19: GENERAL AFFAIR DIV | E19: HR GA | F19: WINCI AYU ADIANINGSIH | G19: 2412014 | H19: PIK1COM109 | I19: 172.17.12.75 | J19: 172.17.128.14 | K19: 2024 | L19: 2029 | M19: 2030 | N19: Active | O19: OFFICER ADMIN | P19: OHB Apr | Q19: - | R19: - | S19: 1 | T19: 1 | U19: TETRANET | V19: 009/PO/HR&GA/GA/X/2024 | W19: 45627 | X19: AFDAL
A20: 16 | B20: FI-01004 | C20: ALL IN ONE | D20: GENERAL AFFAIR DIV | E20: HR GA | F20: ANDRI FAISAL | G20: 1411001 | H20: PIK1COM102 | I20: 172.17.12.45 | J20: 172.17.128.12 | K20: 2024 | L20: 2029 | M20: 2030 | N20: Active | O20: OFFICER ADMIN | P20: OHB Apr | Q20: - | R20: - | S20: 1 | T20: 1
A21: 17 | B21: FI-01003 | C21: ALL IN ONE | D21: GENERAL AFFAIR DIV | E21: HR GA | F21: AHMAD KAMALUDIN (EX: RATNA) | G21: 1604048 | H21: PIK1COM100 | I21: 172.17.12.54 | J21: 172.17.128.13 | K21: 2024 | L21: 2029 | M21: 2030 | N21: Active | O21: OFFICER ADMIN | P21: OHB Apr | Q21: - | R21: - | S21: 1 | T21: 1
A22: 18 | B22: FI-00981 | C22: ALL IN ONE | D22: GENERAL AFFAIR DIV | E22: HR GA | F22: ERNA YULIAWATI | G22: 1208059 | H22: PIK1COM084 | I22: 172.17.12.43 | J22: 172.17.128.11 | K22: 2024 | L22: 2029 | M22: 2030 | N22: Active | O22: OFFICER ADMIN | P22: OHB Apr | Q22: - | R22: - | S22: 1 | T22: 1
A23: 19 | B23: FI-00960 | C23: ALL IN ONE | D23: GENERAL AFFAIR DIV | E23: HR GA | F23: SUSINTAWATI (TC) | G23: 1208058 | H23: PIK1COM056 | I23: 172.17.12.47 | J23: 172.17.128.15 | K23: 2024 | L23: 2029 | M23: 2030 | N23: Active | O23: OFFICER ADMIN | P23: OHB Jun (PP16) | Q23: - | R23: - | S23: 1 | T23: 1
A24: 20 | B24: FI-00787 | C24: LAPTOP | D24: GENERAL AFFAIR DIV | E24: HR GA | F24: TC (AYUNG) | G24: 1205001 | H24: PIK1COM035 | I24: 172.17.12.48 | J24: DHCP | K24: 2023 | L24: 2028 | M24: 2029 | N24: Active | O24: LAPTOP MANAGERIAL | P24: E3 | Q24: E3 | R24: E3 | S24: 1 | T24: 1
A25: 21 | B25: FI-00660 | C25: ALL IN ONE | D25: GENERAL AFFAIR DIV | E25: HR GA | F25: ADNY AGESTIAN VIRZY | G25: 1605034 | H25: PIKPC122 | I25: 172.17.12.222 | J25: 172.17.128.16 | K25: 2022 | L25: 2027 | M25: 2028 | N25: Active | O25: OFFICER ADMIN | P25: OHB Apr | Q25: - | R25: - | S25: 1 | T25: 1 | U25: XDC | V25: 012/PO/HR&GA/GA/GA/III/2025 | W25: 45748 | X25: WIDI | Y25: 0821-2106-7715
A26: 22 | B26: FI-00762 | C26: LAPTOP | D26: GENERAL AFFAIR DIV | E26: HRGA | F26: RIA RATNANINGSIH | G26: 1605033 | H26: PIK1COM022 | I26: 172.17.12.71 | J26: DHCP | K26: 2023 | L26: 2028 | M26: 2029 | N26: Active | O26: LAPTOP MANAGERIAL | P26: E3 | Q26: E3 | R26: E3 | S26: 1 | T26: 1
A27: 23 | B27: FI-00654 | C27: LAPTOP | D27: GENERAL AFFAIR DIV | E27: HRGA | F27: KOITO M-14 (AYUNG YUANSAH) | G27: 1205001 | H27: PIKPC115 | I27: 172.17.12.214 | J27: DHCP | K27: 2021 | L27: 2026 | M27: 2027 | N27: Active | O27: LAPTOP MEETING | P27: E3 | Q27: E3 | R27: E3 | S27: 1 | T27: 1
A28: 24 | B28: FI-00603 | C28: MINI PC | D28: GENERAL AFFAIR DIV | E28: HRGA | F28: MEETING 14 (OJT) EX : SARI REZEKI | G28: 1205001 | H28: PIKPC141 | I28: - | J28: 172.17.128.17 | K28: 2021 | L28: 2026 | M28: 2027 | N28: Active Brrow | O28: MINI PC MEETING | P28: PP16 | S28: 1 | T28: 0
A29: 25 | B29: FI-00602 | C29: MINI PC | D29: GENERAL AFFAIR DIV | E29: HRGA | F29: ROOM TC DEV EX : DEPI JAELANI | G29: 1205001 | H29: PIKPC004 | I29: 172.17.12.215 | J29: 172.17.128.18 | K29: 2021 | L29: 2026 | M29: 2027 | N29: Active Brrow | O29: MINI PC MEETING | P29: PP16 | S29: 1 | T29: 0
A30: 26 | B30: FI-00601 | C30: MINI PC | D30: GENERAL AFFAIR DIV | E30: HRGA | F30: MEETING 12 (OJT) EX: WINDA | G30: 1205001 | H30: PIKPC003 | I30: - | J30: 172.17.128.19 | K30: 2021 | L30: 2026 | M30: 2027 | N30: Active Brrow | O30: MINI PC MEETING | P30: PP16 | S30: 1 | T30: 0
A31: 27 | B31: FI-00583 | C31: MINI PC | D31: GENERAL AFFAIR DIV | E31: HRGA | F31: ROOM MEETING 3 EX : YAHDI | G31: 1205001 | H31: PIKPC146 | I31: 172.17.11.212 | J31: 172.17.128.20 | K31: 2020 | L31: 2025 | M31: 2026 | N31: Active Brrow | O31: MINI PC MEETING | P31: PP16 | S31: 1 | T31: 0
A32: 28 | B32: FI-00582 | C32: MINI PC | D32: GENERAL AFFAIR DIV | E32: HRGA | F32: MEETING 10 (OJT) EX : NURHASIM | G32: 1205001 | H32: PIKPC149 | I32: - | J32: 172.17.118.2 | K32: 2020 | L32: 2025 | M32: 2026 | N32: Active Brrow | O32: MINI PC MEETING | P32: PP16 | S32: 1 | T32: 0
A33: 29 | B33: FI-00581 | C33: MINI PC | D33: GENERAL AFFAIR DIV | E33: HRGA | F33: MEETING 09 (OJT) EX: ABDUL WACHID | G33: 1205001 | H33: PURPC018 | I33: - | J33: 172.17.128.21 | K33: 2020 | L33: 2025 | M33: 2026 | N33: Active Brrow | O33: MINI PC MEETING | P33: PP16 | S33: 1 | T33: 0
A34: 30 | B34: FI-00576 | C34: MINI PC | D34: GENERAL AFFAIR DIV | E34: HRGA | F34: MEETING 08 EX: ADNY | G34: 1205001 | H34: HRGAPC025 | I34: - | J34: 172.17.128.22 | K34: 2020 | L34: 2025 | M34: 2026 | N34: Active Brrow | O34: MINI PC MEETING | P34: PP16 | S34: 1 | T34: 0
A35: 31 | B35: FI-00575 | C35: MINI PC | D35: GENERAL AFFAIR DIV | E35: HRGA | F35: MEETING 07 EX : MONITOR 2 | G35: 1205001 | H35: - | I35: - | J35: 172.17.128.23 | K35: 2020 | L35: 2025 | M35: 2026 | N35: Active Brrow | O35: MINI PC MEETING | P35: PP16 | S35: 1 | T35: 0
A36: 32 | B36: FI-00574 | C36: MINI PC | D36: GENERAL AFFAIR DIV | E36: HRGA | F36: ROOM MEETING A EX : RICHAR | G36: 1205001 | H36: INJPC003 | I36: 172.17.12.211 | J36: 172.17.128.24 | K36: 2020 | L36: 2025 | M36: 2026 | N36: Active Brrow | O36: MINI PC MEETING | P36: PP16 | S36: 1 | T36: 0
A37: 33 | B37: FI-00573 | C37: MINI PC | D37: GENERAL AFFAIR DIV | E37: HRGA | F37: MEETING 05 EX: TARNO | G37: 1205001 | H37: LOGPC003 | I37: - | J37: 172.17.118.3 | K37: 2020 | L37: 2025 | M37: 2026 | N37: Active Brrow | O37: MINI PC MEETING | P37: PP16 | S37: 1 | T37: 0
A38: 34 | B38: FI-00572 | C38: MINI PC | D38: GENERAL AFFAIR DIV | E38: HRGA | F38: ROOM MEETING 1 EX: FATIKA | G38: 1205001 | H38: QEPC021 | I38: 172.17.11.211 | J38: 172.17.118.4 | K38: 2020 | L38: 2025 | M38: 2026 | N38: Active Brrow | O38: MINI PC MEETING | P38: PP16 | S38: 1 | T38: 0
A39: 35 | B39: FI-00571 | C39: MINI PC | D39: GENERAL AFFAIR DIV | E39: HRGA | F39: MEETING 03 EX :IDHAM RAKHMADI | G39: 1205001 | H39: HRGAPC024 | I39: - | J39: 172.17.118.5 | K39: 2020 | L39: 2025 | M39: 2026 | N39: Active Brrow | O39: MINI PC MEETING | P39: PP16 | S39: 1 | T39: 0
... A41: 37 | B41: FI-00553 | C41: MINI PC | D41: GENERAL AFFAIR DIV | E41: HRGA | F41: ROOM MEETING 5 EX: AFIFAH SALMA | G41: 1205001 | H41: QEPC019 | I41: 172.17.11.215 | J41: 172.17.128.25 | K41: 2020 | L41: 2025 | M41: 2026 | N41: Active Brrow | O41: MINI PC MEETING | P41: PP16 | S41: 1 | T41: 0
A42: 38 | B42: FI-00537 | C42: MINI PC | D42: GENERAL AFFAIR DIV | E42: HR GA | F42: EX : AHMAD KAMALUDIN | G42: 1604048 | H42: PIKPC034 | I42: 172.17.12.49 | J42: 172.17.128.26 | K42: 2019 | L42: 2024 | M42: 2025 | N42: Active | O42: OFFICER ADMIN | P42: - | Q42: OHB Mar (depre) | R42: - | S42: 1 | T42: 1
A43: 39 | B43: FI-00532 | C43: LAPTOP | D43: GENERAL AFFAIR DIV | E43: HR GA | F43: KOITO M-07 EX:ARDI/CAHYO) | G43: 1205001 | H43: PIK1COM072 | I43: - | J43: DHCP | K43: 2019 | L43: 2024 | M43: 2025 | N43: Active | O43: OFFICER ADMIN | P43: E3 | Q43: E3 Jun | R43: E3 Jun | S43: 1 | T43: 1 | U43: XDC | V43: 011/PO/HR&GA/GA/GA/III/2025 | W43: 45748 | X43: WIDI | Y43: 0821-2106-7715
A44: 40 | B44: FI-00413 | C44: LAPTOP | D44: GENERAL AFFAIR DIV | E44: HRGA | F44: KOITO M-13 (AYUNG YUANSAH) | G44: 1205001 | H44: ENGMGRLT001 | I44: - | J44: DHCP | K44: 2018 | L44: 2023 | M44: 2024 | N44: Active | O44: LAPTOP MEETING | P44: E3 | Q44: E3 Jun | R44: E3 Jun | S44: 1 | T44: 1
A45: 41 | B45: FI-00412 | C45: LAPTOP | D45: GENERAL AFFAIR DIV | E45: HR GA | F45: KOITO M-19 (AYUNG YUANSAH) | G45: 1205001 | H45: PIK1COM002 | I45: - | J45: DHCP | K45: 2018 | L45: 2023 | M45: 2024 | N45: Active | O45: LAPTOP MEETING | P45: E3 | Q45: E3 Jun | R45: E3 Jun | S45: 1 | T45: 1
A46: 42 | B46: FI-01062 | C46: ALL IN ONE | D46: GENERAL AFFAIR DIV | E46: IT LEGAL | F46: RATNA SAYYIDA | G46: 2304023 | H46: PIK1COM136 | I46: 172.17.12.65 | J46: 172.17.128.40 | K46: 2025 | L46: 2030 | M46: 2031 | N46: Active | O46: OFFICER ADMIN | P46: OHB Apr | Q46: - | R46: - | S46: 1 | T46: 1 | U46: XDC | V46: 012/PO/HR&GA/GA/GA/III/2025 | W46: 45748 | X46: WIDI | Y46: 0821-2106-7715
A47: 43 | B47: FI-01071 | C47: ALL IN ONE | D47: GENERAL AFFAIR DIV | E47: IT LEGAL | F47: SARI REZEKI | G47: 1402011 | H47: PIK1COM140 | I47: 172.17.12.53 | J47: 172.17.128.39 | K47: 2025 | L47: 2030 | M47: 2031 | N47: Active | O47: OFFICER ADMIN | P47: OHB Apr | Q47: - | R47: - | S47: 1 | T47: 1 | U47: XDC | V47: 011/PO/HR&GA/GA/GA/III/2025 | W47: 45748 | X47: WIDI | Y47: 0821-2106-7715
A48: 44 | B48: FI-01100 | C48: ALL IN ONE | D48: GENERAL AFFAIR DIV | E48: IT LEGAL | F48: TRANSFER DATA LOG IT (AYUNG) | G48: 1701036 | H48: PIK1COM156 | I48: 172.17.12.57 | J48: 172.17.128.38 | K48: 2025 | L48: 2030 | M48: 2031 | N48: Active | O48: OPERATOR | P48: OHB | Q48: - | R48: - | S48: 1 | T48: 1 | U48: SBTELECOM | V48: 045/PO/HR&GA/GA/VI/2025 | W48: 1 Sep 2025 | X48: ASTRI | Y48: 0811-1067-925
A49: 45 | B49: FI-00987 | C49: ALL IN ONE | D49: GENERAL AFFAIR DIV | E49: IT LEGAL | F49: DEVITA DWI ANGGRAENI | G49: 2403012 | H49: PIK1COM098 | I49: 172.17.12.59 | J49: 172.17.128.35 | K49: 2024 | L49: 2029 | M49: 2030 | N49: Active | O49: OFFICER ADMIN | P49: OHB Apr | Q49: - | R49: - | S49: 1 | T49: 1
A50: 46 | B50: FI-00969 | C50: WORKSTATION | D50: GENERAL AFFAIR DIV | E50: ITLEGAL | F50: MOHAMAD FAHMY IQBAL | G50: 1803070 | H50: PIK1COM074 | I50: 172.17.12.63 | J50: 172.17.128.34 | K50: 2024 | L50: 2029 | M50: 2030 | N50: Active | O50: TEKNIKAL | P50: OHB Jun (PP16) | Q50: - | R50: - | S50: 1 | T50: 1
A51: 47 | B51: FI-00742 | C51: ALL IN ONE | D51: GENERAL AFFAIR DIV | E51: IT LEGAL | F51: MISBAHUL MUNIR | G51: 1701036 | H51: PIK1COM006 | I51: 172.17.12.60 | J51: 172.17.128.32 | K51: 2023 | L51: 2028 | M51: 2029 | N51: Active | O51: OPERATOR | P51: OHB Jun (PP16) | Q51: - | R51: - | S51: 1 | T51: 1
A52: 48 | B52: FI-00744 | C52: ALL IN ONE | D52: GENERAL AFFAIR DIV | E52: IT LEGAL | F52: ROFIQ SUGARA | G52: 2304024 | H52: PIK1COM012 | I52: 172.17.12.62 | J52: 172.17.128.36 | K52: 2023 | L52: 2028 | M52: 2029 | N52: Active | O52: OFFICER ADMIN | P52: OHB Jun (PP16) | Q52: - | R52: - | S52: 1 | T52: 1
A53: 49 | B53: FI-00783 | C53: ALL IN ONE | D53: GENERAL AFFAIR DIV | E53: IT LEGAL | F53: FADHI WINIATAMA | G53: 1309033 | H53: PIK1COM036 | I53: 172.17.12.61 | J53: 172.17.128.33 | K53: 2023 | L53: 2028 | M53: 2029 | N53: Active | O53: OFFICER ADMIN | P53: OHB Apr | Q53: - | R53: - | S53: 1 | T53: 1
A54: 50 | B54: FI-00666 | C54: ALL IN ONE | D54: GENERAL AFFAIR DIV | E54: IT LEGAL | F54: DENI AGUSTA | G54: 2302029 | H54: PIK1COM104 | I54: 172.17.12.64 | J54: 172.17.128.37 | K54: 2022 | L54: 2027 | M54: 2028 | N54: Active | O54: OPERATOR | P54: OHB Apr | Q54: - | R54: - | S54: 1 | T54: 1
A55: 51 | B55: FI-00721 | C55: LAPTOP | D55: GENERAL AFFAIR DIV | E55: IT LEGAL | F55: IR (SARI REZEKI) | G55: 1402011 | H55: PIKPC999 | I55: - | J55: DHCP | K55: 2022 | L55: =K55+5 -> 2027 | M55: =K55+6 -> 2028 | N55: Active | O55: LAPTOP MANAGERIAL | P55: E3 | Q55: E3 Jun | R55: E3 Jun | S55: 1 | T55: 1 | U55: XDC | V55: 012/PO/HR&GA/GA/GA/III/2025 | W55: 45748 | X55: WIDI | Y55: 0821-2106-7715
A56: 52 | B56: FI-00616 | C56: LAPTOP | D56: GENERAL AFFAIR DIV | E56: IT LEGAL | F56: KOITO M-08 (MISBAHUL MUNIR) | G56: 1205001 | H56: PIKLT006 | I56: - | J56: DHCP | K56: 2021 | L56: 2026 | M56: 2027 | N56: Active | O56: LAPTOP MEETING | P56: E3 | Q56: E3 Jun | R56: E3 Jun | S56: 1 | T56: 1
A57: 53 | B57: FI-00617 | C57: LAPTOP | D57: GENERAL AFFAIR DIV | E57: IT LEGAL | F57: KOITO M-09 (MISBAHUL MUNIR) | G57: 1205001 | H57: PIKLT007 | I57: - | J57: DHCP | K57: 2021 | L57: 2026 | M57: 2027 | N57: Active | O57: LAPTOP MEETING | P57: E3 | Q57: E3 Jun | R57: E3 Jun | S57: 1 | T57: 1
A58: 54 | B58: FI-00652 | C58: LAPTOP | D58: GENERAL AFFAIR DIV | E58: IT LEGAL | F58: AYUNG YUANSAH | G58: 1205001 | H58: PIKPC112 | I58: 172.17.12.44 | J58: DHCP | K58: 2021 | L58: 2026 | M58: 2027 | N58: Active | O58: LAPTOP MANAGERIAL | P58: E3 | Q58: E3 Jun | R58: E3 Jun | S58: 1 | T58: 1 | U58: XDC | V58: 010/PO/HR&GA/GA/GA/III/2025 | W58: 45748 | X58: WIDI | Y58: 0821-2106-7715
A59: 55 | B59: FI-00656 | C59: LAPTOP | D59: GENERAL AFFAIR DIV | E59: IT LEGAL | F59: LAPTOP EX: AZIS | G59: 1205001 | H59: PIK1COM117 | I59: - | J59: DHCP | K59: 2021 | L59: 2026 | M59: 2027 | N59: Active | O59: LAPTOP MEETING | P59: E3 | Q59: E3 Jun | R59: E3 Jun | S59: 1 | T59: 1
A60: 56 | B60: FI-01025 | C60: ALL IN ONE | D60: HSE DIV | E60: HSE | F60: SYAHRI RAHMAN | G60: 1109060 | H60: PIK1COM119 | I60: 172.17.12.41 | J60: 172.17.128.45 | K60: 2024 | L60: 2029 | M60: 2030 | N60: Active | O60: OFFICER ADMIN | P60: OHB Jun (PP16) | Q60: - | R60: - | S60: 1 | T60: 1 | U60: TETRANET | V60: 039/PO/HR&GA/GA/X/2024 | W60: 1 Dec 2024 | X60: AFDAL
A61: 57 | B61: FI-01038 | C61: DESKTOP | D61: HSE DIV | E61: HSE | F61: VMS 1 (ARI PURNOMSIDI) | G61: 1702001 | H61: PIK1COM116 | I61: 172.17.11.109 | J61: 172.17.118.11 | K61: 2024 | L61: 2029 | M61: 2030 | N61: Active | O61: VMS | P61: - | Q61: - | R61: - | S61: 1 | T61: 1 | U61: LINTAS | V61: 047/PO/HR&GA/GA/IX/2024 | W61: 1 Feb 2025 | X61: TUSLAM
A62: 58 | B62: FI-00963 | C62: ALL IN ONE | D62: HSE DIV | E62: HSE | F62: KARTA | G62: 1306003 | H62: PIK1COM055 | I62: 172.17.12.83 | J62: 172.17.128.46 | K62: 2024 | L62: 2029 | M62: 2030 | N62: Active | O62: OFFICER ADMIN | P62: OHB Jun (PP16) | Q62: - | R62: - | S62: 1 | T62: 1
A63: 59 | B63: FI-01021 | C63: ALL IN ONE | D63: HSE DIV | E63: HSE | F63: HERYANSYAH | G63: 1704002 | H63: PIK1COM105 | I63: 172.17.12.67 | J63: 172.17.128.44 | K63: 2024 | L63: 2029 | M63: 2030 | N63: Active | O63: OFFICER ADMIN | P63: OHB Jun (PP16) | Q63: - | R63: - | S63: 1 | T63: 1 | U63: TETRANET | V63: 069/PO/HR&GA/GA/IX/2024 | W63: 45627 | X63: AFDAL
A64: 60 | B64: FI-01020 | C64: ALL IN ONE | D64: HSE DIV | E64: HSE | F64: KLINIK (ARI PURNOMOSIDI) | G64: 1702001 | H64: PIK1COM108 | I64: 172.17.11.25 | J64: 172.17.118.12 | K64: 2024 | L64: 2029 | M64: 2030 | N64: Active | O64: OFFICER ADMIN | P64: OHB Jun (PP16) | Q64: - | R64: - | S64: 1 | T64: 1 | U64: TETRANET | V64: 069/PO/HR&GA/GA/IX/2024 | W64: 45627 | X64: AFDAL
A65: 61 | B65: FI-00985 | C65: ALL IN ONE | D65: HSE DIV | E65: HSE | F65: HAFIDZ ARDIHANSYAH | G65: 1101138 | H65: PIKPC130 | I65: 172.17.12.74 | J65: 172.17.128.43 | K65: 2022 | L65: 2027 | M65: 2028 | N65: Active | O65: OFFICER ADMIN | P65: OHB Apr | Q65: - | R65: - | S65: 1 | T65: 1
A66: 62 | B66: FI-00669 | C66: ALL IN ONE | D66: HSE DIV | E66: HSE | F66: ARI PURNOMOSIDI | G66: 1702001 | H66: PIKPC131 | I66: 172.17.12.73 | J66: 172.17.128.42 | K66: 2022 | L66: 2027 | M66: 2028 | N66: Active | O66: OFFICER ADMIN | P66: OHB Apr | Q66: - | R66: - | S66: 1 | T66: 1
A67: 63 | B67: FI-00705 | C67: ALL IN ONE | D67: HSE DIV | E67: HSE | F67: AGUNG IKSAN NUGRAHA | G67: 1708001 | H67: PIKPC167 | I67: 172.17.12.42 | J67: 172.17.128.47 | K67: 2022 | L67: 2027 | M67: 2028 | N67: Active | O67: OFFICER ADMIN | P67: OHB Apr | Q67: - | R67: - | S67: 1 | T67: 1 | U67: XDC | V67: 012/PO/HR&GA/GA/GA/III/2025 | W67: 45748 | X67: WIDI | Y67: 0821-2106-7715
A68: 64 | B68: BELUM AKUISISI | C68: DESKTOP | D68: HSE DIV | E68: HSE | F68: MONITOR 1 POSKO (SITI SUSILAWATI) | G68: 1702001 | H68: PIK1COM169 | I68: 172.17.101.201 | J68: DHCP | K68: 2025 | L68: 2030 | M68: 2031 | N68: Active | O68: CCTV VIEW | P68: - | Q68: - | R68: - | S68: 1 | T68: 1 | U68: SBTELECOM | V68: 007/PO/HR&GA/GA/X/2025 | X68: ASTRI | Y68: 0811-1067-925
A69: 65 | B69: BELUM AKUISISI | C69: LAPTOP | D69: HSE DIV | E69: HSE | F69: SITI SUSILAWATI | G69: 1404041 | H69: PIK1COM170 | I69: 172.17.12.38 | J69: DHCP | K69: 2025 | L69: 2030 | M69: 2031 | N69: Active | O69: LAPTOP MANAGERIAL | P69: E3 | Q69: E3 Jun | R69: E3 Jun | S69: 1 | T69: 1 | U69: SBTELECOM | V69: 007/PO/HR&GA/GA/X/2025 | X69: ASTRI | Y69: 0811-1067-925
A70: 66 | B70: FI-01039 | C70: ALL IN ONE | D70: HSE DIV | E70: HSE | F70: ALBY ABDULFATAH | G70: 2405006 | H70: PIK1COM189 | I70: 172.17.12.81 | J70: 172.17.128.48 | K70: 2025 | L70: 2030 | M70: 2031 | N70: Active | O70: OPERATOR | P70: OHB | Q70: - | R70: - | S70: 1 | T70: 1 | U70: LINTAS | V70: 052/PO/HR&GA/GA/XI/2024 | X70: TUSLAM | Y70: 0819-0475-2651
A71: 67 | B71: FI-01075 | C71: ALL IN ONE | D71: HSE DIV | E71: HSE | F71: IDHAM RAKHMADI | G71: 1611024 | H71: PIK1COM130 | I71: 172.17.12.82 | J71: 172.17.128.49 | K71: 2025 | L71: 2030 | M71: 2031 | N71: Active | O71: OFFICER ADMIN | P71: OHB Apr | Q71: - | R71: - | S71: 1 | T71: 1 | U71: XDC | V71: 013/PO/HR&GA/GA/GA/III/2025 | W71: 45748 | X71: WIDI | Y71: 0821-2106-7715
A72: 68 | B72: FI-01061 | C72: ALL IN ONE | D72: HSE DIV | E72: HSE | F72: MONITOR 2 POSKO (SITI SUSILAWATI) | G72: 1702001 | H72: PIK1COM142 | I72: 172.17.101.202 | J72: DHCP | K72: 2025 | L72: 2030 | M72: 2031 | N72: Active | O72: CCTV VIEW | P72: - | Q72: - | R72: - | S72: 1 | T72: 1 | U72: XDC | V72: 012/PO/HR&GA/GA/GA/III/2025 | W72: 45748 | X72: WIDI | Y72: 0821-2106-7715
A73: 69 | B73: FI-01066 | C73: DESKTOP | D73: HSE DIV | E73: HSE | F73: VMS 2 (ARI PURNOMOSIDI) | G73: 1702001 | H73: PIK1COM144 | I73: 172.17.101.210 | J73: DHCP | K73: 2025 | L73: 2030 | M73: 2031 | N73: Active | O73: VMS | P73: - | Q73: - | R73: - | S73: 1 | T73: 1 | U73: XDC | V73: 010/PO/HR&GA/GA/GA/III/2025 | W73: 45748 | X73: WIDI | Y73: 0821-2106-7715
A74: 70 | B74: BELUM AKUISISI | C74: ALL IN ONE | D74: HSE DIV | E74: HSE | F74: DIANNE CHRISTIN SIANTURI | G74: 2509013 | H74: PIK1COM163 | I74: 172.17.12.72 | J74: 172.17.128.50 | K74: 2025 | L74: 2030 | M74: 2031 | N74: Active | O74: OFFICER ADMIN | P74: OHB Aug (depre) | Q74: - | R74: - | S74: 1 | T74: 1 | U74: SBTELECOM | V74: 015/PO/HR&GA/GA/VIII/2025 | X74: ASTRI | Y74: 0811-1067-925
A75: 71 | B75: FI-00764 | C75: LAPTOP | D75: INJECTION MOLD DIV | E75: INJECTION MOLD DIV | F75: HIROYOSHI OHI | G75: 2405001 | H75: PIK1COM028 | I75: 172.17.11.26 | J75: DHCP | K75: 2023 | L75: =K75+5 -> 2028 | M75: =K75+6 -> 2029 | N75: Active | O75: LAPTOP MANAGERIAL | P75: E3 INTUNE | Q75: E3 Jun | R75: E3 Jun | S75: 1 | T75: 1
A76: 72 | B76: FI-00653 | C76: LAPTOP | D76: INJECTION MOLD DIV | E76: INJECTION MOLD DIV | F76: EDY PRASETYA | G76: 1011006 | H76: PIKPC120 | I76: 172.17.12.150 | J76: DHCP | K76: 2021 | L76: =K76+5 -> 2026 | M76: =K76+6 -> 2027 | N76: Active | O76: LAPTOP MANAGERIAL | P76: E3 INTUNE | Q76: E3 Jun | R76: E3 Jun | S76: 1 | T76: 1
A77: 73 | B77: FI-01080 | C77: WORKSTATION | D77: INJECTION MOLD DIV | E77: MOLD ENG | F77: ARIP DWI JAYA SINA | G77: 1405013 | H77: PIK1COM145 | I77: 172.17.12.153 | J77: 172.17.128.53 | K77: 2025 | L77: 2030 | M77: 2031 | N77: Active | O77: TEKNIKAL | P77: OHB Apr | Q77: - | R77: - | S77: 1 | T77: 1 | U77: XDC | V77: 014/PO/HR&GA/GA/III/2025 | W77: 45839 | X77: WIDI | Y77: 0821-2106-7715
A78: 74 | B78: FI-00985 | C78: ALL IN ONE | D78: INJECTION MOLD DIV | E78: MOLD ENG | F78: RAHMAWATI HARDIAN PRATIWI | G78: 1904001 | H78: PIK1COM123 | I78: 172.17.12.158 | J78: 172.17.128.54 | K78: 2025 | L78: 2030 | M78: 2031 | N78: Active | O78: OFFICER ADMIN | P78: OHB Apr | Q78: - | R78: - | S78: 1 | T78: 1
A79: 75 | B79: FI-01015 | C79: WORKSTATION | D79: INJECTION MOLD DIV | E79: MOLD ENG | F79: ANDRE MARTHA SAPUTRA | G79: 1511009 | H79: PIK1COM118 | I79: 172.17.12.155 | J79: 172.17.128.55 | K79: 2024 | L79: 2029 | M79: 2030 | N79: Active | O79: TEKNIKAL | P79: OHB Apr | Q79: - | R79: - | S79: 1 | T79: 1 | U79: TETRANET | V79: 008/PO/HR&GA/GA/X/2024 | W79: 45627 | X79: AFDAL
A80: 76 | B80: FI-00770 | C80: LAPTOP | D80: INJECTION MOLD DIV | E80: MOLD ENG | F80: KRISTANTO DWI SAPUTRA | G80: 1804001 | H80: PIK1COM026 | I80: 172.17.12.152 | J80: DHCP | K80: 2023 | L80: 2028 | M80: 2029 | N80: Active | O80: LAPTOP MANAGERIAL | P80: E3 INTUNE | Q80: E3 Jun | R80: E3 Jun | S80: 1 | T80: 1
A81: 77 | B81: FI-00590 | C81: WORKSTATION | D81: INJECTION MOLD DIV | E81: MOLD ENG | F81: CAMTOOL CNC (ALKINDI) | G81: 1703001 | H81: MEDRAWPC002 | I81: 172.17.20.132 | J81: 172.17.218.4 | K81: 2021 | L81: 2026 | M81: 2027 | N81: Active | O81: TEKNIKAL | P81: OHB Jun (PP16) | Q81: AFB Okt | R81: OHB Mei (depre) | S81: 1 | T81: 1
A82: 78 | B82: FI-00591 | C82: WORKSTATION | D82: INJECTION MOLD DIV | E82: MOLD ENG | F82: MOLDFLOW (ISMAIL MARJUKI) | G82: 1801027 | H82: PIK1COM011 | I82: 172.17.12.163 | J82: 172.17.128.56 | K82: 2021 | L82: 2026 | M82: 2027 | N82: Active | O82: TEKNIKAL | P82: OHB Apr | Q82: - | R82: - | S82: 1 | T82: 1
A83: 79 | B83: FI-00952 | C83: WORKSTATION | D83: INJECTION MOLD DIV | E83: MOLD MAKING | F83: REZA ADITYA PERMADI | G83: 2412013 | H83: PIK1COM076 | I83: 172.17.20.135 | J83: 172.17.218.5 | K83: 2024 | L83: 2029 | M83: 2030 | N83: Active | O83: TEKNIKAL | P83: OHB Jun (PP16) | Q83: - | R83: - | S83: 1 | T83: 1
A84: 80 | B84: FI-01014 | C84: WORKSTATION | D84: INJECTION MOLD DIV | E84: MOLD MAKING | F84: DICKY ZULFIKAR | G84: 1206004 | H84: PIK1COM113 | I84: 172.17.20.131 | J84: 172.17.218.2 | K84: 2024 | L84: 2029 | M84: 2030 | N84: Active | O84: TEKNIKAL | P84: OHB Apr | Q84: - | R84: - | S84: 1 | T84: 1 | U84: TETRANET | V84: 038/PO/HR&GA/GA/X/2024 | W84: 45627 | X84: AFDAL
A85: 81 | B85: FI-00743 | C85: ALL IN ONE | D85: INJECTION MOLD DIV | E85: MOLD MAKING | F85: CNC (TOMMY) | G85: 1406005 | H85: PIK1COM008 | I85: 172.17.20.130 | J85: 172.17.218.6 | K85: 2023 | L85: 2028 | M85: 2029 | N85: Active | O85: OFFICER ADMIN | P85: OHB Apr | Q85: - | R85: - | S85: 1 | T85: 1
A86: 82 | B86: FI-00788 | C86: ALL IN ONE | D86: INJECTION MOLD DIV | E86: MOLD MAKING | F86: DENI FIRMANSYAH | G86: 1506012 | H86: PIK1COM039 | I86: 172.17.20.136 | J86: 172.17.218.3 | K86: 2023 | L86: 2028 | M86: 2029 | N86: Active | O86: OPERATOR | P86: OHB Apr | Q86: - | R86: - | S86: 1 | T86: 1
A87: 83 | B87: FI-00612 | C87: WORKSTATION | D87: INJECTION MOLD DIV | E87: MOLD MAKING | F87: CATIA 2 (DADI HERIYANTO) | G87: 1709001 | H87: PIKPC156 | I87: 172.17.20.133 | J87: 172.17.218.7 | K87: 2021 | L87: 2026 | M87: 2027 | N87: Active | O87: TEKNIKAL | P87: OHB Apr | Q87: - | R87: - | S87: 1 | T87: 1
A88: 84 | B88: FI-00541 | C88: WORKSTATION | D88: INJECTION MOLD DIV | E88: MOLD MAKING | F88: MOLD DRAW PC (REZA ADITYA PERMADI) | G88: 2412013 | H88: MEDRAWPC001 | I88: 172.17.20.134 | J88: 172.17.218.8 | K88: 2019 | L88: 2024 | M88: 2025 | N88: Active | O88: TEKNIKAL | P88: OHB Apr | Q88: - | R88: - | S88: 1 | T88: 1
A89: 85 | B89: FI-00507 | C89: MINI PC | D89: INJECTION MOLD DIV | E89: MOLD MAKING | F89: ANDINI SEPTOWATI | G89: 1506019 | H89: MEPC010 | I89: 172.17.12.157 | J89: 172.17.128.57 | K89: 2019 | L89: =K89+5 -> 2024 | M89: 2025 | N89: Active | O89: OFFICER ADMIN | P89: OHB Des (depre) | Q89: - | R89: - | S89: 1 | T89: 1
A90: 86 | B90: FI-01035 | C90: WORKSTATION | D90: INJECTION MOLD DIV | E90: MOLD MTC | F90: DIDI PERIYANTO 2 | G90: 1105005 | H90: PIK1COM188 | I90: 172.17.11.93 | J90: 172.17.118.18 | K90: 2024 | L90: 2029 | M90: 2030 | N90: Active | O90: TEKNIKAL | P90: OHB Jun (PP16) | Q90: - | R90: - | S90: 1 | T90: 1 | U90: LINTAS | V90: 053/PO/HR&GA/GA/XI/2024 | W90: 1 Feb 2025 | X90: TUSLAM | Y90: 0819-0475-2651
A91: 87 | B91: FI-00959 | C91: ALL IN ONE | D91: INJECTION MOLD DIV | E91: MOLD MTC | F91: DIDI PERIYANTO | G91: 1105005 | H91: PIK1COM054 | I91: 172.17.11.76 | J91: 172.17.118.17 | K91: 2024 | L91: 2029 | M91: 2030 | N91: Active | O91: OFFICER ADMIN | P91: OHB Jun (PP16) | Q91: - | R91: - | S91: 1 | T91: 1
A92: 88 | B92: FI-01040 | C92: ALL IN ONE | D92: INJECTION MOLD DIV | E92: MOLD MTC | F92: SAMSURIZAL | G92: 1011023 | H92: PIK1COM122 | I92: 172.17.11.86 | J92: 172.17.118.16 | K92: 2024 | L92: 2029 | M92: 2030 | N92: Active | O92: OFFICER ADMIN | P92: OHB Jun (PP16) | Q92: - | R92: - | S92: 1 | T92: 1 | U92: LINTAS | V92: 052/PO/HR&GA/GA/XI/2024 | W92: 1 Feb 2025 | X92: TUSLAM | Y92: 0819-0475-2651
A93: 89 | B93: FI-00975 | C93: LAPTOP | D93: KPS | E93: KPS | F93: SYAIFUL RAMADHAN | G93: 1302030 | H93: PIK1COM073 | I93: 172.17.11.51 | J93: DHCP | K93: 2024 | L93: 2029 | M93: 2030 | N93: Active | O93: LAPTOP MANAGERIAL | P93: E3 INTUNE | Q93: E3 INTUNE | R93: E3 INTUNE | S93: 1 | T93: 1
A94: 90 | B94: FI-00672 | C94: ALL IN ONE | D94: KPS | E94: KPS | F94: AJI SUSANTO | G94: 1406004 | H94: PIKPC134 | I94: 172.17.11.50 | J94: 172.17.118.22 | K94: 2022 | L94: 2027 | M94: 2028 | N94: Active | O94: OFFICER ADMIN | P94: OHB Apr | Q94: - | R94: - | S94: 1 | T94: 1
A95: 91 | B95: FI-00695 | C95: ALL IN ONE | D95: KPS | E95: KPS | F95: DUDI SUGITO | G95: 1108007 | H95: PIKPC154 | I95: 172.17.11.87 | J95: 172.17.118.24 | K95: 2022 | L95: 2027 | M95: 2028 | N95: Active | O95: OPERATOR | P95: OHB Apr | Q95: - | R95: - | S95: 1 | T95: 1
A96: 92 | B96: FI-00649 | C96: LAPTOP | D96: KPS | E96: KPS | F96: DADANG CAHYADI | G96: 1508002 | H96: PIKPC104 | I96: 172.17.11.57 | J96: DHCP | K96: 2021 | L96: 2026 | M96: 2027 | N96: Active | O96: LAPTOP MANAGERIAL | P96: E3 | Q96: E3 | R96: E3 | S96: 1 | T96: 1
A97: 93 | B97: FI-00526 | C97: MINI PC | D97: KPS | E97: KPS | F97: DENIS | G97: #N/A | H97: KPSPC001 | I97: 172.17.11.53 | J97: 172.17.118.25 | K97: 2019 | L97: 2024 | M97: 2025 | N97: Active | O97: OPERATOR | P97: - | Q97: - | R97: OHB Apr (depre) | S97: 1 | T97: 1
A98: 94 | B98: FI-00536 | C98: MINI PC | D98: KPS | E98: KPS | F98: SYAIFUL RAMADHAN | G98: 1302030 | H98: KPSPC002 | I98: 172.17.11.52 | J98: 172.17.118.23 | K98: 2019 | L98: 2024 | M98: 2025 | N98: Active | O98: OFFICER ADMIN | P98: - | Q98: - | R98: OHB Apr (depre) | S98: 1 | T98: 1
A99: 95 | B99: FI-01095 | C99: LAPTOP | D99: KPS | E99: KPS | F99: LAPTOP MEETING JISUKEN 1 (DADANG) | G99: 1508002 | H99: PIK1COM151 | I99: - | J99: DHCP | K99: 2025 | L99: 2030 | M99: 2031 | N99: Active | O99: LAPTOP MANAGERIAL | P99: E3 INTUNE | Q99: E3 INTUNE | R99: E3 INTUNE | S99: 1 | T99: 1 | U99: SBTELECOM | V99: 034/PO/HR&GA/GA/VI/2025 | W99: 1 Sep 2025 | X99: ASTRI | Y99: 0811-1067-925
A100: 96 | B100: BELUM AKUISISI | C100: LAPTOP | D100: MARKETING DIV | E100: CONTROL | F100: ARIS HERYANTO | G100: 1210002 | H100: PIK1COM171 | I100: 172.17.12.88 | J100: 172.17.128.63 | K100: 2025 | L100: 2030 | M100: =L100+1 -> 2031 | N100: Active | O100: OFFICER ADMIN | P100: E3 | Q100: E3 | R100: E3 | S100: 1 | T100: 1 | U100: SBTELECOM | V100: 007/PO/HR&GA/GA/X/2025 | X100: ASTRI | Y100: 0811-1067-925
A101: 97 | B101: FI-00988 | C101: ALL IN ONE | D101: MARKETING DIV | E101: CONTROL | F101: SITI FAJAR SEPTIA | G101: 2501007 | H101: PIK1COM090 | I101: 172.17.12.107 | J101: 172.17.128.64 | K101: 2024 | L101: 2029 | M101: =L101+1 -> 2030 | N101: Active | O101: OPERATOR | P101: OHB Apr | Q101: - | R101: - | S101: 1 | T101: 1
...

Sheet SUMMARY LINK
A1: SUMARRY
A3: Type | C3: Lisensi : | E3: OS : | I3: NOTE :
A4: 1. PC | C4: OHB | D4: 136 | E4: Windows 10 | F4: 5 | I4: Standar PC | J4: 226
A5: - All In One | B5: 137 | C5: E3 | D5: 54 | E5: Windows 11 | F5: 224 | I5: Additional 2025 | J5: 3
A6: - Mini Pc | B6: 13 | C6: AFB | D6: 21 | E6: Total Windows | F6: 229 | I6: Total PC | J6: =SUM(J4:J5) -> 229
A7: - Workstation | B7: 15 | C7: PP16 | D7: 13
A8: - Dekstop | B8: 11 | C8: No Lisensi | D8: 5
A9: 2. Laptop | B9: 53 | C9: Total | D9: =SUM(D4:D8) -> 229
A10: Total | B10: =SUM(B4:B9) -> 229

Sheet PC  (detail)
E1: CLIENT PC ASSET LIST | AM1: INFORMASI PEMBELIAN
B2: UPDATE | E2: : FEB 2026
I3: Tahun | K3: Status | L3: KLASIFIKASI | Y3: LISENSI | AG3: IP ADDRESS MAIN | AH3: IP ADDRESS BACKUP | AI3: LISENSI MS OFFICE | AJ3: Windows | AK3: Trend Micro (Max PC & Svr 265) | AL3: Cybereason (Max PC & Svr 245)
B4: NO | C4: NO.ASSET | D4: TYPE | E4: DIVISI | F4: DEPT | G4: NAMA | H4: NIK | I4: Pembelian | J4: Depresiasi (5+1 Tahun) | M4: Managerial | N4: Meeting | O4: Aktivitas Khusus | P4: Officer Admin | Q4: Teknikal | R4: Operator | S4: Aplikasi WMS | T4: VMS | U4: CCTV View | V4: Station Delivery | W4: Aplikasi Gathering | X4: OQC | Y4: E3 | Z4: BB | AA4: OHB | AB4: INTUNE | AC4: AFB | AD4: EMAIL | AE4: SMX | AF4: HOSTNAME | AM4: SUPPLIER | AN4: NO PO | AO4: TAHUN BELI | AP4: BULAN DEPRESIASI | AQ4: PIC SUPPLIER | AR4: KONTAK SUPPLIER | AS4: REMARKS | AV4: SCHEDULE DISPOSE 2026
B5: 1 | C5: FI-00936 | D5: LAPTOP | E5: EXECUTIVE BOARD | F5: - | G5: KANTO SHIBATANI (X1 Carbon) | H5: 110501 | I5: 2024 | J5: =I5+6 -> 2030 | K5: ACTIVE | L5: LAPTOP MANAGERIAL | M5: ✓ | Y5: YA | AB5: YA | AC5: TIDAK | AD5: k-shibatani@ikoito.co.id | AE5: YA | AF5: PIK1COM049 | AG5: 172.17.12.19 | AH5: DHCP | AI5: E3 | AJ5: Windows 11 | AK5: 1 | AL5: 1 | AM5: CLARUS | AN5: 019/PO/HR&GA/GA/XII/2023 | AO5: 45261 | AP5: 47453 | AQ5: LUSY | AR5: 0811-1067-925 | AS5: LAPTOP ADD DES 2023
B6: 2 | C6: FI-00639 | D6: LAPTOP | E6: EXECUTIVE BOARD | F6: - | G6: MUTSUHIKO UCHIYAMA | H6: 1007001 | I6: 2021 | J6: =I6+6 -> 2027 | K6: ACTIVE | L6: LAPTOP MANAGERIAL | M6: ✓ | Y6: YA | AB6: YA | AC6: TIDAK | AD6: mu-uchiyama@ikoito.co.id | AE6: YA | AF6: PIKPC116 | AG6: 172.17.12.16 | AH6: DHCP | AI6: E3 | AJ6: Windows 11 | AK6: 1 | AL6: 1 | AM6: SBTELECOM | AN6: 023/PO/HR&GA/GA/ VI/2021 | AO6: 44348 | AP6: 46539 | AQ6: ASTRI | AR6: 0811-1067-925 | AS6: UPGRADE LAP MNGR JUNI 2021 (20 UNIT)
B7: 3 | C7: FI-00640 | D7: LAPTOP | E7: EXECUTIVE BOARD | F7: - | G7: SHIBATANI KANTO | H7: 110501 | I7: 2021 | J7: =I7+6 -> 2027 | K7: ACTIVE | L7: LAPTOP MANAGERIAL | M7: ✓ | Y7: YA | AB7: YA | AC7: TIDAK | AD7: k-shibatani@ikoito.co.id | AE7: YA | AF7: PIKPC106 | AG7: 172.17.12.18 | AH7: DHCP | AI7: E3 | AJ7: Windows 11 | AK7: 1 | AL7: 1 | AM7: SBTELECOM | AN7: 023/PO/HR&GA/GA/ VI/2021 | AO7: 44348 | AP7: 46539 | AQ7: ASTRI | AR7: 0811-1067-925 | AS7: UPGRADE LAP MNGR JUNI 2021 (20 UNIT)
B8: 4 | C8: FI-00641 | D8: LAPTOP | E8: EXECUTIVE BOARD | F8: - | G8: ERMA PURNAMA WIDA PANE | H8: 1008001 | I8: 2021 | J8: =I8+6 -> 2027 | K8: ACTIVE | L8: LAPTOP MANAGERIAL | M8: ✓ | Y8: YA | AB8: YA | AC8: TIDAK | AD8: erma@ikoito.co.id | AE8: YA | AF8: PIKPC107 | AG8: 172.17.12.31 | AH8: DHCP | AI8: E3 | AJ8: Windows 11 | AK8: 1 | AL8: 1 | AM8: SBTELECOM | AN8: 023/PO/HR&GA/GA/ VI/2021 | AO8: 44348 | AP8: 46539 | AQ8: ASTRI | AR8: 0811-1067-925 | AS8: UPGRADE LAP MNGR JUNI 2021 (20 UNIT)
B9: 5 | C9: FI-01114 | D9: ALL IN ONE | E9: FINANCE DIV | F9: FA | G9: MAUDICA FAMELA AGISTY PUTERI | H9: 2508023 | I9: 2025 | J9: =I9+6 -> 2031 | K9: ACTIVE | L9: OFFICER ADMIN | P9: ✓ | Z9: YA | AA9: YA | AC9: TIDAK | AD9: =VLOOKUP(C9,'[39]LAMPIRAN STANDAR'!$E$81:F$216,2,0) -> maudica.f@ikoito.co.id | AE9: YA | AF9: PIK1COM160 | AG9: 172.17.12.192 | AH9: 172.17.128.8 | AI9: OHB | AJ9: Windows 11 | AK9: 1 | AL9: 1 | AM9: SBTELECOM | AN9: 023/PO/HR&GA/GA/VII/2025 | AO9: 45839 | AP9: 48030 | AQ9: ASTRI | AR9: 0811-1067-925 | AS9: DEPRE JUL 2025
B10: 6 | C10: FI-01115 | D10: ALL IN ONE | E10: FINANCE DIV | F10: FA | G10: DIKA PRATAMA PUTRA | H10: 2601016 | I10: 2025 | J10: =I10+6 -> 2031 | K10: ACTIVE | L10: OFFICER ADMIN | P10: ✓ | Z10: YA | AA10: YA | AC10: TIDAK | AD10: =VLOOKUP(C10,'[39]LAMPIRAN STANDAR'!$E$81:F$216,2,0) -> accounting@ikoito.co.id | AE10: YA | AF10: PIK1COM161 | AG10: 172.17.12.197 | AH10: 172.17.128.7 | AI10: OHB | AJ10: Windows 11 | AK10: 1 | AL10: 1 | AM10: SBTELECOM | AN10: 023/PO/HR&GA/GA/VII/2025 | AO10: 45839 | AP10: 48030 | AQ10: ASTRI | AR10: 0811-1067-925 | AS10: DEPRE JUL 2025
B11: 7 | C11: FI-01026 | D11: ALL IN ONE | E11: FINANCE DIV | F11: FA | G11: ASTIANI PEBRIANA | H11: 2203040 | I11: 2024 | J11: =I11+6 -> 2030 | K11: ACTIVE | L11: OFFICER ADMIN | P11: ✓ | Z11: YA | AA11: YA | AC11: TIDAK | AD11: =VLOOKUP(C11,'[39]LAMPIRAN STANDAR'!$E$81:F$216,2,0) -> astiani.p@ikoito.co.id | AE11: YA | AF11: PIK1COM120 | AG11: 172.17.12.199 | AH11: 172.17.128.6 | AI11: OHB | AJ11: Windows 11 | AK11: 1 | AL11: 1 | AM11: TETRANET | AN11: 039/PO/HR&GA/GA/X/2024 | AO11: 45597 | AP11: 47788 | AQ11: AFDAL | AR11: 0831-8760-3905 | AS11: DEPRE NOV 2024
B12: 8 | C12: FI-00767 | D12: LAPTOP | E12: FINANCE DIV | F12: FA | G12: YAYAH ROHIYAH | H12: 1307002 | I12: 2023 | J12: =I12+6 -> 2029 | K12: ACTIVE | L12: LAPTOP MANAGERIAL | M12: ✓ | Y12: YA | Z12: TIDAK | AC12: TIDAK | AD12: yayah.r@ikoito.co.id | AE12: YA | AF12: PIK1COM023 | AG12: 172.17.12.189 | AH12: DHCP | AI12: E3 | AJ12: Windows 11 | AK12: 1 | AL12: 1 | AM12: CLARUS | AN12: 058/PO/HR&GA/GA/VI/2023 | AO12: 45108 | AP12: 47300 | AQ12: LUSY | AR12: 0856-9576-1612 | AS12: LAPTOP ADD JULI 2023 (5 UNIT)
B13: 9 | C13: FI-00775 | D13: ALL IN ONE | E13: FINANCE DIV | F13: FA | G13: FANI YULIANI | H13: 1505006 | I13: 2023 | J13: =I13+6 -> 2029 | K13: ACTIVE | L13: OFFICER ADMIN | P13: ✓ | Z13: YA | AA13: YA | AC13: TIDAK | AD13: =VLOOKUP(C13,'[39]LAMPIRAN STANDAR'!$E$81:F$216,2,0) -> fani.y@ikoito.co.id | AE13: YA | AF13: PIK1COM016 | AG13: 172.17.12.191 | AH13: 172.17.128.5 | AI13: OHB | AJ13: Windows 11 | AK13: 1 | AL13: 1 | AM13: DARUMA | AN13: 049/PO/HR&GA/GA/V/2023 | AO13: 45047 | AP13: 47239 | AQ13: RINDU | AR13: - | AS13: PC DEPRE MEI 2023
B14: 10 | C14: FI-00927 | D14: ALL IN ONE | E14: FINANCE DIV | F14: FA | G14: FERA PEBRIANA | H14: 1403005 | I14: 2023 | J14: =I14+6 -> 2029 | K14: ACTIVE | L14: OFFICER ADMIN | P14: ✓ | Z14: YA | AA14: YA | AC14: TIDAK | AD14: =VLOOKUP(C14,'[39]LAMPIRAN STANDAR'!$E$81:F$216,2,0) -> fera.p@ikoito.co.id | AE14: YA | AF14: PIK1COM044 | AG14: 172.17.12.190 | AH14: 172.17.128.4 | AI14: OHB | AJ14: Windows 11 | AK14: 1 | AL14: 1 | AM14: DARUMA | AN14: 023/PO/HR&GA/GA/XI/2023 | AO14: 45231 | AP14: 47423 | AQ14: RINDU | AR14: - | AS14: PC DEPRE NOV 2023
B15: 11 | C15: FI-00670 | D15: ALL IN ONE | E15: FINANCE DIV | F15: FA | G15: STEVE FANNIE | H15: 1011032 | I15: 2022 | J15: =I15+6 -> 2028 | K15: ACTIVE | L15: AKTIVITAS KHUSUS | O15: ✓ | Z15: YA | AC15: YA | AD15: fannie@ikoito.co.id | AE15: YA | AF15: PIKPC132 | AG15: 172.17.12.188 | AH15: 172.17.128.3 | AI15: AFB | AJ15: Windows 11 | AK15: 1 | AL15: 1 | AM15: SBTELECOM | AN15: 024/PO/HR&GA/GA/VI/2021 | AO15: 44348 | AP15: 46539 | AQ15: ASTRI | AR15: 0811-1067-925 | AS15: UPGRADE AIO JUNI 2021 (18 UNIT)
B16: 12 | C16: FI-00607 | D16: LAPTOP | E16: FINANCE DIV | F16: FA | G16: IMAN KOESTIAMAN | H16: 1112021 | I16: 2021 | J16: =I16+6 -> 2027 | K16: ACTIVE | L16: LAPTOP MANAGERIAL | M16: ✓ | Y16: YA | Z16: TIDAK | AC16: TIDAK | AD16: iman.k@ikoito.co.id | AE16: YA | AF16: PIKLT004 | AG16: 172.17.12.186 | AH16: DHCP | AI16: E3 | AJ16: Windows 11 | AK16: 1 | AL16: 1 | AM16: CLARUS | AN16: 028/PO/HR&GA/GA/ I/2021 | AO16: 44348 | AP16: 46388 | AQ16: LUSY | AR16: 0856-9576-1612 | AS16: PC DEPRE JAN 2021
B17: 13 | C17: FI-01104 | D17: ALL IN ONE | E17: GENERAL AFFAIR DIV | F17: HRGA | G17: GA (NURUSSYIFA MAULIDA) | H17: 1510015 | I17: 2025 | J17: =I17+6 -> 2031 | K17: ACTIVE | L17: OPERATOR | R17: ✓ | Z17: TIDAK | AA17: YA | AC17: TIDAK | AD17: - | AE17: TIDAK | AF17: PIK1COM149 | AG17: 172.17.12.76 | AH17: 172.17.128.27 | AI17: OHB | AJ17: Windows 11 | AK17: 1 | AL17: 1 | AM17: SBTELECOM | AN17: 032/PO/HR&GA/GA/VI/2025 | AO17: 45778 | AP17: 47969 | AQ17: ASTRI | AR17: 0811-1067-925 | AS17: DEPRE MEI 2025
B18: 14 | C18: FI-01094 | D18: LAPTOP | E18: GENERAL AFFAIR DIV | F18: HR GA | G18: PAYROLL (ERNA) | H18: 1208059 | I18: 2025 | J18: =I18+6 -> 2031 | K18: ACTIVE | L18: LAPTOP MANAGERIAL | M18: ✓ | Y18: YA | Z18: TIDAK | AA18: TIDAK | AC18: TIDAK | AD18: payroll@ikoito.co.id | AE18: YA | AF18: PIK1COM152 | AG18: 172.17.12.37 | AH18: DHCP | AI18: E3 | AJ18: Windows 11 | AK18: 1 | AL18: 1 | AM18: SBTELECOM | AN18: 034/PO/HR&GA/GA/VI/2025 | AO18: 45748 | AP18: 47939 | AQ18: ASTRI | AR18: 0811-1067-925 | AS18: DEPRE APR 2025
B19: 15 | C19: FI-01019 | D19: ALL IN ONE | E19: GENERAL AFFAIR DIV | F19: HR GA | G19: DHIGTA OKTORIA | H19: 2508022 | I19: 2024 | J19: =I19+6 -> 2030 | K19: ACTIVE | L19: OFFICER ADMIN | P19: ✓ | Y19: TIDAK | Z19: YA | AA19: YA | AC19: TIDAK | AD19: =VLOOKUP(C19,'[39]LAMPIRAN STANDAR'!$E$81:F$216,2,0) -> ga@ikoito.co.id | AE19: YA | AF19: PIK1COM109 | AG19: 172.17.12.75 | AH19: 172.17.128.14 | AI19: OHB | AJ19: Windows 11 | AK19: 1 | AL19: 1 | AM19: TETRANET | AN19: 009/PO/HR&GA/GA/X/2024 | AO19: 45566 | AP19: 47757 | AQ19: AFDAL | AR19: 0831-8760-3905 | AS19: DEPRE OKT 2024
B20: 16 | C20: FI-01004 | D20: ALL IN ONE | E20: GENERAL AFFAIR DIV | F20: HR GA | G20: ANDRI FAISAL | H20: 1411001 | I20: 2024 | J20: =I20+6 -> 2030 | K20: ACTIVE | L20: OFFICER ADMIN | P20: ✓ | Y20: TIDAK | Z20: YA | AA20: YA | AB20: TIDAK | AC20: TIDAK | AD20: =VLOOKUP(C20,'[39]LAMPIRAN STANDAR'!$E$81:F$216,2,0) -> andri.f@ikoito.co.id | AE20: YA | AF20: PIK1COM102 | AG20: 172.17.12.45 | AH20: 172.17.128.12 | AI20: OHB | AJ20: Windows 11 | AK20: 1 | AL20: 1 | AM20: RBS | AN20: 041/PO/HR&GA/GA/VIII/2024 | AO20: 45505 | AP20: 47696 | AQ20: SANJAYA | AR20: 0858-8878-8800 | AS20: DEPRE AGUST 2024
B21: 17 | C21: FI-01003 | D21: ALL IN ONE | E21: GENERAL AFFAIR DIV | F21: HR GA | G21: HR RECRUITMENT (KAMILAH) | H21: 1109018 | I21: 2024 | J21: =I21+6 -> 2030 | K21: ACTIVE | L21: OFFICER ADMIN | P21: ✓ | Y21: TIDAK | Z21: YA | AA21: YA | AB21: TIDAK | AC21: TIDAK | AD21: =VLOOKUP(C21,'[39]LAMPIRAN STANDAR'!$E$81:F$216,2,0) -> recruitment@ikoito.co.id | AE21: YA | AF21: PIK1COM100 | AG21: 172.17.12.54 | AH21: 172.17.128.13 | AI21: OHB | AJ21: Windows 11 | AK21: 1 | AL21: 1 | AM21: RBS | AN21: 041/PO/HR&GA/GA/VIII/2024 | AO21: 45505 | AP21: 47696 | AQ21: SANJAYA | AR21: 0858-8878-8800 | AS21: DEPRE AGUST 2024
B22: 18 | C22: FI-00981 | D22: ALL IN ONE | E22: GENERAL AFFAIR DIV | F22: HR GA | G22: ERNA YULIAWATI | H22: 1208059 | I22: 2024 | J22: =I22+6 -> 2030 | K22: ACTIVE | L22: OFFICER ADMIN | P22: ✓ | Y22: TIDAK | Z22: YA | AA22: YA | AB22: TIDAK | AC22: TIDAK | AD22: =VLOOKUP(C22,'[39]LAMPIRAN STANDAR'!$E$81:F$216,2,0) -> erna@ikoito.co.id | AE22: YA | AF22: PIK1COM084 | AG22: 172.17.12.43 | AH22: 172.17.128.11 | AI22: OHB | AJ22: Windows 11 | AK22: 1 | AL22: 1 | AM22: SBTELECOM | AN22: 007/PO/HR&GA/GA/V/2024 | AO22: 45413 | AP22: 47604 | AQ22: ASTRI | AR22: 0811-1067-925 | AS22: PERCEPATAN MEI 2024
B23: 19 | C23: FI-00960 | D23: ALL IN ONE | E23: GENERAL AFFAIR DIV | F23: HR GA | G23: SUSINTAWATI (TC) | H23: 1208058 | I23: 2024 | J23: =I23+6 -> 2030 | K23: ACTIVE | L23: OFFICER ADMIN | P23: ✓ | Y23: TIDAK | Z23: YA | AA23: YA | AB23: TIDAK | AC23: TIDAK | AD23: =VLOOKUP(C23,'[39]LAMPIRAN STANDAR'!$E$81:F$216,2,0) -> hr-training@ikoito.co.id | AE23: YA | AF23: PIK1COM056 | AG23: 172.17.12.47 | AH23: 172.17.128.15 | AI23: OHB | AJ23: Windows 11 | AK23: 1 | AL23: 1 | AM23: SBTELECOM | AN23: 063/PO/HR&GA/GA/I/2024 | AO23: 45292 | AP23: 47484 | AQ23: ASTRI | AR23: 0811-1067-925 | AS23: PC DEPRE JAN 2024
B24: 20 | C24: FI-00787 | D24: LAPTOP | E24: GENERAL AFFAIR DIV | F24: HR GA | G24: TC (AYUNG) | H24: 1205001 | I24: 2023 | J24: =I24+6 -> 2029 | K24: ACTIVE | L24: LAPTOP MANAGERIAL | M24: ✓ | Y24: TIDAK | Z24: TIDAK | AA24: TIDAK | AB24: TIDAK | AC24: TIDAK | AD24: - | AE24: TIDAK | AF24: PIK1COM035 | AG24: 172.17.12.48 | AH24: DHCP | AI24: E3 | AJ24: Windows 11 | AK24: 1 | AL24: 1 | AM24: DARUMA | AN24: 043/PO/HR&GA/GA/VIII/2023 | AO24: 45139 | AP24: 47331 | AQ24: RINDU | AR24: - | AS24: LAPTOP DEPRE AGUST 2023
B25: 21 | C25: FI-00660 | D25: ALL IN ONE | E25: GENERAL AFFAIR DIV | F25: HR GA | G25: HR PAYROLL (RINDY) | H25: 2602032 | I25: 2022 | J25: =I25+6 -> 2028 | K25: ACTIVE | L25: OFFICER ADMIN | P25: ✓ | Y25: TIDAK | Z25: YA | AA25: YA | AB25: TIDAK | AC25: TIDAK | AD25: =VLOOKUP(C25,'[39]LAMPIRAN STANDAR'!$E$81:F$216,2,0) -> hr1@ikoito.co.id | AE25: YA | AF25: PIKPC122 | AG25: 172.17.12.222 | AH25: 172.17.128.16 | AI25: OHB | AJ25: Windows 11 | AK25: 1 | AL25: 1 | AM25: SBTELECOM | AN25: 024/PO/HR&GA/GA/VI/2021 | AO25: 44348 | AP25: 46539 | AQ25: ASTRI | AR25: 0811-1067-925 | AS25: UPGRADE AIO JUNI 2021 (18 UNIT)
B26: 22 | C26: FI-00762 | D26: LAPTOP | E26: GENERAL AFFAIR DIV | F26: HRGA | G26: DEPARTEMEN HEAD HR&GA (HAFIDZ) | H26: 1101138 | I26: 2023 | J26: =I26+6 -> 2029 | K26: ACTIVE | L26: LAPTOP MANAGERIAL | M26: ✓ | Y26: YA | Z26: TIDAK | AA26: TIDAK | AB26: TIDAK | AC26: TIDAK | AD26: hafidz.ardiansyah@ikoito.co.id | AE26: YA | AF26: PIK1COM022 | AG26: 172.17.12.71 | AH26: DHCP | AI26: E3 | AJ26: Windows 11 | AK26: 1 | AL26: 1 | AM26: CLARUS | AN26: 059/PO/HR&GA/GA/VI/2023 | AO26: 45078 | AP26: 47270 | AQ26: LUSY | AR26: 0856-9576-1612 | AS26: PC DEPRE JUNI 2023
B27: 23 | C27: FI-00654 | D27: LAPTOP | E27: GENERAL AFFAIR DIV | F27: HRGA | G27: KOITO M-14 (ERNA) | H27: 1205001 | I27: 2021 | J27: =I27+6 -> 2027 | K27: ACTIVE | L27: LAPTOP MEETING | N27: ✓ | Y27: TIDAK | Z27: TIDAK | AA27: TIDAK | AB27: TIDAK | AC27: TIDAK | AD27: - | AE27: TIDAK | AF27: PIKPC115 | AG27: 172.17.12.214 | AH27: DHCP | AI27: E3 | AJ27: Windows 11 | AK27: 1 | AL27: 1 | AM27: SBTELECOM | AN27: 023/PO/HR&GA/GA/ VI/2021 | AO27: 44348 | AP27: 46539 | AQ27: ASTRI | AR27: 0811-1067-925 | AS27: UPGRADE LAP MNGR JUNI 2021 (20 UNIT)
B28: 24 | C28: FI-00537 | D28: MINI PC | E28: GENERAL AFFAIR DIV | F28: HR GA | G28: HR SH | I28: 43826 | J28: =EDATE(I28,72) -> 46018 | K28: ACTIVE | L28: OFFICER ADMIN | P28: ✓ | Y28: TIDAK | Z28: YA | AA28: YA | AB28: TIDAK | AC28: TIDAK | AD28: =VLOOKUP(C28,'[39]LAMPIRAN STANDAR'!$E$81:F$216,2,0) -> hr-sh@ikoito.co.id | AE28: YA | AF28: PIKPC034 | AG28: 172.17.12.49 | AH28: 172.17.128.26 | AI28: PP16 | AJ28: Windows 11 | AK28: 1 | AL28: 1 | AM28: CLARUS | AN28: 011/PO/HR&GA/GA/VIII/2019 | AO28: 43678 | AP28: 45870 | AQ28: LUSY | AR28: 0856-9576-1612 | AS28: PC DEPRE AGUST 2019
B29: 25 | C29: FI-00532 | D29: LAPTOP | E29: GENERAL AFFAIR DIV | F29: HR GA | G29: KOITO M-07 EX:ARDI/CAHYO) | H29: 1208059 | I29: 43826 | J29: =EDATE(I29,72) -> 46018 | K29: ACTIVE | L29: LAPTOP MEETING | N29: ✓ | Y29: TIDAK | Z29: TIDAK | AA29: TIDAK | AB29: TIDAK | AC29: TIDAK | AD29: - | AE29: TIDAK | AF29: PIK1COM072 | AG29: - | AH29: DHCP | AI29: E3 | AJ29: Windows 11 | AK29: 1 | AL29: 1 | AM29: CLARUS | AN29: 009/PO/HR&GA/GA/VIII/2019 | AO29: 43678 | AP29: 45870 | AQ29: LUSY | AR29: 0856-9576-1612 | AS29: PC DEPRE AGUST 2019
B30: 26 | C30: FI-00413 | D30: LAPTOP | E30: GENERAL AFFAIR DIV | F30: HRGA | G30: KOITO M-13 (ERNA) | H30: 1208059 | I30: 43455 | J30: =EDATE(I30,72) -> 45647 | K30: ACTIVE | L30: LAPTOP MEETING | N30: ✓ | Y30: TIDAK | Z30: TIDAK | AA30: TIDAK | AB30: TIDAK | AC30: TIDAK | AD30: - | AE30: TIDAK | AF30: ENGMGRLT001 | AG30: - | AH30: DHCP | AI30: E3 | AJ30: Windows 11 | AK30: 1 | AL30: 1 | AM30: CSI | AN30: 011/PO/HR&GA/GA/X/2018 | AO30: 43374 | AP30: 45566 | AQ30: IBRAIM | AR30: 0812-8097-4409 | AS30: PC ADD OKT 2018
B31: 27 | C31: FI-00412 | D31: LAPTOP | E31: GENERAL AFFAIR DIV | F31: HR GA | G31: KOITO M-19 (ERNA) | H31: 1208059 | I31: 43455 | J31: =EDATE(I31,72) -> 45647 | K31: ACTIVE | L31: LAPTOP MEETING | N31: ✓ | Y31: TIDAK | Z31: TIDAK | AA31: TIDAK | AB31: TIDAK | AC31: TIDAK | AD31: - | AE31: TIDAK | AF31: PIK1COM002 | AG31: - | AH31: DHCP | AI31: E3 | AJ31: Windows 11 | AK31: 1 | AL31: 1 | AM31: CSI | AN31: 011/PO/HR&GA/GA/X/2018 | AO31: 43374 | AP31: 45566 | AQ31: IBRAIM | AR31: 0812-8097-4409 | AS31: PC ADD OKT 2018
B32: 28 | C32: BELUM AKUISISI | D32: WORKSTATION | E32: GENERAL AFFAIR DIV | F32: IT LEGAL | G32: DARYANA | H32: 1801046 | I32: 2026 | J32: =I32+6 -> 2032 | K32: ACTIVE | L32: TEKNIKAL | Q32: ✓ | Y32: TIDAK | Z32: YA | AA32: YA | AB32: TIDAK | AC32: TIDAK | AD32: it.dx@ikoito.co.id | AE32: YA | AF32: PIK1COM191 | AG32: 172.17.12.66 | AH32: 172.17.128.41 | AI32: OHB | AJ32: Windows 11 | AK32: 1 | AL32: 1 | AM32: SBTELECOM | AN32: 021/PO/HR&GA/GA/XI/2026 | AO32: 46023 | AP32: 48214 | AQ32: ASTRI | AR32: 0811-1067-925 | AS32: ADD JAN 2026
B33: 29 | C33: FI-01100 | D33: ALL IN ONE | E33: GENERAL AFFAIR DIV | F33: IT LEGAL | G33: TRANSFER DATA LOG IT (AYUNG) | H33: 1701036 | I33: 2025 | J33: =I33+6 -> 2031 | K33: ACTIVE | L33: OPERATOR | R33: ✓ | Y33: TIDAK | Z33: TIDAK | AA33: YA | AB33: TIDAK | AC33: TIDAK | AD33: - | AE33: TIDAK | AF33: PIK1COM156 | AG33: 172.17.12.57 | AH33: 172.17.128.38 | AI33: OHB | AJ33: Windows 11 | AK33: 1 | AL33: 1 | AM33: SBTELECOM | AN33: 045/PO/HR&GA/GA/VI/2025 | AO33: 45778 | AP33: 47969 | AQ33: ASTRI | AR33: 0811-1067-925 | AS33: DEPRE MEI 2025
B34: 30 | C34: FI-01071 | D34: ALL IN ONE | E34: GENERAL AFFAIR DIV | F34: IT LEGAL | G34: SARI REZEKI | H34: 1402011 | I34: 2025 | J34: 2030 | K34: ACTIVE | L34: OFFICER ADMIN | P34: ✓ | Y34: TIDAK | Z34: YA | AA34: YA | AB34: TIDAK | AC34: TIDAK | AD34: =VLOOKUP(C34,'[39]LAMPIRAN STANDAR'!$E$81:F$216,2,0) -> legal-control@ikoito.co.id | AE34: YA | AF34: PIK1COM140 | AG34: 172.17.12.53 | AH34: 172.17.128.39 | AI34: OHB | AJ34: Windows 11 | AK34: 1 | AL34: 1 | AM34: XDC | AN34: 011/PO/HR&GA/GA/III/2025 | AO34: 45717 | AP34: 47908 | AQ34: WIDI | AR34: 0821-2106-7715 | AS34: PERCEPATAN MAR 2025 (14 UNIT)
AD35: gratifikasi@ikoito.co.id
B36: 31 | C36: FI-01062 | D36: ALL IN ONE | E36: GENERAL AFFAIR DIV | F36: IT LEGAL | G36: ADNI AGESTIAN VIRZY | H36: 1605033 | I36: 2025 | J36: =I36+6 -> 2031 | K36: ACTIVE | L36: OFFICER ADMIN | P36: ✓ | Y36: TIDAK | Z36: YA | AA36: YA | AB36: TIDAK | AC36: TIDAK | AD36: =VLOOKUP(C36,'[39]LAMPIRAN STANDAR'!$E$81:F$216,2,0) -> ir@ikoito.co.id | AE36: YA | AF36: PIK1COM136 | AG36: 172.17.12.65 | AH36: 172.17.128.40 | AI36: OHB | AJ36: Windows 11 | AK36: 1 | AL36: 1 | AM36: XDC | AN36: 012/PO/HR&GA/GA//III/2025 | AO36: 45689 | AP36: 47880 | AQ36: WIDI | AR36: 0821-2106-7715 | AS36: PERCEPATAN FEB 2025 (14 UNIT)
B37: 32 | C37: FI-01025 | D37: ALL IN ONE | E37: GENERAL AFFAIR DIV | F37: IT LEGAL | G37: YULYAYU KURNIAWATI | H37: 1210042 | I37: 2024 | J37: =I37+6 -> 2030 | K37: ACTIVE | L37: OFFICER ADMIN | P37: ✓ | Y37: TIDAK | Z37: YA | AA37: YA | AB37: TIDAK | AC37: TIDAK | AD37: =VLOOKUP(C37,'[39]LAMPIRAN STANDAR'!$E$81:F$216,2,0) -> compliance@ikoito.co.id | AE37: YA | AF37: PIK1COM119 | AG37: 172.17.12.41 | AH37: 172.17.128.45 | AI37: OHB | AJ37: Windows 11 | AK37: 1 | AL37: 1 | AM37: TETRANET | AN37: 039/PO/HR&GA/GA/X/2024 | AO37: 45597 | AP37: 47788 | AQ37: AFDAL | AR37: 0831-8760-3905 | AS37: DEPRE NOV 2024
B38: 33 | C38: FI-00987 | D38: ALL IN ONE | E38: GENERAL AFFAIR DIV | F38: IT LEGAL | G38: DEVITA DWI ANGGRAENI | H38: 2403012 | I38: 2024 | J38: =I38+6 -> 2030 | K38: ACTIVE | L38: OFFICER ADMIN | P38: ✓ | Y38: TIDAK | Z38: YA | AA38: YA | AB38: TIDAK | AC38: TIDAK | AD38: =VLOOKUP(C38,'[39]LAMPIRAN STANDAR'!$E$81:F$216,2,0) -> it.admin@ikoito.co.id | AE38: YA | AF38: PIK1COM098 | AG38: 172.17.12.59 | AH38: 172.17.128.35 | AI38: OHB | AJ38: Windows 11 | AK38: 1 | AL38: 1 | AM38: TETRANET | AN38: 034/PO/HR&GA/GA/VI/2024 | AO38: 45444 | AP38: 47635 | AQ38: AFDAL | AR38: 0831-8760-3905 | AS38: DEPRE JUNI 2024
B39: 34 | C39: FI-00969 | D39: WORKSTATION | E39: GENERAL AFFAIR DIV | F39: ITLEGAL | G39: MOHAMAD FAHMY IQBAL | H39: 1803070 | I39: 2024 | J39: =I39+6 -> 2030 | K39: ACTIVE | L39: TEKNIKAL | Q39: ✓ | Y39: TIDAK | Z39: YA | AA39: YA | AB39: TIDAK | AC39: TIDAK | AD39: fahmy.i@ikoito.co.id | AE39: YA | AF39: PIK1COM074 | AG39: 172.17.12.63 | AH39: 172.17.128.34 | AI39: OHB | AJ39: Windows 11 | AK39: 1 | AL39: 1 | AM39: SBTELECOM | AN39: 028/PO/HR/GA/GA/V/2024 | AO39: 45413 | AP39: 47604 | AQ39: ASTRI | AR39: 0811-1067-925 | AS39: DEPRE MEI 2024
B40: 35 | C40: FI-00783 | D40: ALL IN ONE | E40: GENERAL AFFAIR DIV | F40: IT LEGAL | G40: FADHI WINIATAMA | H40: 1309033 | I40: 2023 | J40: =I40+6 -> 2029 | K40: ACTIVE | L40: OFFICER ADMIN | P40: ✓ | Y40: TIDAK | Z40: YA | AA40: YA | AB40: TIDAK | AC40: TIDAK | AD40: =VLOOKUP(C40,'[39]LAMPIRAN STANDAR'!$E$81:F$216,2,0) -> fadhi.w@ikoito.co.id | AE40: YA | AF40: PIK1COM036 | AG40: 172.17.12.61 | AH40: 172.17.128.33 | AI40: OHB | AJ40: Windows 11 | AK40: 1 | AL40: 1 | AM40: DARUMA | AN40: 019/PO/HR&GA/GA/VIII/2023 | AO40: 45139 | AP40: 47331 | AQ40: RINDU | AR40: - | AS40: PC DEPRE AGUST 2023
B41: 36 | C41: FI-00744 | D41: ALL IN ONE | E41: GENERAL AFFAIR DIV | F41: IT LEGAL | G41: FARID BAGAS SAPUTRA | H41: 2512025 | I41: 2023 | J41: =I41+6 -> 2029 | K41: ACTIVE | L41: OFFICER ADMIN | P41: ✓ | Y41: TIDAK | Z41: YA | AA41: YA | AB41: TIDAK | AC41: TIDAK | AD41: =VLOOKUP(C41,'[39]LAMPIRAN STANDAR'!$E$81:F$216,2,0) -> it.support@ikoito.co.id | AE41: YA | AF41: PIK1COM012 | AG41: 172.17.12.62 | AH41: 172.17.128.36 | AI41: OHB | AJ41: Windows 11 | AK41: 1 | AL41: 1 | AM41: SBTELECOM | AN41: 027/PO/HR&GA/GA/IV/2022 | AO41: 44652 | AP41: 46844 | AQ41: ASTRI | AR41: 0811-1067-925 | AS41: PC DEPRE APRIL 2022
B42: 37 | C42: FI-00742 | D42: ALL IN ONE | E42: GENERAL AFFAIR DIV | F42: IT LEGAL | G42: MISBAHUL MUNIR | H42: 1701036 | I42: 2023 | J42: =I42+6 -> 2029 | K42: ACTIVE | L42: OFFICER ADMIN | P42: ✓ | Y42: TIDAK | Z42: YA | AA42: YA | AB42: TIDAK | AC42: TIDAK | AD42: =VLOOKUP(C42,'[39]LAMPIRAN STANDAR'!$E$81:F$216,2,0) -> misbahul.m@ikoito.co.id | AE42: YA | AF42: PIK1COM006 | AG42: 172.17.12.60 | AH42: 172.17.128.32 | AI42: OHB | AJ42: Windows 11 | AK42: 1 | AL42: 1 | AM42: SBTELECOM | AN42: 027/PO/HR&GA/GA/IV/2022 | AO42: 44652 | AP42: 46844 | AQ42: ASTRI | AR42: 0811-1067-925 | AS42: PC DEPRE APRIL 2022
B43: 38 | C43: FI-00721 | D43: LAPTOP | E43: GENERAL AFFAIR DIV | F43: IT LEGAL | G43: IR (SARI REZEKI) | H43: 1402011 | I43: 2022 | J43: =I43+6 -> 2028 | K43: ACTIVE | L43: LAPTOP MANAGERIAL | M43: ✓ | Y43: YA | Z43: TIDAK | AA43: TIDAK | AB43: TIDAK | AC43: TIDAK | AD43: - | AE43: TIDAK | AF43: PIKPC999 | AG43: - | AH43: DHCP | AI43: E3 | AJ43: Windows 11 | AK43: 1 | AL43: 1 | AM43: UNICORN | AN43: 014/PO/HR&GA/GA/XII/2022 | AO43: 44896 | AP43: 47088 | AQ43: AWENK | AR43: 0878-8284-8529 | AS43: LAPTOP ADD DES 2022
B44: 39 | C44: FI-00666 | D44: ALL IN ONE | E44: GENERAL AFFAIR DIV | F44: IT LEGAL | G44: DENI AGUSTA | H44: 2302029 | I44: 2022 | J44: =I44+6 -> 2028 | K44: ACTIVE | L44: OPERATOR | R44: ✓ | Y44: TIDAK | Z44: TIDAK | AA44: YA | AB44: TIDAK | AC44: TIDAK | AD44: - | AE44: YA | AF44: PIK1COM104 | AG44: 172.17.12.64 | AH44: 172.17.128.37 | AI44: OHB | AJ44: Windows 11 | AK44: 1 | AL44: 1 | AM44: SBTELECOM | AN44: 024/PO/HR&GA/GA/VI/2021 | AO44: 44348 | AP44: 46539 | AQ44: ASTRI | AR44: 0811-1067-925 | AS44: UPGRADE AIO JUNI 2021 (18 UNIT)
B45: 40 | C45: FI-00652 | D45: LAPTOP | E45: GENERAL AFFAIR DIV | F45: IT LEGAL | G45: AYUNG YUANSAH | H45: 1205001 | I45: 2021 | J45: =I45+6 -> 2027 | K45: ACTIVE | L45: LAPTOP MANAGERIAL | M45: ✓ | Y45: YA | Z45: TIDAK | AA45: TIDAK | AB45: TIDAK | AC45: TIDAK | AD45: ayung@ikoito.co.id | AE45: YA | AF45: PIKPC112 | AG45: 172.17.12.44 | AH45: DHCP | AI45: E3 | AJ45: Windows 11 | AK45: 1 | AL45: 1 | AM45: SBTELECOM | AN45: 023/PO/HR&GA/GA/ VI/2021 | AO45: 44348 | AP45: 46539 | AQ45: ASTRI | AR45: 0811-1067-925 | AS45: UPGRADE LAP MNGR JUNI 2021 (20 UNIT)
B46: 41 | C46: FI-00617 | D46: LAPTOP | E46: GENERAL AFFAIR DIV | F46: IT LEGAL | G46: KOITO M-09 (AYUNG) | H46: 1205001 | I46: 2021 | J46: =I46+6 -> 2027 | K46: ACTIVE | L46: LAPTOP MEETING | N46: ✓ | Y46: TIDAK | Z46: TIDAK | AA46: TIDAK | AB46: TIDAK | AC46: TIDAK | AD46: - | AE46: TIDAK | AF46: PIKLT007 | AG46: - | AH46: DHCP | AI46: E3 | AJ46: Windows 11 | AK46: 1 | AL46: 1 | AM46: CLARUS | AN46: 027/PO/HR&GA/GA/1/2021 | AO46: 44197 | AP46: 46388 | AQ46: LUSY | AR46: 0856-9576-1612 | AS46: LAPTOP ADD JAN 2021 | AT46: OHB | AU46: OHB | AV46: OHB | AW46: OHB
B47: 42 | C47: FI-00616 | D47: LAPTOP | E47: GENERAL AFFAIR DIV | F47: IT LEGAL | G47: KOITO M-08 (AYUNG) | H47: 1205001 | I47: 2021 | J47: =I47+6 -> 2027 | K47: ACTIVE | L47: LAPTOP MEETING | N47: ✓ | Y47: TIDAK | Z47: TIDAK | AA47: TIDAK | AB47: TIDAK | AC47: TIDAK | AD47: - | AE47: TIDAK | AF47: PIKLT006 | AG47: - | AH47: DHCP | AI47: E3 | AJ47: Windows 11 | AK47: 1 | AL47: 1 | AM47: CLARUS | AN47: 027/PO/HR&GA/GA/1/2021 | AO47: 44197 | AP47: 46388 | AQ47: LUSY | AR47: 0856-9576-1612 | AS47: LAPTOP ADD JAN 2021 | AT47: OHB | AU47: OHB | AV47: OHB | AW47: OHB
B48: 43 | C48: FI-01038 | D48: DESKTOP | E48: HSE DIV | F48: HSE | G48: VMS 1 (ARI PURNOMSIDI) | H48: 1702001 | I48: 2024 | J48: =I48+6 -> 2030 | K48: ACTIVE | L48: VMS | T48: ✓ | Y48: TIDAK | Z48: TIDAK | AA48: TIDAK | AB48: TIDAK | AC48: TIDAK | AD48: - | AE48: TIDAK | AF48: PIK1COM116 | AG48: 172.17.11.109 | AH48: 172.17.118.11 | AI48: - | AJ48: Windows 11 | AK48: 1 | AL48: 1 | AM48: LISNTAS | AN48: 047/PO/HR&GA/GA/XI/2024 | AO48: 45627 | AP48: 47818 | AQ48: TUSLAM | AR48: 0819-0475-2651 | AS48: DEPRE DES 2024 | AT48: OHB | AU48: OHB | AV48: OHB | AW48: OHB
B49: 44 | C49: FI-00963 | D49: ALL IN ONE | E49: HSE DIV | F49: HSE | G49: KARTA | H49: 1306003 | I49: 2024 | J49: =I49+6 -> 2030 | K49: ACTIVE | L49: OFFICER ADMIN | P49: ✓ | Y49: TIDAK | Z49: YA | AA49: YA | AB49: TIDAK | AC49: TIDAK | AD49: =VLOOKUP(C49,'[39]LAMPIRAN STANDAR'!$E$81:F$216,2,0) -> karta@ikoito.co.id | AE49: YA | AF49: PIK1COM055 | AG49: 172.17.12.83 | AH49: 172.17.128.46 | AI49: OHB | AJ49: Windows 11 | AK49: 1 | AL49: 1 | AM49: SBTELECOM | AN49: 064/PO/HR&GA/GA/I/2024 | AO49: 45292 | AP49: 47484 | AQ49: ASTRI | AR49: 0811-1067-925 | AS49: PC DEPRE JAN 2024
B50: 45 | C50: FI-01021 | D50: ALL IN ONE | E50: HSE DIV | F50: HSE | G50: HERYANSYAH | H50: 1704002 | I50: 2024 | J50: =I50+6 -> 2030 | K50: ACTIVE | L50: OFFICER ADMIN | P50: ✓ | Y50: TIDAK | Z50: YA | AA50: YA | AB50: TIDAK | AC50: TIDAK | AD50: =VLOOKUP(C50,'[39]LAMPIRAN STANDAR'!$E$81:F$216,2,0) -> enviro@ikoito.co.id | AE50: YA | AF50: PIK1COM105 | AG50: 172.17.12.67 | AH50: 172.17.128.44 | AI50: OHB | AJ50: Windows 11 | AK50: 1 | AL50: 1 | AM50: TETRANET | AN50: 069/PO/HR&GA/GA/IX/2024 | AO50: 45536 | AP50: 47727 | AQ50: AFDAL | AR50: 0831-8760-3905 | AS50: DEP SEP 2024
B51: 46 | C51: FI-01020 | D51: ALL IN ONE | E51: HSE DIV | F51: HSE | G51: KLINIK (ARI PURNOMOSIDI) | H51: 1702001 | I51: 2024 | J51: =I51+6 -> 2030 | K51: ACTIVE | L51: OFFICER ADMIN | P51: ✓ | Y51: TIDAK | Z51: YA | AA51: YA | AB51: TIDAK | AC51: TIDAK | AD51: =VLOOKUP(C51,'[39]LAMPIRAN STANDAR'!$E$81:F$216,2,0) -> health@ikoito.co.id | AE51: YA | AF51: PIK1COM108 | AG51: 172.17.11.25 | AH51: 172.17.118.12 | AI51: OHB | AJ51: Windows 11 | AK51: 1 | AL51: 1 | AM51: TETRANET | AN51: 069/PO/HR&GA/GA/IX/2024 | AO51: 45536 | AP51: 47727 | AQ51: AFDAL | AR51: 0831-8760-3905 | AS51: DEP SEP 2024
B52: 47 | C52: FI-00668 | D52: ALL IN ONE | E52: HSE DIV | F52: HSE | G52: AHMAD KAMALUDIN | H52: 1604048 | I52: 2022 | J52: =I52+6 -> 2028 | K52: ACTIVE | L52: OFFICER ADMIN | P52: ✓ | Y52: TIDAK | Z52: YA | AA52: YA | AB52: TIDAK | AC52: TIDAK | AD52: ahmad.k@ikoito.co.id | AE52: YA | AF52: PIKPC130 | AG52: 172.17.12.74 | AH52: 172.17.128.43 | AI52: OHB | AJ52: Windows 11 | AK52: 1 | AL52: 1 | AM52: SBTELECOM | AN52: 024/PO/HR&GA/GA/VI/2021 | AO52: 44348 | AP52: 46539 | AQ52: ASTRI | AR52: 0811-1067-925 | AS52: UPGRADE AIO JUNI 2021 (18 UNIT)
B53: 48 | C53: FI-00669 | D53: ALL IN ONE | E53: HSE DIV | F53: HSE | G53: SITI SUSILAWATI | H53: 1404041 | I53: 2022 | J53: =I53+6 -> 2028 | K53: ACTIVE | L53: OFFICER ADMIN | P53: ✓ | Y53: TIDAK | Z53: YA | AA53: YA | AB53: TIDAK | AC53: TIDAK | AD53: =VLOOKUP(C53,'[39]LAMPIRAN STANDAR'!$E$81:F$216,2,0) -> siti.s@ikoito.co.id | AE53: YA | AF53: PIKPC131 | AG53: 172.17.12.73 | AH53: 172.17.128.42 | AI53: OHB | AJ53: Windows 11 | AK53: 1 | AL53: 1 | AM53: SBTELECOM | AN53: 024/PO/HR&GA/GA/VI/2021 | AO53: 44348 | AP53: 46539 | AQ53: ASTRI | AR53: 0811-1067-925 | AS53: UPGRADE AIO JUNI 2021 (18 UNIT)
B54: 49 | C54: FI-00705 | D54: ALL IN ONE | E54: HSE DIV | F54: HSE | G54: AGUNG IKSAN NUGRAHA | H54: 1708001 | I54: 2022 | J54: =I54+6 -> 2028 | K54: ACTIVE | L54: OFFICER ADMIN | P54: ✓ | Y54: TIDAK | Z54: YA | AA54: YA | AB54: TIDAK | AC54: TIDAK | AD54: =VLOOKUP(C54,'[39]LAMPIRAN STANDAR'!$E$81:F$216,2,0) -> safety@ikoito.co.id | AE54: YA | AF54: PIKPC167 | AG54: 172.17.12.42 | AH54: 172.17.128.47 | AI54: OHB | AJ54: Windows 11 | AK54: 1 | AL54: 1 | AM54: CLARUS | AN54: 006/PO/HR&GA/GA/VIII/2022 | AO54: 44774 | AP54: 46966 | AQ54: LUSY | AR54: 0856-9576-1612 | AS54: PC DEPRE AGUST 2022
B55: 50 | C55: BELUM AKUISISI | D55: DESKTOP | E55: HSE DIV | F55: HSE | G55: MONITOR 1 POSKO (SITI SUSILAWATI) | H55: 1702001 | I55: 2025 | J55: =I55+6 -> 2031 | K55: ACTIVE | L55: CCTV VIEW | U55: ✓ | Y55: TIDAK | Z55: TIDAK | AA55: TIDAK | AB55: TIDAK | AC55: TIDAK | AD55: - | AE55: TIDAK | AF55: PIK1COM169 | AG55: 172.17.101.201 | AI55: - | AJ55: Windows 11 | AK55: 1 | AL55: 1 | AM55: SBTELECOM | AN55: 007/PO/HR&GA/GA/X/2025 | AO55: 45931 | AP55: 48122 | AQ55: ASTRI | AR55: 0811-1067-925 | AS55: DEPRE OKT 2025
B56: 51 | C56: BELUM AKUISISI | D56: LAPTOP | E56: HSE DIV | F56: HSE | G56: ARI PURNOMOSIDI | H56: 1702001 | I56: 2025 | J56: =I56+6 -> 2031 | K56: ACTIVE | L56: LAPTOP MANAGERIAL | M56: ✓ | Y56: YA | Z56: TIDAK | AA56: TIDAK | AB56: TIDAK | AC56: TIDAK | AD56: ari.p@ikoito.co.id | AE56: YA | AF56: PIK1COM170 | AG56: 172.17.12.38 | AH56: DHCP | AI56: E3 | AJ56: Windows 11 | AK56: 1 | AL56: 1 | AM56: SBTELECOM | AN56: 007/PO/HR&GA/GA/X/2025 | AO56: 45931 | AP56: 48122 | AQ56: ASTRI | AR56: 0811-1067-925 | AS56: DEPRE OKT 2025
B57: 52 | C57: FI-01039 | D57: ALL IN ONE | E57: HSE DIV | F57: HSE | G57: SAHRONI | H57: 1110033 | I57: 2025 | J57: =I57+6 -> 2031 | K57: ACTIVE | L57: OFFICER ADMIN | P57: ✓ | Y57: TIDAK | Z57: YA | AA57: YA | AB57: TIDAK | AC57: TIDAK | AD57: hse@ikoito.co.id | AE57: YA | AF57: PIK1COM189 | AG57: 172.17.12.81 | AH57: 172.17.128.48 | AI57: OHB | AJ57: Windows 11 | AK57: 1 | AL57: 1 | AM57: LINTAS | AN57: 052/PO/HR&GA/GA/XI/2024 | AO57: 45597 | AP57: 47788 | AQ57: TUSLAM | AR57: 0819-0475-2651 | AS57: DEPRE DES 2025
B58: 53 | C58: FI-01075 | D58: ALL IN ONE | E58: HSE DIV | F58: HSE | G58: IDHAM RAKHMADI | H58: 1611024 | I58: 2025 | J58: =I58+6 -> 2031 | K58: ACTIVE | L58: OFFICER ADMIN | P58: ✓ | Y58: TIDAK | Z58: YA | AA58: YA | AB58: TIDAK | AC58: TIDAK | AD58: =VLOOKUP(C58,'[39]LAMPIRAN STANDAR'!$E$81:F$216,2,0) -> hse@ikoito.co.id | AE58: YA | AF58: PIK1COM130 | AG58: 172.17.12.82 | AH58: 172.17.128.49 | AI58: OHB | AJ58: Windows 11 | AK58: 1 | AL58: 1 | AM58: XDC | AN58: 013/PO/HR&GA/GA/GA/III/2025 | AO58: 45658 | AP58: 47849 | AQ58: WIDI | AR58: 0821-2106-7715 | AS58: PERCEPATAN JAN 2025 (14 UNIT)
B59: 54 | C59: FI-01061 | D59: DESKTOP | E59: HSE DIV | F59: HSE | G59: MONITOR 2 POSKO (SITI SUSILAWATI) | H59: 1702001 | I59: 2025 | J59: =I59+6 -> 2031 | K59: ACTIVE | L59: CCTV VIEW | U59: ✓ | Y59: TIDAK | Z59: TIDAK | AA59: TIDAK | AB59: TIDAK | AC59: TIDAK | AD59: - | AE59: TIDAK | AF59: PIK1COM142 | AG59: 172.17.101.202 | AI59: - | AJ59: Windows 11 | AK59: 1 | AL59: 1 | AM59: XDC | AN59: 012/PO/HR&GA/GA//III/2025 | AO59: 45689 | AP59: 47880 | AQ59: WIDI | AR59: 0821-2106-7715 | AS59: PERCEPATAN FEB 2025 (14 UNIT)
B60: 55 | C60: FI-01066 | D60: DESKTOP | E60: HSE DIV | F60: HSE | G60: VMS 2 (ARI PURNOMOSIDI) | H60: 1702001 | I60: 2025 | J60: =I60+6 -> 2031 | K60: ACTIVE | L60: VMS | T60: ✓ | Y60: TIDAK | Z60: TIDAK | AA60: TIDAK | AB60: TIDAK | AC60: TIDAK | AD60: - | AE60: TIDAK | AF60: PIK1COM144 | AG60: 172.17.101.210 | AI60: - | AJ60: Windows 11 | AK60: 1 | AL60: 1 | AM60: XDC | AN60: 010/PO/HR&GA/GA/III/2025 | AO60: 45689 | AP60: 47880 | AQ60: WIDI | AR60: 0821-2106-7715 | AS60: DEPRE FEB 2025
B61: 56 | C61: FI-01124 | D61: ALL IN ONE | E61: HSE DIV | F61: HSE | G61: DIANNE CHRISTIN SIANTURI | H61: 2509013 | I61: 2025 | J61: =I61+6 -> 2031 | K61: ACTIVE | L61: OFFICER ADMIN | P61: ✓ | Y61: TIDAK | Z61: YA | AA61: YA | AB61: TIDAK | AC61: TIDAK | AD61: enviro@ikoito.co.id | AE61: YA | AF61: PIK1COM163 | AG61: 172.17.12.72 | AH61: 172.17.128.50 | AI61: OHB | AJ61: Windows 11 | AK61: 1 | AL61: 1 | AM61: SBTELECOM | AN61: 015/PO/HR&GA/GA/VIII/2025 | AO61: 45870 | AP61: 48061 | AQ61: ASTRI | AR61: 0811-1067-925 | AS61: DEPRE AGUST 2025
B62: 57 | C62: FI-00764 | D62: LAPTOP | E62: INJECTION MOLD DIV | F62: INJECTION MOLD DIV | G62: HIROYOSHI OHI | H62: 2405001 | I62: 2023 | J62: =I62+6 -> 2029 | K62: ACTIVE | L62: LAPTOP MANAGERIAL | M62: ✓ | Y62: YA | Z62: TIDAK | AA62: TIDAK | AB62: YA | AC62: TIDAK | AD62: h-ooi@ikoito.co.id | AE62: YA | AF62: PIK1COM028 | AG62: 172.17.11.26 | AH62: DHCP | AI62: E3 | AJ62: Windows 11 | AK62: 1 | AL62: 1 | AM62: CLARUS | AN62: 059/PO/HR&GA/GA/VI/2023 | AO62: 45078 | AP62: 47270 | AQ62: LUSY | AR62: 0856-9576-1612 | AS62: PC DEPRE JUNI 2023
B63: 58 | C63: FI-00653 | D63: LAPTOP | E63: INJECTION MOLD DIV | F63: INJECTION MOLD DIV | G63: EDY PRASETYA | H63: 1011006 | I63: 2021 | J63: =I63+6 -> 2027 | K63: ACTIVE | L63: LAPTOP MANAGERIAL | M63: ✓ | Y63: YA | Z63: TIDAK | AA63: TIDAK | AB63: YA | AC63: TIDAK | AD63: thomas.e.p@ikoito.co.id | AE63: YA | AF63: PIKPC120 | AG63: 172.17.12.150 | AH63: DHCP | AI63: E3 | AJ63: Windows 11 | AK63: 1 | AL63: 1 | AM63: SBTELECOM | AN63: 023/PO/HR&GA/GA/ VI/2021 | AO63: 44348 | AP63: 46539 | AQ63: ASTRI | AR63: 0811-1067-925 | AS63: UPGRADE LAP MNGR JUNI 2021 (20 UNIT)
B64: 59 | C64: FI-01080 | D64: WORKSTATION | E64: INJECTION MOLD DIV | F64: MOLD ENG | G64: ARIP DWI JAYA SINA | H64: 1405013 | I64: 2025 | J64: =I64+6 -> 2031 | K64: ACTIVE | L64: TEKNIKAL | Q64: ✓ | Y64: TIDAK | Z64: YA | AA64: YA | AB64: TIDAK | AC64: TIDAK | AD64: mold_eng@ikoito.co.id | AE64: YA | AF64: PIK1COM145 | AG64: 172.17.12.153 | AH64: 172.17.128.53 | AI64: OHB | AJ64: Windows 11 | AK64: 1 | AL64: 1 | AM64: XDC | AN64: 014/PO/HR&GA/GA/III/2025 | AO64: 45717 | AP64: 47908 | AQ64: WIDI | AR64: 0821-2106-7715 | AS64: DEPRE MAR 2025
B65: 60 | C65: FI-00985 | D65: ALL IN ONE | E65: INJECTION MOLD DIV | F65: MOLD ENG | G65: RAHMAWATI HARDIAN PRATIWI | H65: 1904001 | I65: 2025 | J65: =I65+6 -> 2031 | K65: ACTIVE | L65: OFFICER ADMIN | P65: ✓ | Y65: TIDAK | Z65: YA | AA65: YA | AB65: TIDAK | AC65: TIDAK | AD65: =VLOOKUP(C65,'[39]LAMPIRAN STANDAR'!$E$81:F$216,2,0) -> ahmad.k@ikoito.co.id | AE65: YA | AF65: PIK1COM123 | AG65: 172.17.12.158 | AH65: 172.17.128.54 | AI65: OHB | AJ65: Windows 11 | AK65: 1 | AL65: 1 | AM65: TETRANET | AN65: 034/PO/HR&GA/GA/VI/2024 | AO65: 45444 | AP65: 47635 | AQ65: AFDAL | AR65: 0831-8760-3905 | AS65: DEPRE JUNI 2024
B66: 61 | C66: FI-01015 | D66: WORKSTATION | E66: INJECTION MOLD DIV | F66: MOLD ENG | G66: ANDRE MARTHA SAPUTRA | H66: 1511009 | I66: 2024 | J66: =I66+6 -> 2030 | K66: ACTIVE | L66: TEKNIKAL | Q66: ✓ | Y66: TIDAK | Z66: YA | AA66: YA | AB66: TIDAK | AC66: TIDAK | AD66: mold_eng3@ikoito.co.id | AE66: YA | AF66: PIK1COM118 | AG66: 172.17.12.155 | AH66: 172.17.128.55 | AI66: OHB | AJ66: Windows 11 | AK66: 1 | AL66: 1 | AM66: TETRANET | AN66: 008/PO/HR&GA/GA/X/2024 | AO66: 45566 | AP66: 47757 | AQ66: AFDAL | AR66: 0831-8760-3905 | AS66: ADD OKT 2024
B67: 62 | C67: FI-00770 | D67: LAPTOP | E67: INJECTION MOLD DIV | F67: MOLD ENG | G67: KRISTANTO DWI SAPUTRA | H67: 1804001 | I67: 2023 | J67: =I67+6 -> 2029 | K67: ACTIVE | L67: LAPTOP MANAGERIAL | M67: ✓ | Y67: YA | Z67: TIDAK | AA67: TIDAK | AB67: YA | AC67: TIDAK | AD67: kristanto.d@ikoito.co.id | AE67: YA | AF67: PIK1COM026 | AG67: 172.17.12.152 | AH67: DHCP | AI67: E3 | AJ67: Windows 11 | AK67: 1 | AL67: 1 | AM67: CLARUS | AN67: 058/PO/HR&GA/GA/VI/2023 | AO67: 45108 | AP67: 47300 | AQ67: LUSY | AR67: 0856-9576-1612 | AS67: LAPTOP ADD JULI 2023 (5 UNIT)
B68: 63 | C68: FI-00590 | D68: WORKSTATION | E68: INJECTION MOLD DIV | F68: MOLD ENG | G68: CAMTOOL CNC (ALKINDI) | H68: 1703001 | I68: 2021 | J68: =I68+6 -> 2027 | K68: ACTIVE | L68: TEKNIKAL | Q68: ✓ | Y68: TIDAK | Z68: TIDAK | AA68: YA | AB68: TIDAK | AC68: TIDAK | AD68: - | AE68: TIDAK | AF68: MEDRAWPC002 | AG68: 172.17.20.132 | AH68: 172.17.218.4 | AI68: OHB | AJ68: Windows 11 | AK68: 1 | AL68: 1 | AM68: CLARUS | AN68: 025/PO/HR&GA/GA/X/2020 | AO68: 44105 | AP68: 46296 | AQ68: LUSY | AR68: 0856-9576-1612 | AS68: PC DEPRE OKT 2020
B69: 64 | C69: FI-00591 | D69: WORKSTATION | E69: INJECTION MOLD DIV | F69: MOLD ENG | G69: MOLDFLOW (ISMAIL MARJUKI) | H69: 1801027 | I69: 2021 | J69: =I69+6 -> 2027 | K69: ACTIVE | L69: TEKNIKAL | Q69: ✓ | Y69: TIDAK | Z69: YA | AA69: YA | AB69: TIDAK | AC69: TIDAK | AD69: ismail.m@ikoito.co.id | AE69: YA | AF69: PIK1COM011 | AG69: 172.17.12.163 | AH69: 172.17.128.56 | AI69: OHB | AJ69: Windows 11 | AK69: 1 | AL69: 1 | AM69: CLARUS | AN69: 025/PO/HR&GA/GA/X/2020 | AO69: 44105 | AP69: 46296 | AQ69: LUSY | AR69: 0856-9576-1612 | AS69: PC DEPRE OKT 2020
B70: 65 | C70: FI-00952 | D70: WORKSTATION | E70: INJECTION MOLD DIV | F70: MOLD MAKING | G70: REZA ADITYA PERMADI | H70: 2412013 | I70: 2024 | J70: =I70+6 -> 2030 | K70: ACTIVE | L70: TEKNIKAL | Q70: ✓ | Y70: TIDAK | Z70: TIDAK | AA70: YA | AB70: TIDAK | AC70: TIDAK | AD70: - | AE70: YA | AF70: PIK1COM076 | AG70: 172.17.20.135 | AH70: 172.17.218.5 | AI70: OHB | AJ70: Windows 11 | AK70: 1 | AL70: 1 | AM70: CLARUS | AN70: 021/PO/HR&GA/GA/XII/2023 | AO70: 45261 | AP70: 47453 | AQ70: LUSY | AR70: 0856-9576-1612 | AS70: PC ADD DES 2023
B71: 66 | C71: FI-01014 | D71: WORKSTATION | E71: INJECTION MOLD DIV | F71: MOLD MAKING | G71: DICKY ZULFIKAR | H71: 1206004 | I71: 2024 | J71: =I71+6 -> 2030 | K71: ACTIVE | L71: TEKNIKAL | Q71: ✓ | Y71: TIDAK | Z71: YA | AA71: YA | AB71: TIDAK | AC71: TIDAK | AD71: dicky.z@ikoito.co.id | AE71: YA | AF71: PIK1COM113 | AG71: 172.17.20.131 | AH71: 172.17.218.2 | AI71: OHB | AJ71: Windows 11 | AK71: 1 | AL71: 1 | AM71: TETRANET | AN71: 038/PO/HR&GA/GA/X/2024 | AO71: 45597 | AP71: 47788 | AQ71: AFDAL | AR71: 0831-8760-3905 | AS71: ADD NOV 2024
B72: 67 | C72: FI-00743 | D72: ALL IN ONE | E72: INJECTION MOLD DIV | F72: MOLD MAKING | G72: CNC (TOMMY) | H72: 1406005 | I72: 2023 | J72: =I72+6 -> 2029 | K72: ACTIVE | L72: OFFICER ADMIN | P72: ✓ | Y72: TIDAK | Z72: YA | AA72: YA | AB72: TIDAK | AC72: TIDAK | AD72: =VLOOKUP(C72,'[39]LAMPIRAN STANDAR'!$E$81:F$216,2,0) -> cnc@ikoito.co.id | AE72: YA | AF72: PIK1COM008 | AG72: 172.17.20.130 | AH72: 172.17.218.6 | AI72: OHB | AJ72: Windows 11 | AK72: 1 | AL72: 1 | AM72: SBTELECOM | AN72: 027/PO/HR&GA/GA/IV/2022 | AO72: 44652 | AP72: 46844 | AQ72: ASTRI | AR72: 0811-1067-925 | AS72: PC DEPRE APR 2022
B73: 68 | C73: FI-00788 | D73: ALL IN ONE | E73: INJECTION MOLD DIV | F73: MOLD MAKING | G73: AHMAD BAHTIAR | H73: 1312002 | I73: 2023 | J73: =I73+6 -> 2029 | K73: ACTIVE | L73: OFFICER ADMIN | P73: ✓ | Y73: TIDAK | Z73: YA | AA73: YA | AB73: TIDAK | AC73: TIDAK | AD73: =VLOOKUP(C73,'[39]LAMPIRAN STANDAR'!$E$81:F$216,2,0) -> a.bahtiar@ikoito.co.id | AE73: YA | AF73: PIK1COM039 | AG73: 172.17.20.136 | AH73: 172.17.218.3 | AI73: OHB | AJ73: Windows 11 | AK73: 1 | AL73: 1 | AM73: DARUMA | AN73: 012/PO/HR&GA/GA/IX/2023 | AO73: 45200 | AP73: 47392 | AQ73: RINDU | AR73: - | AS73: PC DEPRE OKT 2023
J74: =I74+6 -> 6 | AD74: deri.m@ikoito.co.id
B75: 69 | C75: FI-00612 | D75: WORKSTATION | E75: INJECTION MOLD DIV | F75: MOLD MAKING | G75: CATIA 2 (DADI HERIYANTO) | H75: 1709001 | I75: 2021 | J75: =I75+6 -> 2027 | K75: ACTIVE | L75: TEKNIKAL | Q75: ✓ | Y75: TIDAK | Z75: YA | AA75: YA | AB75: TIDAK | AC75: TIDAK | AD75: dadi.h@ikoito.co.id | AE75: YA | AF75: PIKPC156 | AG75: 172.17.20.133 | AH75: 172.17.218.7 | AI75: OHB | AJ75: Windows 11 | AK75: 1 | AL75: 1 | AM75: CLARUS | AN75: 021/PO/HR&GA/GA/ XII/2020 | AO75: 44166 | AP75: 46357 | AQ75: LUSY | AR75: 0856-9576-1612 | AS75: PC DEPRE DES 2020
B76: 70 | C76: FI-00541 | D76: WORKSTATION | E76: INJECTION MOLD DIV | F76: MOLD MAKING | G76: MOLD DRAW PC (REZA ADITYA PERMADI) | H76: 2412013 | I76: 43826 | J76: =EDATE(I76,72) -> 46018 | K76: Non Active | L76: TEKNIKAL | Q76: ✓ | Y76: TIDAK | Z76: TIDAK | AA76: YA | AB76: TIDAK | AC76: TIDAK | AD76: - | AE76: TIDAK | AF76: MEDRAWPC001 | AG76: 172.17.20.134 | AH76: 172.17.218.8 | AI76: OHB | AJ76: Windows 10 | AK76: 1 | AL76: 1 | AM76: CSI | AN76: 012/PO/HR&GA/GA/IX/2019 | AO76: 43709 | AP76: 45901 | AQ76: IBRAIM | AR76: 0812-8097-4409 | AS76: PC DEPRE SEP 2019
B77: 71 | C77: FI-00507 | D77: ALL IN ONE | E77: INJECTION MOLD DIV | F77: MOLD MAKING | G77: ANDINI SEPTOWATI | H77: 1506019 | I77: 43732 | J77: =EDATE(I77,72) -> 45924 | K77: ACTIVE | L77: OFFICER ADMIN | P77: ✓ | Y77: TIDAK | Z77: YA | AA77: YA | AB77: TIDAK | AC77: TIDAK | AD77: =VLOOKUP(C77,'[39]LAMPIRAN STANDAR'!$E$81:F$216,2,0) -> moldmaking.adm@ikoito.co.id | AE77: YA | AF77: MEPC010 | AG77: 172.17.12.157 | AH77: 172.17.128.57 | AI77: PP16 | AJ77: Windows 11 | AK77: 1 | AL77: 1 | AM77: SBTELECOM | AN77: - | AO77: 46054 | AP77: 48245 | AQ77: ASTRI | AS77: PC DEPRE DES 2025
B78: 72 | C78: FI-01035 | D78: WORKSTATION | E78: INJECTION MOLD DIV | F78: MOLD MTC | G78: DIDI PERIYANTO 2 | H78: 1105005 | I78: 2024 | J78: =I78+6 -> 2030 | K78: ACTIVE | L78: TEKNIKAL | Q78: ✓ | Y78: TIDAK | Z78: YA | AA78: YA | AB78: TIDAK | AC78: TIDAK | AD78: didi.p@ikoito.co.id | AE78: YA | AF78: PIK1COM188 | AG78: 172.17.11.93 | AH78: 172.17.118.18 | AI78: OHB | AJ78: Windows 11 | AK78: 1 | AL78: 1 | AM78: LINTAS | AN78: 053/PO/HR&GA/GA/XI/2024 | AO78: 45627 | AP78: 47818 | AQ78: TUSLAM | AR78: 0819-0475-2651 | AS78: ADD DES 2024
B79: 73 | C79: FI-00959 | D79: ALL IN ONE | E79: INJECTION MOLD DIV | F79: MOLD MTC | G79: DIDI PERIYANTO | H79: 1105005 | I79: 2024 | J79: =I79+6 -> 2030 | K79: ACTIVE | L79: OFFICER ADMIN | P79: ✓ | Y79: TIDAK | Z79: YA | AA79: YA | AB79: TIDAK | AC79: TIDAK | AD79: =VLOOKUP(C79,'[39]LAMPIRAN STANDAR'!$E$81:F$216,2,0) -> didi.p@ikoito.co.id | AE79: YA | AF79: PIK1COM054 | AG79: 172.17.11.76 | AH79: 172.17.118.17 | AI79: OHB | AJ79: Windows 11 | AK79: 1 | AL79: 1 | AM79: SBTELECOM | AN79: 063/PO/HR&GA/GA/I/2024 | AO79: 45292 | AP79: 47484 | AQ79: ASTRI | AR79: 0811-1067-925 | AS79: PC DEPRE JAN 2024
B80: 74 | C80: FI-01040 | D80: ALL IN ONE | E80: INJECTION MOLD DIV | F80: MOLD MTC | G80: SAMSURIZAL | H80: 1011023 | I80: 2024 | J80: =I80+6 -> 2030 | K80: ACTIVE | L80: OFFICER ADMIN | P80: ✓ | Y80: TIDAK | Z80: YA | AA80: YA | AB80: TIDAK | AC80: TIDAK | AD80: =VLOOKUP(C80,'[39]LAMPIRAN STANDAR'!$E$81:F$216,2,0) -> samsurizal@ikoito.co.id | AE80: YA | AF80: PIK1COM122 | AG80: 172.17.11.86 | AH80: 172.17.118.16 | AI80: OHB | AJ80: Windows 11 | AK80: 1 | AL80: 1 | AM80: LINTAS | AN80: 052/PO/HR&GA/GA/XI/2024 | AO80: 45597 | AP80: 47788 | AQ80: TUSLAM | AR80: 0819-0475-2651 | AS80: DEPRE DES 2025
B81: 75 | C81: FI-00975 | D81: LAPTOP | E81: KPS | F81: KPS | G81: SYAIFUL RAMADHAN | H81: 1302030 | I81: 2024 | J81: =I81+6 -> 2030 | K81: ACTIVE | L81: LAPTOP MANAGERIAL | M81: ✓ | Y81: YA | Z81: TIDAK | AA81: TIDAK | AB81: YA | AC81: TIDAK | AD81: kps.kaizen@ikoito.co.id | AE81: YA | AF81: PIK1COM073 | AG81: 172.17.11.51 | AH81: DHCP | AI81: E3 | AJ81: Windows 11 | AK81: 1 | AL81: 1 | AM81: SBTELECOM | AN81: 031/PO/HR&GA/GA/IV/2024 | AO81: 45383 | AP81: 47574 | AQ81: ASTRI | AR81: 0811-1067-925 | AS81: DEPRE APR 2024
B82: 76 | C82: FI-00672 | D82: ALL IN ONE | E82: KPS | F82: KPS | G82: AJI SUSANTO | H82: 1406004 | I82: 2022 | J82: =I82+6 -> 2028 | K82: ACTIVE | L82: OFFICER ADMIN | P82: ✓ | Y82: TIDAK | Z82: YA | AA82: YA | AB82: TIDAK | AC82: TIDAK | AD82: =VLOOKUP(C82,'[39]LAMPIRAN STANDAR'!$E$81:F$216,2,0) -> aji.s@ikoito.co.id | AE82: YA | AF82: PIKPC134 | AG82: 172.17.11.50 | AH82: 172.17.118.22 | AI82: OHB | AJ82: Windows 11 | AK82: 1 | AL82: 1 | AM82: SBTELECOM | AN82: 024/PO/HR&GA/GA/VI/2021 | AO82: 44348 | AP82: 46539 | AQ82: ASTRI | AR82: 0811-1067-925 | AS82: UPGRADE AIO JUNI 2021 (18 UNIT)
B83: 77 | C83: FI-00695 | D83: ALL IN ONE | E83: KPS | F83: KPS | G83: DUDI SUGITO | H83: 1108007 | I83: 2022 | J83: =I83+6 -> 2028 | K83: ACTIVE | L83: OPERATOR | R83: ✓ | Y83: TIDAK | Z83: TIDAK | AA83: YA | AB83: TIDAK | AC83: TIDAK | AD83: - | AE83: TIDAK | AF83: PIKPC154 | AG83: 172.17.11.87 | AH83: 172.17.118.24 | AI83: OHB | AJ83: Windows 11 | AK83: 1 | AL83: 1 | AM83: SBTELECOM | AN83: 039/PO/HR&GA/GA/IV/2022 | AO83: 44652 | AP83: 46844 | AQ83: ASTRI | AR83: 0811-1067-925 | AS83: PC DEPRE APRIL 2022
B84: 78 | C84: FI-00649 | D84: LAPTOP | E84: KPS | F84: KPS | G84: DADANG CAHYADI | H84: 1508002 | I84: 2021 | J84: =I84+6 -> 2027 | K84: ACTIVE | L84: LAPTOP MANAGERIAL | M84: ✓ | Y84: YA | Z84: TIDAK | AA84: TIDAK | AB84: TIDAK | AC84: TIDAK | AD84: dadang.c@ikoito.co.id | AE84: YA | AF84: PIKPC104 | AG84: 172.17.11.57 | AH84: DHCP | AI84: E3 | AJ84: Windows 11 | AK84: 1 | AL84: 1 | AM84: SBTELECOM | AN84: 023/PO/HR&GA/GA/ VI/2021 | AO84: 44348 | AP84: 46539 | AQ84: ASTRI | AR84: 0811-1067-925 | AS84: UPGRADE LAP MNGR JUNI 2021 (20 UNIT)
B85: 79 | C85: FI-00526 | D85: ALL IN ONE | E85: KPS | F85: KPS | G85: EX: DENIS | H85: - | I85: 43796 | J85: =EDATE(I85,72) -> 45988 | K85: ACTIVE | L85: OPERATOR | R85: ✓ | Y85: TIDAK | Z85: TIDAK | AA85: YA | AB85: TIDAK | AC85: TIDAK | AD85: - | AE85: TIDAK | AF85: KPSPC001 | AG85: 172.17.11.53 | AH85: 172.17.118.25 | AI85: PP16 | AJ85: Windows 11 | AK85: 1 | AL85: 1 | AM85: SBTELECOM | AN85: - | AO85: 46054 | AP85: 48245 | AQ85: ASTRI | AS85: PC DEPRE DES 2025
B86: 80 | C86: FI-00536 | D86: MINI PC | E86: KPS | F86: KPS | G86: SYAIFUL RAMADHAN | H86: 1302030 | I86: 43826 | J86: =EDATE(I86,72) -> 46018 | K86: ACTIVE | L86: OFFICER ADMIN | P86: ✓ | Y86: TIDAK | Z86: YA | AA86: YA | AB86: TIDAK | AC86: TIDAK | AD86: kps.kaizen@ikoito.co.id | AE86: YA | AF86: KPSPC002 | AG86: 172.17.11.52 | AH86: 172.17.118.23 | AI86: PP16 | AJ86: Windows 11 | AK86: 1 | AL86: 1 | AM86: CLARUS | AN86: 010/PO/HR&GA/GA/VIII/2019 | AO86: 43678 | AP86: 45870 | AQ86: LUSY | AR86: 0856-9576-1612 | AS86: PC DEPRE AGUST 2019
B87: 81 | C87: FI-01095 | D87: LAPTOP | E87: KPS | F87: KPS | G87: LAPTOP MEETING JISUKEN 1 (DADANG) | H87: 1508002 | I87: 2025 | J87: =I87+6 -> 2031 | K87: ACTIVE | L87: LAPTOP MANAGERIAL | M87: ✓ | Y87: TIDAK | Z87: TIDAK | AA87: TIDAK | AB87: YA | AC87: TIDAK | AD87: kps.kaizen@ikoito.co.id | AE87: YA | AF87: PIK1COM151 | AG87: - | AH87: DHCP | AI87: E3 | AJ87: Windows 11 | AK87: 1 | AL87: 1 | AM87: SBTELECOM | AN87: 034/PO/HR&GA/GA/VI/2025 | AO87: 45748 | AP87: 47939 | AQ87: ASTRI | AR87: 0811-1067-925 | AS87: DEPRE APR 2025
B88: 82 | C88: BELUM AKUISISI | D88: LAPTOP | E88: MARKETING DIV | F88: CONTROL | G88: ARIS HERYANTO | H88: 1210002 | I88: 2025 | J88: =I88+6 -> 2031 | K88: ACTIVE | L88: LAPTOP MANAGERIAL | M88: ✓ | Y88: YA | Z88: TIDAK | AA88: TIDAK | AB88: YA | AC88: TIDAK | AD88: aris@ikoito.co.id | AE88: YA | AF88: PIK1COM171 | AG88: 172.17.12.88 | AH88: 172.17.128.63 | AI88: E3 | AJ88: Windows 11 | AK88: 1 | AL88: 1 | AM88: SBTELECOM | AN88: 007/PO/HR&GA/GA/X/2025 | AO88: 45931 | AP88: 48122 | AQ88: ASTRI | AR88: 0811-1067-925 | AS88: DEPRE OKT 2025
B89: 83 | C89: FI-00988 | D89: ALL IN ONE | E89: MARKETING DIV | F89: CONTROL | G89: SITI FAJAR SEPTIA | H89: 2501007 | I89: 2024 | J89: =I89+6 -> 2030 | K89: ACTIVE | L89: OFFICER ADMIN | P89: ✓ | Y89: TIDAK | Z89: YA | AA89: YA | AB89: TIDAK | AC89: TIDAK | AD89: marketing@ikoito.co.id | AE89: YA | AF89: PIK1COM090 | AG89: 172.17.12.107 | AH89: 172.17.128.64 | AI89: OHB | AJ89: Windows 11 | AK89: 1 | AL89: 1 | AM89: TETRANET | AN89: 033/PO/HR&GA/GA/VI/2024 | AO89: 45444 | AP89: 47635 | AQ89: AFDAL | AR89: 0831-8760-3905 | AS89: ADD JUNI 2024
B90: 84 | C90: FI-00761 | D90: ALL IN ONE | E90: MARKETING DIV | F90: CONTROL | G90: DINDA CAHYA RUBIANTI | H90: 2305015 | I90: 2023 | J90: =I90+6 -> 2029 | K90: ACTIVE | L90: OFFICER ADMIN | P90: ✓ | Y90: TIDAK | Z90: YA | AA90: YA | AB90: TIDAK | AC90: TIDAK | AD90: =VLOOKUP(C90,'[39]LAMPIRAN STANDAR'!$E$81:F$216,2,0) -> marketing@ikoito.co.id | AE90: YA | AF90: PIK1COM018 | AG90: 172.17.12.112 | AH90: 172.17.128.65 | AI90: OHB | AJ90: Windows 11 | AK90: 1 | AL90: 1 | AM90: DARUMA | AN90: 049/PO/HR&GA/GA/V/2023 | AO90: 45047 | AP90: 47239 | AQ90: RINDU | AR90: - | AS90: PC DEPRE MEI 2023
B91: 85 | C91: FI-00706 | D91: ALL IN ONE | E91: MARKETING DIV | F91: CONTROL | G91: SIFA NURJANAH | H91: 2507006 | I91: 2022 | J91: =I91+6 -> 2028 | K91: ACTIVE | L91: OFFICER ADMIN | P91: ✓ | Y91: TIDAK | Z91: YA | AA91: YA | AB91: TIDAK | AC91: TIDAK | AD91: marketing@ikoito.co.id | AE91: YA | AF91: PIKPC171 | AG91: 172.17.12.104 | AH91: 172.17.128.66 | AI91: OHB | AJ91: Windows 11 | AK91: 1 | AL91: 1 | AM91: CLARUS | AN91: 019/PO/HR&GA/GA/ IX/2022 | AO91: 44805 | AP91: 46997 | AQ91: LUSY | AR91: 0856-9576-1612 | AS91: PC DEPRE SEP 2022
B92: 86 | C92: FI-00719 | D92: ALL IN ONE | E92: MARKETING DIV | F92: CONTROL | G92: DINI DURROTUL AENI | H92: 2108002 | I92: 2022 | J92: =I92+6 -> 2028 | K92: ACTIVE | L92: OFFICER ADMIN | P92: ✓ | Y92: TIDAK | Z92: YA | AA92: YA | AB92: TIDAK | AC92: TIDAK | AD92: =VLOOKUP(C92,'[39]LAMPIRAN STANDAR'!$E$81:F$216,2,0) -> dini.d@ikoito.co.id | AE92: YA | AF92: PIKPC180 | AG92: 172.17.12.106 | AH92: 172.17.128.67 | AI92: OHB | AJ92: Windows 11 | AK92: 1 | AL92: 1 | AM92: CLARUS | AN92: 015/PO/HR&GA/GA/ XII/2022 | AO92: 44896 | AP92: 47058 | AQ92: LUSY | AR92: 0856-9576-1612 | AS92: PC DEPRE DES 2022
B93: 87 | C93: FI-00763 | D93: LAPTOP | E93: MARKETING DIV | F93: MARKETING DIV | G93: SHINSUKE TANAKA | H93: 2112043 | I93: 2023 | J93: =I93+6 -> 2029 | K93: ACTIVE | L93: LAPTOP MANAGERIAL | M93: ✓ | Y93: YA | Z93: TIDAK | AA93: TIDAK | AB93: YA | AC93: TIDAK | AD93: s-tanaka@ikoito.co.id | AE93: YA | AF93: PIK1COM030 | AG93: 172.17.12.29 | AH93: DHCP | AI93: E3 | AJ93: Windows 11 | AK93: 1 | AL93: 1 | AM93: CLARUS | AN93: 059/PO/HR&GA/GA/VI/2023 | AO93: 45078 | AP93: 47270 | AQ93: LUSY | AR93: 0856-9576-1612 | AS93: PC DEPRE JUNI 2023
B94: 88 | C94: FI-00650 | D94: LAPTOP | E94: MARKETING DIV | F94: MARKETING DIV | G94: WINARDI | H94: 1008004 | I94: 2021 | J94: =I94+6 -> 2027 | K94: ACTIVE | L94: LAPTOP MANAGERIAL | M94: ✓ | Y94: YA | Z94: TIDAK | AA94: TIDAK | AB94: TIDAK | AC94: TIDAK | AD94: winardi@ikoito.co.id | AE94: YA | AF94: PIKPC113 | AG94: 172.17.12.101 | AH94: DHCP | AI94: E3 | AJ94: Windows 11 | AK94: 1 | AL94: 1 | AM94: SBTELECOM | AN94: 023/PO/HR&GA/GA/ VI/2021 | AO94: 44348 | AP94: 46539 | AQ94: ASTRI | AR94: 0811-1067-925 | AS94: UPGRADE LAP MNGR JUNI 2021 (20 UNIT)
B95: 89 | C95: FI-01074 | D95: ALL IN ONE | E95: MARKETING DIV | F95: SALES | G95: MUHAMMAD TOHARI MUSLIM | H95: 2602030 | I95: 2025 | J95: =I95+6 -> 2031 | K95: ACTIVE | L95: OFFICER ADMIN | P95: ✓ | Y95: TIDAK | Z95: YA | AA95: YA | AB95: TIDAK | AC95: TIDAK | AD95: sales.support@ikoito.co.id | AE95: YA | AF95: PIK1COM129 | AG95: 172.17.12.95 | AH95: 172.17.128.74 | AI95: OHB | AJ95: Windows 11 | AK95: 1 | AL95: 1 | AM95: XDC | AN95: 013/PO/HR&GA/GA/GA/III/2025 | AO95: 45658 | AP95: 47849 | AQ95: WIDI | AR95: 0821-2106-7715 | AS95: PERCEPATAN JAN 2025 (14 UNIT)
B96: 90 | C96: FI-01082 | D96: WORKSTATION | E96: MARKETING DIV | F96: SALES | G96: TRI HARIYANTO | H96: 1604003 | I96: 2025 | J96: =I96+6 -> 2031 | K96: ACTIVE | L96: TEKNIKAL | Q96: ✓ | Y96: TIDAK | Z96: YA | AA96: YA | AB96: TIDAK | AC96: TIDAK | AD96: tri.h@ikoito.co.id | AE96: YA | AF96: PIK1COM147 | AG96: 172.17.12.141 | AH96: 172.17.128.71 | AI96: OHB | AJ96: Windows 11 | AK96: 1 | AL96: 1 | AM96: XDC | AN96: 014/PO/HR&GA/GA/III/2025 | AO96: 45717 | AP96: 47908 | AQ96: WIDI | AR96: 0821-2106-7715 | AS96: DEPRE MAR 2025
B97: 91 | C97: FI-01022 | D97: ALL IN ONE | E97: MARKETING DIV | F97: SALES | G97: DINA ANGGRAENI | H97: 1202045 | I97: 2024 | J97: =I97+6 -> 2030 | K97: ACTIVE | L97: OFFICER ADMIN | P97: ✓ | Y97: TIDAK | Z97: YA | AA97: YA | AB97: TIDAK | AC97: TIDAK | AD97: =VLOOKUP(C97,'[39]LAMPIRAN STANDAR'!$E$81:F$216,2,0) -> dina.a@ikoito.co.id | AE97: YA | AF97: PIK1COM106 | AG97: 172.17.12.89 | AH97: 172.17.128.72 | AI97: OHB | AJ97: Windows 11 | AK97: 1 | AL97: 1 | AM97: TETRANET | AN97: 069/PO/HR&GA/GA/IX/2024 | AO97: 45536 | AP97: 47727 | AQ97: AFDAL | AR97: 0831-8760-3905 | AS97: DEPRE SEP 2024
B98: 92 | C98: FI-00718 | D98: ALL IN ONE | E98: MARKETING DIV | F98: SALES | G98: REZKI RAHMAD SURGAWAN | H98: 2301036 | I98: 2022 | J98: =I98+6 -> 2028 | K98: ACTIVE | L98: OFFICER ADMIN | P98: ✓ | Y98: TIDAK | Z98: YA | AA98: YA | AB98: TIDAK | AC98: TIDAK | AD98: =VLOOKUP(C98,'[39]LAMPIRAN STANDAR'!$E$81:F$216,2,0) -> sales.support@ikoito.co.id | AE98: YA | AF98: PIKPC174 | AG98: 172.17.12.105 | AH98: 172.17.128.73 | AI98: OHB | AJ98: Windows 11 | AK98: 1 | AL98: 1 | AM98: CLARUS | AN98: 015/PO/HR&GA/GA/ XII/2022 | AO98: 44896 | AP98: 47058 | AQ98: LUSY | AR98: 0856-9576-1612 | AS98: PC DEPRE DES 2022
B99: 93 | C99: FI-00748 | D99: ALL IN ONE | E99: PART PROCESS DIV | F99: ASSEMBLING | G99: AJI CHANDRA WINARTO | H99: 1310002 | I99: 2023 | J99: =I99+6 -> 2029 | K99: ACTIVE | L99: OFFICER ADMIN | P99: ✓ | Y99: TIDAK | Z99: YA | AA99: YA | AB99: TIDAK | AC99: TIDAK | AD99: =VLOOKUP(C99,'[39]LAMPIRAN STANDAR'!$E$81:F$216,2,0) -> aji.c@ikoito.co.id | AE99: YA | AF99: PIK1COM009 | AG99: 172.17.11.68 | AH99: 172.17.118.29 | AI99: OHB | AJ99: Windows 11 | AK99: 1 | AL99: 1 | AM99: SBTELECOM | AN99: 026/PO/HR&GA/GA/IV/2023 | AO99: 45017 | AP99: 47209 | AQ99: ASTRI | AR99: 0811-1067-925 | AS99: PC ADD APR 2023
B100: 94 | C100: FI-00647 | D100: LAPTOP | E100: PART PROCESS DIV | F100: ASSEMBLING | G100: A ZAKY ALATTAS | H100: 1301005 | I100: 2021 | J100: =I100+6 -> 2027 | K100: ACTIVE | L100: LAPTOP MANAGERIAL | M100: ✓ | Y100: YA | Z100: TIDAK | AA100: TIDAK | AB100: TIDAK | AC100: TIDAK | AD100: zaky.a@ikoito.co.id | AE100: YA | AF100: PIKPC118 | AG100: 172.17.11.66 | AH100: DHCP | AI100: E3 | AJ100: Windows 11 | AK100: 1 | AL100: 1 | AM100: SBTELECOM | AN100: 023/PO/HR&GA/GA/ VI/2021 | AO100: 44348 | AP100: 46539 | AQ100: ASTRI | AR100: 0811-1067-925 | AS100: UPGRADE LAP MNGR JUNI 2021 (20 UNIT)
...

Sheet PC NG
C1: CLIENT PC ASSET LIST | Z1: INFORMASI PEMBELIAN
A2: UPDATE | D2: : FEB 2026
D3: USER | M3: Klasifikasi User | Z3: SUPPLIER | AA3: NO PO | AB3: PIC SUPPLIER | AC3: KONTAK SUPPLIER | AD3: REMARKS
A4: NO | B4: NO.ASSET | C4: TYPE | D4: DIVISI | E4: DEPT | F4: NAMA | G4: NIK | H4: Pembelian | I4: Depresiasi (5+1 Tahun) | J4: HOSTNAME | K4: IP ADDRESS MAIN | L4: IP ADDRESS BACKUP | M4: Managerial | N4: Meeting | O4: Aktivitas Khusus | P4: Officer Admin | Q4: Teknikal | R4: Operator | S4: Aplikasi WMS | T4: VMS | U4: CCTV View | V4: Station Delivery | W4: Aplikasi Gathering | X4: OQC | Y4: Status
A5: 1 | B5: FI-00412 | C5: LAPTOP | D5: GENERAL AFFAIR DIV | E5: HR GA | F5: KOITO M-19 (ERNA) | G5: 1208059 | H5: 43455 | I5: 45647 | J5: PIK1COM002 | K5: - | L5: DHCP | N5: ✓ | Y5: ACTIVE | Z5: CSI | AA5: 011/PO/HR&GA/GA/X/2018 | AB5: IBRAIM | AC5: 0812-8097-4409 | AD5: PC ADD OKT 2018
A6: 2 | B6: FI-00413 | C6: LAPTOP | D6: GENERAL AFFAIR DIV | E6: HR GA | F6: KOITO M-13 (ERNA) | G6: 1208059 | H6: 43455 | I6: 45647 | J6: ENGMGRLT001 | K6: - | L6: DHCP | N6: ✓ | Y6: ACTIVE | Z6: CSI | AA6: 011/PO/HR&GA/GA/X/2018 | AB6: IBRAIM | AC6: 0812-8097-4409 | AD6: PC ADD OKT 2018
A7: 3 | B7: FI-00507 | C7: ALL IN ONE | D7: INJECTION MOLD DIV | E7: MOLD MAKING | F7: ANDINI SEPTOWATI | G7: 1506019 | H7: 43732 | I7: 45924 | J7: MEPC010 | K7: 172.17.12.157 | L7: 172.17.128.57 | P7: ✓ | Y7: ACTIVE | Z7: SBTELECOM | AA7: - | AB7: ASTRI | AD7: PC DEPRE DES 2025
A8: 4 | B8: FI-00509 | C8: ALL IN ONE | D8: PART PROCESS DIV | E8: ASSEMBLING | F8: RENI MAROZA | G8: 1109101 | H8: 43732 | I8: 45924 | J8: ASSYPC022 | K8: 172.17.11.69 | L8: 172.17.118.31 | P8: ✓ | Y8: ACTIVE | Z8: SBTELECOM | AA8: - | AB8: ASTRI | AC8: 0856-9576-1612 | AD8: PC DEPRE DES 2025
A9: 5 | B9: FI-00526 | C9: ALL IN ONE | D9: KPS | E9: KPS | F9: EX: DENIS | G9: - | H9: 43796 | I9: 45988 | J9: KPSPC001 | K9: 172.17.11.53 | L9: 172.17.118.25 | R9: ✓ | Y9: ACTIVE | Z9: SBTELECOM | AA9: - | AB9: ASTRI | AD9: PC DEPRE DES 2025
A10: 6 | B10: FI-00527 | C10: ALL IN ONE | D10: PART PROCESS DIV | E10: ASSEMBLING | F10: RAMLAN HIKMAT | G10: 1108001 | H10: 43796 | I10: 45988 | J10: PIKPC003 | K10: 172.17.11.67 | L10: 172.17.118.27 | P10: ✓ | Y10: ACTIVE | Z10: SBTELECOM | AA10: - | AB10: ASTRI | AD10: PC DEPRE JAN 2026
A11: 7 | B11: FI-00532 | C11: LAPTOP | D11: GENERAL AFFAIR DIV | E11: HR GA | F11: KOITO M-07 EX:ARDI/CAHYO) | G11: 1208059 | H11: 43826 | I11: 46018 | J11: PIK1COM072 | K11: - | L11: DHCP | N11: ✓ | Y11: ACTIVE | Z11: CLARUS | AA11: 009/PO/HR&GA/GA/VIII/2019 | AB11: LUSY | AC11: 0856-9576-1612 | AD11: PC DEPRE AGUST 2019
A12: 8 | B12: FI-00533 | C12: MINI PC | D12: PART PROCESS DIV | E12: ST | F12: AMUD | G12: 1808002 | H12: 43826 | I12: 46018 | J12: SFTPC001 | K12: 172.17.11.49 | L12: 172.17.118.43 | P12: ✓ | Y12: ACTIVE | Z12: CLARUS | AA12: 054/PO/HR&GA/GA/VII/2019 | AB12: LUSY | AC12: 0856-9576-1612 | AD12: PC ADD JUL 2019
A13: 9 | B13: FI-00534 | C13: ALL IN ONE | D13: QE DIV | E13: PROD DEV | F13: PUJI EFENDI | G13: 1405012 | H13: 43826 | I13: 46018 | J13: PIK1COM092 | K13: 172.17.12.146 | L13: 172.17.128.134 | P13: ✓ | Y13: ACTIVE | Z13: SBTELECOM | AB13: ASTRI | AD13: PC DEPRE JAN 2026
A14: 10 | B14: FI-00535 | C14: ALL IN ONE | D14: PART PROCESS DIV | E14: ASSEMBLING | F14: ABU KHAMID | G14: 1302034 | H14: 43826 | I14: 46018 | J14: ASSYPC026 | K14: 172.17.11.101 | L14: 172.17.118.28 | P14: ✓ | Y14: ACTIVE | Z14: SBTELECOM | AA14: - | AB14: ASTRI | AD14: PC DEPRE JAN 2026
A15: 11 | B15: FI-00536 | C15: MINI PC | D15: KPS | E15: KPS | F15: SYAIFUL RAMADHAN | G15: 1302030 | H15: 43826 | I15: 46018 | J15: KPSPC002 | K15: 172.17.11.52 | L15: 172.17.118.23 | P15: ✓ | Y15: ACTIVE | Z15: CLARUS | AA15: 010/PO/HR&GA/GA/VIII/2019 | AB15: LUSY | AC15: 0856-9576-1612 | AD15: PC DEPRE AGUST 2019
A16: 12 | B16: FI-00537 | C16: MINI PC | D16: GENERAL AFFAIR DIV | E16: HR GA | F16: HR SH | H16: 43826 | I16: 46018 | J16: PIKPC034 | K16: 172.17.12.49 | L16: 172.17.128.26 | P16: ✓ | Y16: ACTIVE | Z16: CLARUS | AA16: 011/PO/HR&GA/GA/VIII/2019 | AB16: LUSY | AC16: 0856-9576-1612 | AD16: PC DEPRE AGUST 2019
A17: 13 | B17: FI-00538 | C17: MINI PC | D17: PART PROCESS DIV | E17: INJECTION | F17: INJ GROUP LEADER (ANDRIE SUHERMAN) | G17: 1011021 | H17: 43826 | I17: 46018 | J17: INJPC004 | K17: 172.17.11.42 | L17: 172.17.118.38 | P17: ✓ | Y17: ACTIVE | Z17: CLARUS | AA17: 011/PO/HR&GA/GA/VIII/2019 | AB17: LUSY | AC17: 0856-9576-1612 | AD17: PC DEPRE AGUST 2019
A18: 14 | B18: FI-00541 | C18: WORKSTATION | D18: INJECTION MOLD DIV | E18: MOLD MAKING | F18: MOLD DRAW PC (REZA ADITYA PERMADI) | G18: 2412013 | H18: 43826 | I18: 46018 | J18: MEDRAWPC001 | K18: 172.17.20.134 | L18: 172.17.218.8 | Q18: ✓ | Y18: Non Active | Z18: CSI | AA18: 012/PO/HR&GA/GA/IX/2019 | AB18: IBRAIM | AC18: 0812-8097-4409 | AD18: PC DEPRE SEP 2019
A19: 15 | B19: FI-00545 | C19: MINI PC | D19: QA DIV | E19: QT | F19: PANDU PRAMUDYA | G19: 1503046 | H19: 43861 | I19: 46053 | J19: QTPC001 | K19: 172.17.12.183 | L19: 172.17.128.118 | R19: ✓ | Y19: ACTIVE | Z19: CLARUS | AA19: 054/PO/HR&GA/GA/VII/2019 | AB19: LUSY | AC19: 0856-9576-1612 | AD19: PC ADD JUL 2019
A20: 16 | B20: FI-00547 | C20: MINI PC | D20: TECHNICAL DIV | E20: PROD ENG | F20: ARITONANG ARIA KUSUMA | G20: 1011015 | H20: 43861 | I20: 46053 | J20: ENGPC004 | K20: 172.17.11.78 | L20: 172.17.118.88 | P20: ✓ | Y20: ACTIVE | Z20: CLARUS | AA20: 012/PO/HR&GA/GA/VIII/2019 | AB20: LUSY | AC20: 0856-9576-1612 | AD20: PC DEPRE AGUST 2019
A21: 17 | B21: FI-00549 | C21: MINI PC | D21: PART PROCESS DIV | E21: ASSEMBLING | F21: ASSEMBLY GRUP LEADER (KUSNO) | G21: 1302038 | H21: 43861 | I21: 46053 | J21: PIKPC023 | K21: 172.17.11.100 | L21: 172.17.118.30 | P21: ✓ | Y21: Non Active | Z21: CLARUS | AA21: 011/PO/HR&GA/GA/VIII/2019 | AB21: LUSY | AC21: 0856-9576-1612 | AD21: PC DEPRE AGUST 2019
A22: 18 | B22: FI-00590 | C22: WORKSTATION | D22: INJECTION MOLD DIV | E22: MOLD ENG | F22: CAMTOOL CNC (ALKINDI) | G22: 1703001 | H22: 44227 | I22: 46418 | J22: MEDRAWPC002 | K22: 172.17.20.132 | L22: 172.17.218.4 | Q22: ✓ | Y22: ACTIVE | Z22: CLARUS | AA22: 025/PO/HR&GA/GA/X/2020 | AB22: LUSY | AC22: 0856-9576-1612 | AD22: PC DEPRE OKT 2020
A23: 19 | B23: FI-00591 | C23: WORKSTATION | D23: INJECTION MOLD DIV | E23: MOLD ENG | F23: MOLDFLOW (ISMAIL MARJUKI) | G23: 1801027 | H23: 44227 | I23: 46418 | J23: PIK1COM011 | K23: 172.17.12.163 | L23: 172.17.128.56 | Q23: ✓ | Y23: ACTIVE | Z23: CLARUS | AA23: 025/PO/HR&GA/GA/X/2020 | AB23: LUSY | AC23: 0856-9576-1612 | AD23: PC DEPRE OKT 2020
A24: 20 | B24: FI-00605 | C24: LAPTOP | D24: TECHNICAL DIV | E24: TECHNICAL DIV | F24: EDI KUSNADI | G24: 1011031 | H24: 44286 | I24: 46477 | J24: PIKLT003 | K24: 172.17.11.24 | L24: DHCP | M24: ✓ | Y24: ACTIVE | Z24: CLARUS | AA24: 028/PO/HR&GA/GA/ I/2021 | AB24: LUSY | AC24: 0856-9576-1612 | AD24: PC DEPRE JAN 2021
A25: 21 | B25: FI-00606 | C25: LAPTOP | D25: QA DIV | E25: QA DIV | F25: UJANG SOPANDI | G25: 1106001 | H25: 44286 | I25: 46477 | J25: PIKLT002 | K25: 172.17.12.116 | L25: DHCP | M25: ✓ | Y25: ACTIVE | Z25: CLARUS | AA25: 028/PO/HR&GA/GA/ I/2021 | AB25: LUSY | AC25: 0856-9576-1612 | AD25: PC DEPRE JAN 2021
A26: 22 | B26: FI-00607 | C26: LAPTOP | D26: FINANCE DIV | E26: FA | F26: IMAN KOESTIAMAN | G26: 1112021 | H26: 44286 | I26: 46477 | J26: PIKLT004 | K26: 172.17.12.186 | L26: DHCP | M26: ✓ | Y26: ACTIVE | Z26: CLARUS | AA26: 028/PO/HR&GA/GA/ I/2021 | AB26: LUSY | AC26: 0856-9576-1612 | AD26: PC DEPRE JAN 2021
A27: 23 | B27: FI-00612 | C27: WORKSTATION | D27: INJECTION MOLD DIV | E27: MOLD MAKING | F27: CATIA 2 (DADI HERIYANTO) | G27: 1709001 | H27: 44316 | I27: 46507 | J27: PIKPC156 | K27: 172.17.20.133 | L27: 172.17.218.7 | Q27: ✓ | Y27: ACTIVE | Z27: CLARUS | AA27: 021/PO/HR&GA/GA/ XII/2020 | AB27: LUSY | AC27: 0856-9576-1612 | AD27: PC DEPRE DES 2020
A28: 24 | B28: FI-00616 | C28: LAPTOP | D28: GENERAL AFFAIR DIV | E28: IT LEGAL | F28: KOITO M-08 (AYUNG) | G28: 1205001 | H28: 44377 | I28: 46568 | J28: - | K28: - | L28: DHCP | N28: ✓ | Y28: ACTIVE | Z28: CLARUS | AA28: 027/PO/HR&GA/GA/1/2021 | AB28: LUSY | AC28: 0856-9576-1612 | AD28: LAPTOP ADD JAN 2021
A29: 25 | B29: FI-00617 | C29: LAPTOP | D29: GENERAL AFFAIR DIV | E29: IT LEGAL | F29: KOITO M-09 (AYUNG) | G29: 1205001 | H29: 44377 | I29: 46568 | J29: PIKLT007 | K29: - | L29: DHCP | N29: ✓ | Y29: ACTIVE | Z29: CLARUS | AA29: 027/PO/HR&GA/GA/1/2021 | AB29: LUSY | AC29: 0856-9576-1612 | AD29: LAPTOP ADD JAN 2021
A30: 26 | B30: FI-00638 | C30: LAPTOP | D30: QA DIV | E30: QT | F30: HERMAN AZIS | G30: 1104009 | H30: 44406 | I30: 46808 | J30: PIKPC111 | K30: 172.17.12.133 | L30: DHCP | M30: ✓ | Y30: ACTIVE | Z30: SBTELECOM | AA30: 023/PO/HR&GA/GA/ VI/2021 | AB30: ASTRI | AC30: 0811-1067-925 | AD30: UPGRADE LAP MNGR JUNI 2021 (20 UNIT)
A31: 27 | B31: FI-00639 | C31: LAPTOP | D31: EXECUTIVE BOARD | E31: - | F31: MUTSUHIKO UCHIYAMA | G31: 1007001 | H31: 44406 | I31: 46808 | J31: PIKPC116 | K31: 172.17.12.16 | L31: DHCP | M31: ✓ | Y31: ACTIVE | Z31: SBTELECOM | AA31: 023/PO/HR&GA/GA/ VI/2021 | AB31: ASTRI | AC31: 0811-1067-925 | AD31: UPGRADE LAP MNGR JUNI 2021 (20 UNIT)
A32: 28 | B32: FI-00640 | C32: LAPTOP | D32: EXECUTIVE BOARD | E32: - | F32: SHIBATANI KANTO | G32: 110501 | H32: 44406 | I32: 46808 | J32: PIKPC106 | K32: 172.17.12.18 | L32: DHCP | M32: ✓ | Y32: ACTIVE | Z32: SBTELECOM | AA32: 023/PO/HR&GA/GA/ VI/2021 | AB32: ASTRI | AC32: 0811-1067-925 | AD32: UPGRADE LAP MNGR JUNI 2021 (20 UNIT)
A33: 29 | B33: FI-00641 | C33: LAPTOP | D33: EXECUTIVE BOARD | E33: - | F33: ERMA PURNAMA WIDA PANE | G33: 1008001 | H33: 44406 | I33: 46808 | J33: PIKPC107 | K33: 172.17.12.31 | L33: DHCP | M33: ✓ | Y33: ACTIVE | Z33: SBTELECOM | AA33: 023/PO/HR&GA/GA/ VI/2021 | AB33: ASTRI | AC33: 0811-1067-925 | AD33: UPGRADE LAP MNGR JUNI 2021 (20 UNIT)
A34: 30 | B34: FI-00642 | C34: LAPTOP | D34: PURCHASING DIV | E34: PURCHASING DIV | F34: YUSUKE FUJISAWA | G34: 2205002 | H34: 44406 | I34: 46808 | J34: PIKPC109 | K34: 172.17.12.22 | L34: DHCP | M34: ✓ | Y34: ACTIVE | Z34: SBTELECOM | AA34: 023/PO/HR&GA/GA/ VI/2021 | AB34: ASTRI | AC34: 0811-1067-925 | AD34: UPGRADE LAP MNGR JUNI 2021 (20 UNIT)
A35: 31 | B35: FI-00643 | C35: LAPTOP | D35: PPIC DIV | E35: PPIC DIV | F35: TAKEO FUKUSHIMA | G35: 2311019 | H35: 44406 | I35: 46808 | J35: PIK1COM175 | K35: 172.17.11.130 | L35: DHCP | M35: ✓ | Y35: ACTIVE | Z35: SBTELECOM | AA35: 023/PO/HR&GA/GA/ VI/2021 | AB35: ASTRI | AC35: 0811-1067-925 | AD35: UPGRADE LAP MNGR JUNI 2021 (20 UNIT)
A36: 32 | B36: FI-00644 | C36: LAPTOP | D36: QE DIV | E36: QE DIV | F36: KATSUMI MOCHIZUKI | G36: 2305002 | H36: 44406 | I36: 46808 | J36: PIKLT006 | K36: 172.17.12.27 | L36: DHCP | M36: ✓ | Y36: ACTIVE | Z36: SBTELECOM | AA36: 023/PO/HR&GA/GA/ VI/2021 | AB36: ASTRI | AC36: 0811-1067-925 | AD36: UPGRADE LAP MNGR JUNI 2021 (20 UNIT)
A37: 33 | B37: FI-00645 | C37: LAPTOP | D37: TECHNICAL DIV | E37: TECHNICAL DIV | F37: YUSUKE ADACHI | G37: 2305001 | H37: 44406 | I37: 46808 | J37: PIKPC101 | K37: 172.17.11.23 | L37: DHCP | M37: ✓ | Y37: ACTIVE | Z37: SBTELECOM | AA37: 023/PO/HR&GA/GA/ VI/2021 | AB37: ASTRI | AC37: 0811-1067-925 | AD37: UPGRADE LAP MNGR JUNI 2021 (20 UNIT)
A38: 34 | B38: FI-00646 | C38: LAPTOP | D38: TECHNICAL DIV | E38: M/C MAINTENANCE | F38: TEGUH MAHENDRA | G38: 1301030 | H38: 44406 | I38: 46808 | J38: PIKPC102 | K38: 172.17.11.73 | L38: DHCP | M38: ✓ | Y38: ACTIVE | Z38: SBTELECOM | AA38: 023/PO/HR&GA/GA/ VI/2021 | AB38: ASTRI | AC38: 0811-1067-925 | AD38: UPGRADE LAP MNGR JUNI 2021 (20 UNIT)
A39: 35 | B39: FI-00647 | C39: LAPTOP | D39: PART PROCESS DIV | E39: ASSEMBLING | F39: A ZAKY ALATTAS | G39: 1301005 | H39: 44406 | I39: 46808 | J39: PIKPC118 | K39: 172.17.11.66 | L39: DHCP | M39: ✓ | Y39: ACTIVE | Z39: SBTELECOM | AA39: 023/PO/HR&GA/GA/ VI/2021 | AB39: ASTRI | AC39: 0811-1067-925 | AD39: UPGRADE LAP MNGR JUNI 2021 (20 UNIT)
A40: 36 | B40: FI-00648 | C40: LAPTOP | D40: QA DIV | E40: QI | F40: SUKADI | G40: 1109118 | H40: 44406 | I40: 46808 | J40: PIKPC119 | K40: 172.17.12.165 | L40: DHCP | M40: ✓ | Y40: ACTIVE | Z40: SBTELECOM | AA40: 023/PO/HR&GA/GA/ VI/2021 | AB40: ASTRI | AC40: 0811-1067-925 | AD40: UPGRADE LAP MNGR JUNI 2021 (20 UNIT)
A41: 37 | B41: FI-00649 | C41: LAPTOP | D41: KPS | E41: KPS | F41: DADANG CAHYADI | G41: 1508002 | H41: 44406 | I41: 46808 | J41: PIKPC104 | K41: 172.17.11.57 | L41: DHCP | M41: ✓ | Y41: ACTIVE | Z41: SBTELECOM | AA41: 023/PO/HR&GA/GA/ VI/2021 | AB41: ASTRI | AC41: 0811-1067-925 | AD41: UPGRADE LAP MNGR JUNI 2021 (20 UNIT)
... A45: 41 | B45: FI-00653 | C45: LAPTOP | D45: INJECTION MOLD DIV | E45: INJECTION MOLD DIV | F45: EDY PRASETYA | G45: 1011006 | H45: 44406 | I45: 46808 | J45: PIKPC120 | K45: 172.17.12.150 | L45: DHCP | M45: ✓ | Y45: ACTIVE | Z45: SBTELECOM | AA45: 023/PO/HR&GA/GA/ VI/2021 | AB45: ASTRI | AC45: 0811-1067-925 | AD45: UPGRADE LAP MNGR JUNI 2021 (20 UNIT)
A46: 42 | B46: FI-00654 | C46: LAPTOP | D46: GENERAL AFFAIR DIV | E46: HRGA | F46: KOITO M-14 (ERNA) | G46: 1205001 | H46: 44406 | I46: 46808 | J46: PIKPC115 | K46: 172.17.12.214 | L46: DHCP | N46: ✓ | Y46: ACTIVE | Z46: SBTELECOM | AA46: 023/PO/HR&GA/GA/ VI/2021 | AB46: ASTRI | AC46: 0811-1067-925 | AD46: UPGRADE LAP MNGR JUNI 2021 (20 UNIT)
A47: 43 | B47: FI-00655 | C47: LAPTOP | D47: PART PROCESS DIV | E47: ST | F47: REZA MORTA | G47: 1011014 | H47: 44406 | I47: 46808 | J47: PIKPC105 | K47: 172.17.11.45 | L47: DHCP | M47: ✓ | Y47: ACTIVE | Z47: SBTELECOM | AA47: 023/PO/HR&GA/GA/ VI/2021 | AB47: ASTRI | AC47: 0811-1067-925 | AD47: UPGRADE LAP MNGR JUNI 2021 (20 UNIT)
A48: 44 | B48: FI-00656 | C48: LAPTOP | D48: PPIC DIV | E48: PPC | F48: AZIS HERIAWAN | G48: 1306001 | H48: 44406 | I48: 46808 | J48: PIK1COM117 | K48: - | L48: DHCP | M48: ✓ | Y48: ACTIVE | Z48: SBTELECOM | AA48: 023/PO/HR&GA/GA/ VI/2021 | AB48: ASTRI | AC48: 0811-1067-925 | AD48: UPGRADE LAP MNGR JUNI 2021 (20 UNIT)
A49: 45 | B49: FI-00657 | C49: LAPTOP | D49: QA DIV | E49: QA DIV | F49: DOLAR MEDIA | G49: 1100201 | H49: 44406 | I49: 46808 | J49: PIKPC117 | K49: 172.17.12.86 | L49: DHCP | M49: ✓ | Y49: ACTIVE | Z49: SBTELECOM | AA49: 023/PO/HR&GA/GA/ VI/2021 | AB49: ASTRI | AC49: 0811-1067-925 | AD49: UPGRADE LAP MNGR JUNI 2021 (20 UNIT)
A50: 46 | B50: FI-00658 | C50: ALL IN ONE | D50: PPIC DIV | E50: LOGISTIK | F50: ROSIYAH | G50: 1509003 | H50: 44406 | I50: 46808 | J50: PIKPC138 | K50: 172.17.20.107 | L50: 172.17.218.22 | O50: ✓ | Y50: ACTIVE | Z50: SBTELECOM | AA50: 024/PO/HR&GA/GA/VI/2021 | AB50: ASTRI | AC50: 0811-1067-925 | AD50: UPGRADE AIO JUNI 2021 (18 UNIT)
A51: 47 | B51: FI-00659 | C51: ALL IN ONE | D51: PURCHASING DIV | E51: PURCHASING | F51: DENIS RAMADHANI MALIK | G51: 2410011 | H51: 44406 | I51: 46808 | J51: PIKPC121 | K51: 172.17.12.198 | L51: 172.17.128.89 | P51: ✓ | Y51: ACTIVE | Z51: SBTELECOM | AA51: 024/PO/HR&GA/GA/VI/2021 | AB51: ASTRI | AC51: 0811-1067-925 | AD51: UPGRADE AIO JUNI 2021 (18 UNIT)
A52: 48 | B52: FI-00660 | C52: ALL IN ONE | D52: GENERAL AFFAIR DIV | E52: HR GA | F52: HR PAYROLL (RINDY) | G52: 2602032 | H52: 44406 | I52: 46808 | J52: PIKPC122 | K52: 172.17.12.222 | L52: 172.17.128.16 | P52: ✓ | Y52: ACTIVE | Z52: SBTELECOM | AA52: 024/PO/HR&GA/GA/VI/2021 | AB52: ASTRI | AC52: 0811-1067-925 | AD52: UPGRADE AIO JUNI 2021 (18 UNIT)
A53: 49 | B53: FI-00661 | C53: ALL IN ONE | D53: PURCHASING DIV | E53: PURCHASING | F53: SULISTIANINGSIH | G53: 1310003 | H53: 44406 | I53: 46808 | J53: PIKPC123 | K53: 172.17.12.126 | L53: 172.17.128.85 | O53: ✓ | Y53: ACTIVE | Z53: SBTELECOM | AA53: 024/PO/HR&GA/GA/VI/2021 | AB53: ASTRI | AC53: 0811-1067-925 | AD53: UPGRADE AIO JUNI 2021 (18 UNIT)
A54: 50 | B54: FI-00662 | C54: ALL IN ONE | D54: PURCHASING DIV | E54: PURCHASING | F54: HANDY NUR PRATAMA | G54: 2207015 | H54: 44406 | I54: 46808 | J54: PIKPC124 | K54: 172.17.12.127 | L54: 172.17.128.86 | P54: ✓ | Y54: ACTIVE | Z54: SBTELECOM | AA54: 024/PO/HR&GA/GA/VI/2021 | AB54: ASTRI | AC54: 0811-1067-925 | AD54: UPGRADE AIO JUNI 2021 (18 UNIT)
A55: 51 | B55: FI-00663 | C55: ALL IN ONE | D55: PPIC DIV | E55: LOGISTIK | F55: YULIA | G55: 1302028 | H55: 44406 | I55: 46808 | J55: PIKPC125 | K55: 172.17.20.108 | L55: 172.17.218.21 | O55: ✓ | Y55: ACTIVE | Z55: SBTELECOM | AA55: 024/PO/HR&GA/GA/VI/2021 | AB55: ASTRI | AC55: 0811-1067-925 | AD55: UPGRADE AIO JUNI 2021 (18 UNIT)
A56: 52 | B56: FI-00664 | C56: ALL IN ONE | D56: PPIC DIV | E56: LOGISTIK | F56: JAHRI RIZALDI | G56: 1603046 | H56: 44406 | I56: 46808 | J56: PIKPC126 | K56: 172.17.20.122 | L56: 172.17.218.15 | O56: ✓ | Y56: ACTIVE | Z56: SBTELECOM | AA56: 024/PO/HR&GA/GA/VI/2021 | AB56: ASTRI | AC56: 0811-1067-925 | AD56: UPGRADE AIO JUNI 2021 (18 UNIT)
A57: 53 | B57: FI-00665 | C57: ALL IN ONE | D57: QE DIV | E57: PPM | F57: CUCU FARIDA | G57: 1203027 | H57: 44406 | I57: 46808 | J57: PIKPC127 | K57: 172.17.12.137 | L57: 172.17.128.123 | P57: ✓ | Y57: ACTIVE | Z57: SBTELECOM | AA57: 024/PO/HR&GA/GA/VI/2021 | AB57: ASTRI | AC57: 0811-1067-925 | AD57: UPGRADE AIO JUNI 2021 (18 UNIT)
A58: 54 | B58: FI-00666 | C58: ALL IN ONE | D58: GENERAL AFFAIR DIV | E58: IT LEGAL | F58: DENI AGUSTA | G58: 2302029 | H58: 44406 | I58: 46808 | J58: PIK1COM104 | K58: 172.17.12.64 | L58: 172.17.128.37 | R58: ✓ | Y58: ACTIVE | Z58: SBTELECOM | AA58: 024/PO/HR&GA/GA/VI/2021 | AB58: ASTRI | AC58: 0811-1067-925 | AD58: UPGRADE AIO JUNI 2021 (18 UNIT)
A59: 55 | B59: FI-00667 | C59: ALL IN ONE | D59: QE DIV | E59: PROD DEV | F59: PURNOMO JUNIADI | G59: 1410001 | H59: 44406 | I59: 46808 | J59: PIKPC129 | K59: 172.17.12.148 | L59: 172.17.128.132 | P59: ✓ | Y59: ACTIVE | Z59: SBTELECOM | AA59: 024/PO/HR&GA/GA/VI/2021 | AB59: ASTRI | AC59: 0811-1067-925 | AD59: UPGRADE AIO JUNI 2021 (18 UNIT)
A60: 56 | B60: FI-00668 | C60: ALL IN ONE | D60: HSE DIV | E60: HSE | F60: AHMAD KAMALUDIN | G60: 1604048 | H60: 44406 | I60: 46808 | J60: PIKPC130 | K60: 172.17.12.74 | L60: 172.17.128.43 | P60: ✓ | Y60: ACTIVE | Z60: SBTELECOM | AA60: 024/PO/HR&GA/GA/VI/2021 | AB60: ASTRI | AC60: 0811-1067-925 | AD60: UPGRADE AIO JUNI 2021 (18 UNIT)
A61: 57 | B61: FI-00669 | C61: ALL IN ONE | D61: HSE DIV | E61: HSE | F61: SITI SUSILAWATI | G61: 1404041 | H61: 44406 | I61: 46808 | J61: PIKPC131 | K61: 172.17.12.73 | L61: 172.17.128.42 | P61: ✓ | Y61: ACTIVE | Z61: SBTELECOM | AA61: 024/PO/HR&GA/GA/VI/2021 | AB61: ASTRI | AC61: 0811-1067-925 | AD61: UPGRADE AIO JUNI 2021 (18 UNIT)
A62: 58 | B62: FI-00670 | C62: ALL IN ONE | D62: FINANCE DIV | E62: FA | F62: STEVE FANNIE | G62: 1011032 | H62: 44406 | I62: 46808 | J62: PIKPC132 | K62: 172.17.12.188 | L62: 172.17.128.3 | O62: ✓ | Y62: ACTIVE | Z62: SBTELECOM | AA62: 024/PO/HR&GA/GA/VI/2021 | AB62: ASTRI | AC62: 0811-1067-925 | AD62: UPGRADE AIO JUNI 2021 (18 UNIT)
A63: 59 | B63: FI-00671 | C63: ALL IN ONE | D63: PURCHASING DIV | E63: PURCHASING | F63: MUHAMMAD FAKIH AL GHIFARI | G63: 2401038 | H63: 44406 | I63: 46808 | J63: PIKPC133 | K63: 172.17.12.123 | L63: 172.17.128.87 | O63: ✓ | Y63: ACTIVE | Z63: SBTELECOM | AA63: 024/PO/HR&GA/GA/VI/2021 | AB63: ASTRI | AC63: 0811-1067-925 | AD63: UPGRADE AIO JUNI 2021 (18 UNIT)
A64: 60 | B64: FI-00672 | C64: ALL IN ONE | D64: KPS | E64: KPS | F64: AJI SUSANTO | G64: 1406004 | H64: 44406 | I64: 46808 | J64: PIKPC134 | K64: 172.17.11.50 | L64: 172.17.118.22 | P64: ✓ | Y64: ACTIVE | Z64: SBTELECOM | AA64: 024/PO/HR&GA/GA/VI/2021 | AB64: ASTRI | AC64: 0811-1067-925 | AD64: UPGRADE AIO JUNI 2021 (18 UNIT)
A65: 61 | B65: FI-00673 | C65: ALL IN ONE | D65: QA DIV | E65: QI | F65: EX:LUKMAN NULHAKIM | G65: 1603090 | H65: 44406 | I65: 46808 | J65: PIKPC135 | K65: 172.17.12.178 | L65: 172.17.128.110 | R65: ✓ | Y65: ACTIVE | Z65: SBTELECOM | AA65: 024/PO/HR&GA/GA/VI/2021 | AB65: ASTRI | AC65: 0811-1067-925 | AD65: UPGRADE AIO JUNI 2021 (18 UNIT)
A66: 62 | B66: FI-00674 | C66: ALL IN ONE | D66: QE DIV | E66: PROD DEV | F66: ARIS RAHAYU MAULIDAN | G66: 1505002 | H66: 44406 | I66: 46808 | J66: PIKPC136 | K66: 172.17.12.145 | L66: 172.17.128.133 | P66: ✓ | Y66: ACTIVE | Z66: SBTELECOM | AA66: 024/PO/HR&GA/GA/VI/2021 | AB66: ASTRI | AC66: 0811-1067-925 | AD66: UPGRADE AIO JUNI 2021 (18 UNIT)
A67: 63 | B67: FI-00675 | C67: ALL IN ONE | D67: QA DIV | E67: QI | F67: KIKI RAHMAWATI | G67: 1404024 | H67: 44406 | I67: 46808 | J67: PIKPC137 | K67: 172.17.12.172 | L67: 172.17.128.111 | P67: ✓ | Y67: ACTIVE | Z67: SBTELECOM | AA67: 024/PO/HR&GA/GA/VI/2021 | AB67: ASTRI | AC67: 0811-1067-925 | AD67: UPGRADE AIO JUNI 2021 (18 UNIT)
A68: 64 | B68: FI-00686 | C68: DESKTOP | D68: PPIC DIV | E68: LOGISTIK | F68: STATION 4 (RYAN ANDRIAN PUTRA) | G68: 1105004 | H68: 44804 | I68: 46996 | J68: PIKPC160 | K68: 172.17.20.128 | L68: 172.17.218.25 | V68: ✓ | Y68: ACTIVE | Z68: SBTELECOM | AA68: 022/PO/HR&GA/GA/ V/2022 | AB68: ASTRI | AC68: 0811-1067-925 | AD68: PC DERPRE MEI 2022
A69: 65 | B69: FI-00692 | C69: ALL IN ONE | D69: QE DIV | E69: PPM | F69: ALWI FADILAH RAHAYU | G69: 2303006 | H69: 44834 | I69: 47026 | J69: PIKPC157 | K69: 172.17.12.138 | L69: 172.17.128.124 | P69: ✓ | Y69: ACTIVE | Z69: SBTELECOM | AA69: 009/PO/HR&GA/GA/V/2022 | AB69: ASTRI | AC69: 0811-1067-925 | AD69: PC DEPRE MEI 2022
A70: 66 | B70: FI-00693 | C70: ALL IN ONE | D70: QA DIV | E70: QI | F70: TIARA ARSITA MEILINDA | G70: 1508034 | H70: 44834 | I70: 47026 | J70: PIKPC164 | K70: 172.17.12.171 | L70: 172.17.128.112 | P70: ✓ | Y70: ACTIVE | Z70: SBTELECOM | AA70: 009/PO/HR&GA/GA/V/2022 | AB70: ASTRI | AC70: 0811-1067-925 | AD70: PC DEPRE MEI 2022
A71: 67 | B71: FI-00694 | C71: ALL IN ONE | D71: PPIC DIV | E71: PPC | F71: DERI NOVIANDI | G71: 1805062 | H71: 44834 | I71: 47026 | J71: PIK1COM003 | K71: 172.17.11.31 | L71: 172.17.118.54 | O71: ✓ | Y71: ACTIVE | Z71: SBTELECOM | AA71: 009/PO/HR&GA/GA/V/2022 | AB71: ASTRI | AC71: 0811-1067-925 | AD71: PC DEPRE MEI 2022
A72: 68 | B72: FI-00695 | C72: ALL IN ONE | D72: KPS | E72: KPS | F72: DUDI SUGITO | G72: 1108007 | H72: 44834 | I72: 47026 | J72: PIKPC154 | K72: 172.17.11.87 | L72: 172.17.118.24 | R72: ✓ | Y72: ACTIVE | Z72: SBTELECOM | AA72: 039/PO/HR&GA/GA/IV/2022 | AB72: ASTRI | AC72: 0811-1067-925 | AD72: PC DEPRE APRIL 2022
A73: 69 | B73: FI-00696 | C73: ALL IN ONE | D73: PART PROCESS DIV | E73: ST | F73: ANDI AZIZ JULIAN | G73: 1011025 | H73: 44834 | I73: 47026 | J73: PIKPC153 | K73: 172.17.11.88 | L73: 172.17.118.42 | P73: ✓ | Y73: ACTIVE | Z73: SBTELECOM | AA73: 039/PO/HR&GA/GA/IV/2022 | AB73: ASTRI | AC73: 0811-1067-925 | AD73: PC DEPRE APRIL 2022
A74: 70 | B74: FI-00697 | C74: ALL IN ONE | D74: SPM | E74: SPM | F74: SPM 2 PT INDONESIA KOITO | G74: - | H74: 44834 | I74: 47026 | J74: SPMPC | K74: 172.17.20.117 | L74: - | P74: ✓ | Y74: ACTIVE | Z74: SBTELECOM | AA74: 039/PO/HR&GA/GA/IV/2022 | AB74: ASTRI | AC74: 0811-1067-925 | AD74: PC DEPRE APRIL 2022
A75: 71 | B75: FI-00699 | C75: ALL IN ONE | D75: QA DIV | E75: QC | F75: MUHAMAD DIKRI | G75: 1305020 | H75: 44865 | I75: 47057 | J75: PIKPC165 | K75: 172.17.12.139 | L75: 172.17.128.96 | P75: ✓ | Y75: ACTIVE | Z75: SBTELECOM | AA75: 005/PO/HR&GA/GA/VIII/2022 | AB75: ASTRI | AC75: 0811-1067-925 | AD75: PC DEPRE AGUST 2022
A76: 72 | B76: FI-00700 | C76: ALL IN ONE | D76: QA DIV | E76: QT | F76: FAUZI AKBAR (PHOTOMETRIC) | G76: 1209002 | H76: 44865 | I76: 47057 | J76: PIKPC170 | K76: 172.17.12.170 | L76: 172.17.128.117 | P76: ✓ | Y76: ACTIVE | Z76: SBTELECOM | AA76: 005/PO/HR&GA/GA/VIII/2022 | AB76: ASTRI | AC76: 0811-1067-925 | AD76: PC DEPRE AGUST 2022
A77: 73 | B77: FI-00701 | C77: ALL IN ONE | D77: TECHNICAL DIV | E77: PROD ENG | F77: KURNIA PERMADI | G77: 1406008 | H77: 44865 | I77: 47057 | J77: PIKPC168 | K77: 172.17.11.89 | L77: 172.17.118.93 | P77: ✓ | Y77: ACTIVE | Z77: SBTELECOM | AA77: 005/PO/HR&GA/GA/VIII/2022 | AB77: ASTRI | AC77: 0811-1067-925 | AD77: PC DEPRE AGUST 2022
A78: 74 | B78: FI-00704 | C78: ALL IN ONE | D78: TECHNICAL DIV | E78: PLANT & UTILITY | F78: ARIEF YUDISTIA YUDHAWAN | G78: 1011018 | H78: 44865 | I78: 47057 | J78: PIKPC166 | K78: - | L78: 172.17.118.83 | P78: ✓ | Y78: ACTIVE | Z78: CLARUS | AA78: 006/PO/HR&GA/GA/VIII/2022 | AB78: LUSY | AC78: 0856-9576-1612 | AD78: PC DEPRE AGUST 2022
A79: 75 | B79: FI-00705 | C79: ALL IN ONE | D79: HSE DIV | E79: HSE | F79: AGUNG IKSAN NUGRAHA | G79: 1708001 | H79: 44865 | I79: 47057 | J79: PIKPC167 | K79: 172.17.12.42 | L79: 172.17.128.47 | P79: ✓ | Y79: ACTIVE | Z79: CLARUS | AA79: 006/PO/HR&GA/GA/VIII/2022 | AB79: LUSY | AC79: 0856-9576-1612 | AD79: PC DEPRE AGUST 2022
A80: 76 | B80: FI-00707 | C80: ALL IN ONE | D80: PPIC DIV | E80: PPC | F80: MUHAMMAD RIZKI RIFALDY SOFYAN | G80: 2411003 | H80: 44895 | I80: 47087 | J80: PIK003 | K80: 172.17.11.33 | L80: 172.17.118.55 | P80: ✓ | Y80: ACTIVE | Z80: CLARUS | AA80: 019/PO/HR&GA/GA/ IX/2022 | AB80: LUSY | AC80: 0856-9576-1612 | AD80: PC DEPRE SEP 2022
A81: 77 | B81: FI-00708 | C81: ALL IN ONE | D81: PURCHASING DIV | E81: PURCHASING | F81: CHANDRA ADRIAN FAUJI | G81: 1302041 | H81: 44895 | I81: 47087 | J81: PIKPC169 | K81: 172.17.12.124 | L81: 172.17.128.80 | O81: ✓ | Y81: ACTIVE | Z81: CLARUS | AA81: 019/PO/HR&GA/GA/ IX/2022 | AB81: LUSY | AC81: 0856-9576-1612 | AD81: PC DEPRE SEP 2022
A82: 78 | B82: FI-00709 | C82: ALL IN ONE | D82: PPIC DIV | E82: LOGISTIK | F82: ATILAH | G82: 1702053 | H82: 44895 | I82: 47087 | J82: PIKCOM009 | K82: 172.17.20.106 | L82: 172.17.218.16 | P82: ✓ | Y82: ACTIVE | Z82: CLARUS | AA82: 020/PO/HR&GA/GA/IX/2022 | AB82: LUSY | AC82: 0856-9576-1612 | AD82: PC DEPRE SEP 2022
A83: 79 | B83: FI-00709 | C83: ALL IN ONE | D83: PPIC DIV | E83: LOGISTIK | F83: LALAN SUHERLAN | G83: 1108033 | H83: 44895 | I83: 47087 | J83: PIK005 | K83: 172.17.20.112 | L83: 172.17.218.26 | P83: ✓ | Y83: ACTIVE | Z83: CLARUS | AA83: 020/PO/HR&GA/GA/IX/2022 | AB83: LUSY | AC83: 0856-9576-1612 | AD83: PC DEPRE SEP 2022
A84: 80 | B84: FI-00710 | C84: ALL IN ONE | D84: PPIC DIV | E84: PPC | F84: BUNGA AYU PITALOKA | G84: 1109057 | H84: 44895 | I84: 47087 | J84: PIK004 | K84: 172.17.11.29 | L84: 172.17.118.48 | O84: ✓ | Y84: ACTIVE | Z84: CLARUS | AA84: 020/PO/HR&GA/GA/IX/2022 | AB84: LUSY | AC84: 0856-9576-1612 | AD84: PC DEPRE SEP 2022
A85: 81 | B85: FI-00711 | C85: ALL IN ONE | D85: PPIC DIV | E85: LOGISTIK | F85: PPIC PORTAL (SEPTA ANGGELA) | G85: 1608004 | H85: 44895 | I85: 47087 | J85: PIKPC163 | K85: 172.17.20.115 | L85: 172.17.218.17 | O85: ✓ | Y85: ACTIVE | Z85: CLARUS | AA85: 020/PO/HR&GA/GA/IX/2022 | AB85: LUSY | AC85: 0856-9576-1612 | AD85: PC DEPRE SEP 2022
A86: 82 | B86: FI-00706 | C86: ALL IN ONE | D86: MARKETING DIV | E86: CONTROL | F86: SIFA NURJANAH | G86: 2507006 | H86: 44896 | I86: 47088 | J86: PIKPC171 | K86: 172.17.12.104 | L86: 172.17.128.66 | P86: ✓ | Y86: ACTIVE | Z86: CLARUS | AA86: 019/PO/HR&GA/GA/ IX/2022 | AB86: LUSY | AC86: 0856-9576-1612 | AD86: PC DEPRE SEP 2022
A87: 83 | B87: FI-00718 | C87: ALL IN ONE | D87: MARKETING DIV | E87: SALES | F87: REZKI RAHMAD SURGAWAN | G87: 2301036 | H87: 44985 | I87: 47177 | J87: PIKPC174 | K87: 172.17.12.105 | L87: 172.17.128.73 | P87: ✓ | Y87: ACTIVE | Z87: CLARUS | AA87: 015/PO/HR&GA/GA/ XII/2022 | AB87: LUSY | AC87: 0856-9576-1612 | AD87: PC DEPRE DES 2022
A88: 84 | B88: FI-00719 | C88: ALL IN ONE | D88: MARKETING DIV | E88: CONTROL | F88: DINI DURROTUL AENI | G88: 2108002 | H88: 44985 | I88: 47177 | J88: PIKPC180 | K88: 172.17.12.106 | L88: 172.17.128.67 | P88: ✓ | Y88: ACTIVE | Z88: CLARUS | AA88: 015/PO/HR&GA/GA/ XII/2022 | AB88: LUSY | AC88: 0856-9576-1612 | AD88: PC DEPRE DES 2022
A89: 85 | B89: FI-00720 | C89: ALL IN ONE | D89: PURCHASING DIV | E89: PURCHASING | F89: NENG FITRIANI ROMADONA | G89: 2207013 | H89: 44985 | I89: 47177 | J89: PIKCOM010 | K89: 172.17.12.129 | L89: 172.17.128.88 | O89: ✓ | Y89: ACTIVE | Z89: CLARUS | AA89: 015/PO/HR&GA/GA/ XII/2022 | AB89: LUSY | AC89: 0856-9576-1612 | AD89: PC DEPRE DES 2022
A90: 86 | B90: FI-00721 | C90: LAPTOP | D90: GENERAL AFFAIR DIV | E90: IT LEGAL | F90: IR (SARI REZEKI) | G90: 1402011 | H90: 44985 | I90: 47177 | J90: PIKPC999 | K90: - | L90: DHCP | M90: ✓ | Y90: ACTIVE | Z90: UNICORN | AA90: 014/PO/HR&GA/GA/XII/2022 | AB90: AWENK | AC90: 0878-8284-8529 | AD90: LAPTOP ADD DES 2022
A91: 87 | B91: FI-00742 | C91: ALL IN ONE | D91: GENERAL AFFAIR DIV | E91: IT LEGAL | F91: MISBAHUL MUNIR | G91: 1701036 | H91: 45138 | I91: 47330 | J91: PIK1COM006 | K91: 172.17.12.60 | L91: 172.17.128.32 | P91: ✓ | Y91: ACTIVE | Z91: SBTELECOM | AA91: 027/PO/HR&GA/GA/IV/2022 | AB91: ASTRI | AC91: 0811-1067-925 | AD91: PC DEPRE APRIL 2022
A92: 88 | B92: FI-00743 | C92: ALL IN ONE | D92: INJECTION MOLD DIV | E92: MOLD MAKING | F92: CNC (TOMMY) | G92: 1406005 | H92: 45138 | I92: 47330 | J92: PIK1COM008 | K92: 172.17.20.130 | L92: 172.17.218.6 | P92: ✓ | Y92: ACTIVE | Z92: SBTELECOM | AA92: 027/PO/HR&GA/GA/IV/2022 | AB92: ASTRI | AC92: 0811-1067-925 | AD92: PC DEPRE APR 2022
A93: 89 | B93: FI-00744 | C93: ALL IN ONE | D93: GENERAL AFFAIR DIV | E93: IT LEGAL | F93: FARID BAGAS SAPUTRA | G93: 2512025 | H93: 45138 | I93: 47330 | J93: PIK1COM012 | K93: 172.17.12.62 | L93: 172.17.128.36 | P93: ✓ | Y93: ACTIVE | Z93: SBTELECOM | AA93: 027/PO/HR&GA/GA/IV/2022 | AB93: ASTRI | AC93: 0811-1067-925 | AD93: PC DEPRE APRIL 2022
A94: 90 | B94: FI-00747 | C94: ALL IN ONE | D94: TECHNICAL DIV | E94: PROD ENG | F94: RANDY RAHADIAN RAMADHAN | G94: 1011007 | H94: 45138 | I94: 47330 | J94: PIK1COM007 | K94: 172.17.11.90 | L94: 172.17.118.87 | P94: ✓ | Y94: ACTIVE | Z94: SBTELECOM | AA94: 026/PO/HR&GA/GA/IV/2023 | AB94: ASTRI | AC94: 0811-1067-925 | AD94: PC ADD APR 2023
A95: 91 | B95: FI-00748 | C95: ALL IN ONE | D95: PART PROCESS DIV | E95: ASSEMBLING | F95: AJI CHANDRA WINARTO | G95: 1310002 | H95: 45138 | I95: 47330 | J95: PIK1COM009 | K95: 172.17.11.68 | L95: 172.17.118.29 | P95: ✓ | Y95: ACTIVE | Z95: SBTELECOM | AA95: 026/PO/HR&GA/GA/IV/2023 | AB95: ASTRI | AC95: 0811-1067-925 | AD95: PC ADD APR 2023
A96: 92 | B96: FI-00749 | C96: ALL IN ONE | D96: TECHNICAL DIV | E96: PROD ENG | F96: DIAN EKA PRATAMA | G96: 1605039 | H96: 45138 | I96: 47330 | J96: PIK1COM010 | K96: 172.17.11.91 | L96: 172.17.118.92 | P96: ✓ | Y96: ACTIVE | Z96: SBTELECOM | AA96: 026/PO/HR&GA/GA/IV/2023 | AB96: ASTRI | AC96: 0811-1067-925 | AD96: PC ADD APR 2023
A97: 93 | B97: FI-00758 | C97: ALL IN ONE | D97: TECHNICAL DIV | E97: ASSY ENG | F97: LUTHFI NAUFAL RINALDI | G97: 2203035 | H97: 45198 | I97: 47390 | J97: PIK1COM013 | K97: 172.17.11.64 | L97: 172.17.118.70 | P97: ✓ | Y97: ACTIVE | Z97: SBTELECOM | AA97: 065/PO/HR&GA/GA/V/2023 | AB97: ASTRI | AC97: 0811-1067-925 | AD97: PC DEPRE MEI 2023
A98: 94 | B98: FI-00759 | C98: ALL IN ONE | D98: QA DIV | E98: QT | F98: DIAN FAHMI BAYU MURTI | G98: 1402014 | H98: 45198 | I98: 47390 | J98: PIK1COM014 | K98: 172.17.12.184 | L98: 172.17.128.119 | P98: ✓ | Y98: ACTIVE | Z98: SBTELECOM | AA98: 065/PO/HR&GA/GA/V/2023 | AB98: ASTRI | AC98: 0811-1067-925 | AD98: PC DEPRE MEI 2023
A99: 95 | B99: FI-00760 | C99: ALL IN ONE | D99: PPIC DIV | E99: PPC | F99: ROBI CAHYADI | G99: 1807021 | H99: 45198 | I99: 47390 | J99: PIK1COM015 | K99: 172.17.11.32 | L99: 172.17.118.53 | O99: ✓ | Y99: ACTIVE | Z99: SBTELECOM | AA99: 065/PO/HR&GA/GA/V/2023 | AB99: ASTRI | AC99: 0811-1067-925 | AD99: PC DEPRE MEI 2023
A100: 96 | B100: FI-00761 | C100: ALL IN ONE | D100: MARKETING DIV | E100: CONTROL | F100: DINDA CAHYA RUBIANTI | G100: 2305015 | H100: 45198 | I100: 47390 | J100: PIK1COM018 | K100: 172.17.12.112 | L100: 172.17.128.65 | P100: ✓ | Y100: ACTIVE | Z100: DARUMA | AA100: 049/PO/HR&GA/GA/V/2023 | AB100: RINDU | AC100: - | AD100: PC DEPRE MEI 2023
A101: 97 | B101: FI-00762 | C101: LAPTOP | D101: GENERAL AFFAIR DIV | E101: HRGA | F101: DEPARTEMEN HEAD HR&GA (HAFIDZ) | G101: 1101138 | H101: 45198 | I101: 47390 | J101: PIK1COM022 | K101: 172.17.12.71 | L101: DHCP | M101: ✓ | Y101: ACTIVE | Z101: CLARUS | AA101: 059/PO/HR&GA/GA/VI/2023 | AB101: LUSY | AC101: 0856-9576-1612 | AD101: PC DEPRE JUNI 2023
A102: 98 | B102: FI-00763 | C102: LAPTOP | D102: MARKETING DIV | E102: MARKETING DIV | F102: SHINSUKE TANAKA | G102: 2112043 | H102: 45198 | I102: 47390 | J102: PIK1COM030 | K102: 172.17.12.29 | L102: DHCP | M102: ✓ | Y102: ACTIVE | Z102: CLARUS | AA102: 059/PO/HR&GA/GA/VI/2023 | AB102: LUSY | AC102: 0856-9576-1612 | AD102: PC DEPRE JUNI 2023
A103: 99 | B103: FI-00764 | C103: LAPTOP | D103: INJECTION MOLD DIV | E103: INJECTION MOLD DIV | F103: HIROYOSHI OHI | G103: 2405001 | H103: 45198 | I103: 47390 | J103: PIK1COM028 | K103: 172.17.11.26 | L103: DHCP | M103: ✓ | Y103: ACTIVE | Z103: CLARUS | AA103: 059/PO/HR&GA/GA/VI/2023 | AB103: LUSY | AC103: 0856-9576-1612 | AD103: PC DEPRE JUNI 2023
...

Sheet  LAMA CCTV
G1: LIST ASSET CCTV | Q1: INFORMASI PEMBELIAN
B2: Tanggal Update: | F2: =TODAY() -> 46122
B3: User | L3: Tahun
B4: NO | C4: ZONA | D4: ID | E4: NO.ASSET | F4: TYPE | G4: DIVISI | H4: DEPT | I4: NAMA | J4: HOSTNAME | K4: IP ADDRESS | L4: Pemberlian | M4: Batas Depresiasi (5 Tahun) | N4: Batas Extend (+1 Tahun) | O4: Status | P4: PLAN DISPOSE | Q4: SUPPLIER | R4: NO PO | S4: AKUISISI | T4: PIC SUPPLIER | U4: KONTAK SUPPLIER | V4: MODEL | W4: SERIAL NUMBER
B5: 1 | C5: ZONA 1 | D5: CAM-01 | E5: FI-00999 | F5: OUTDOOR | G5: GENERAL AFFAIR | H5: IT LEGAL DEPT | I5: PARKIR MOBIL 1 | J5: PIK1CAM001 | K5: 172.17.101.42 | L5: 2025 | M5: =L5+5 -> 2030 | N5: =M5+1 -> 2031 | O5: ACTIVE | P5: 47880 | Q5: PILAR TEKNOLOGI SOLUSI | R5: 027/PO/HR&GA/GA/V/2024 | S5: 45931 | T5: ARGAN | U5: 085711148741
B6: 2 | C6: ZONA 1 | D6: CAM-02 | E6: FI-01000 | F6: OUTDOOR | G6: GENERAL AFFAIR | H6: IT LEGAL DEPT | I6: LOBY LUAR | J6: PIK1CAM002 | K6: 172.17.101.14 | L6: 2025 | M6: =L6+5 -> 2030 | N6: =M6+1 -> 2031 | O6: ACTIVE | P6: 47880 | Q6: PILAR TEKNOLOGI SOLUSI | R6: 027/PO/HR&GA/GA/V/2024 | S6: 45931 | T6: ARGAN | U6: 085711148741
B7: 3 | C7: ZONA 1 | D7: CAM-03 | E7: FI-01009 | F7: OUTDOOR | G7: GENERAL AFFAIR | H7: IT LEGAL DEPT | I7: DEPAN POSKO | J7: PIK1CAM003 | K7: 172.17.101.10 | L7: 2025 | M7: =L7+5 -> 2030 | N7: =M7+1 -> 2031 | O7: ACTIVE | P7: 47908 | Q7: PILAR TEKNOLOGI SOLUSI | R7: 076/PO/HR&GA/GA/V/2024 | S7: 45962 | T7: ARGAN | U7: 085711148741
B8: 4 | C8: ZONA 1 | D8: CAM-04 | E8: FI-00188 | F8: OUTDOOR | G8: GENERAL AFFAIR | H8: IT LEGAL DEPT | I8: PARKIR MOBIL 2 | J8: PIK1CAM004 | K8: 172.17.101.32 | L8: 2014 | M8: =L8+5 -> 2019 | N8: =M8+1 -> 2020 | O8: ACTIVE | P8: 46235 | Q8: SECOM INDONESIA | R8: 22/HRGA/PO/IX/2014 | S8: 42004
B9: 5 | C9: ZONA 1 | D9: CAM-05 | E9: FI-00728 | F9: OUTDOOR | G9: GENERAL AFFAIR | H9: IT LEGAL DEPT | I9: PARKIR MOTOR | J9: PIK1CAM005 | K9: 172.17.101.11 | L9: 2023 | M9: =L9+5 -> 2028 | N9: =M9+1 -> 2029 | O9: ACTIVE | P9: 47119 | Q9: SECOM INDONESIA | R9: 069/PO/HR&GA/GA/XI/2022 | S9: 45044 | T9: CAHYO
B10: 6 | C10: ZONA 1 | D10: CAM-06 | E10: FI-01010 | F10: OUTDOOR | G10: GENERAL AFFAIR | H10: IT LEGAL DEPT | I10: PARKIR MOBIL 3 | J10: PIK1CAM006 | K10: 172.17.101.41 | L10: 2025 | M10: =L10+5 -> 2030 | N10: =M10+1 -> 2031 | O10: ACTIVE | P10: 47908 | Q10: PILAR TEKNOLOGI SOLUSI | R10: 076/PO/HR&GA/GA/V/2024 | S10: 45962 | T10: ARGAN | U10: 085711148741
B11: 7 | C11: ZONA 1 | D11: CAM-07 | E11: FI-01053 | F11: OUTDOOR | G11: GENERAL AFFAIR | H11: IT LEGAL DEPT | I11: TPS 1 | J11: PIK1CAM007 | K11: 172.17.101.13 | L11: 2025 | M11: =L11+5 -> 2030 | N11: =M11+1 -> 2031 | O11: ACTIVE | P11: 47939 | Q11: PILAR TEKNOLOGI SOLUSI | R11: 035/PO/HR&GA/GA/ VI/2024 | S11: 45748 | T11: ARGAN | U11: 085711148741
B12: 8 | C12: ZONA 1 | D12: CAM-08 | E12: FI-01054 | F12: OUTDOOR | G12: GENERAL AFFAIR | H12: IT LEGAL DEPT | I12: TENT HOUSE 2 (BOILEER BELAKANG) | J12: PIK1CAM008 | K12: 172.17.101.20 | L12: 2025 | M12: =L12+5 -> 2030 | N12: =M12+1 -> 2031 | O12: ACTIVE | P12: 47939 | Q12: PILAR TEKNOLOGI SOLUSI | R12: 035/PO/HR&GA/GA/ VI/2024 | S12: 45748 | T12: ARGAN | U12: 085711148741
B13: 9 | C13: ZONA 1 | D13: CAM-09 | E13: FI-01007 | F13: DOME | G13: GENERAL AFFAIR | H13: IT LEGAL DEPT | I13: LOBBY DALAM | J13: PIK1CAM009 | K13: 172.17.101.4 | L13: 2025 | M13: =L13+5 -> 2030 | N13: =M13+1 -> 2031 | O13: ACTIVE | P13: 47969 | Q13: PILAR TEKNOLOGI SOLUSI | R13: 039/PO/HR&GA/GA/VIII/2024 | S13: 45962 | T13: ARGAN | U13: 085711148741
B14: 10 | C14: ZONA 1 | D14: CAM-10 | E14: FI-01046 | F14: DOME | G14: GENERAL AFFAIR | H14: IT LEGAL DEPT | I14: LORONG PANTRY | J14: PIK1CAM010 | K14: 172.17.101.22 | L14: 2025 | M14: =L14+5 -> 2030 | N14: =M14+1 -> 2031 | O14: ACTIVE | P14: 47969 | Q14: PILAR TEKNOLOGI SOLUSI | R14: 006/PO/HR&GA/GA/XI/2024 | S14: 45689 | T14: ARGAN | U14: 085711148741
B15: 11 | C15: ZONA 1 | D15: CAM-11 | E15: FI-00991 | F15: DOME | G15: GENERAL AFFAIR | H15: IT LEGAL DEPT | I15: OFFICE ADM 1 | J15: PIK1CAM011 | K15: 172.17.101.31 | L15: 2024 | M15: =L15+5 -> 2029 | N15: =M15+1 -> 2030 | O15: ACTIVE | P15: 48000 | Q15: PILAR TEKNOLOGI SOLUSI | R15: 075/PO/HR&GA/GA/V/2024 | S15: 45536 | T15: ARGAN | U15: 085711148741
B16: 12 | C16: ZONA 1 | D16: CAM-12 | E16: FI-00992 | F16: DOME | G16: GENERAL AFFAIR | H16: IT LEGAL DEPT | I16: OFFICE ADM 2 | J16: PIK1CAM012 | K16: 172.17.101.5 | L16: =2024 -> 2024 | M16: =L16+5 -> 2029 | N16: =M16+1 -> 2030 | O16: ACTIVE | P16: 48000 | Q16: PILAR TEKNOLOGI SOLUSI | R16: 075/PO/HR&GA/GA/V/2024 | S16: 45536 | T16: ARGAN | U16: 085711148741
B17: 13 | C17: ZONA 1 | D17: CAM-13 | E17: FI-00993 | F17: DOME | G17: GENERAL AFFAIR | H17: IT LEGAL DEPT | I17: SERVER ROOM | J17: PIK1CAM013 | K17: 172.17.11.43 | L17: =2024 -> 2024 | M17: =L17+5 -> 2029 | N17: =M17+1 -> 2030 | O17: ACTIVE | P17: 48030 | Q17: PILAR TEKNOLOGI SOLUSI | R17: 075/PO/HR&GA/GA/V/2024 | S17: 45536 | T17: ARGAN | U17: 085711148741
B18: 14 | C18: ZONA 1 | D18: CAM-14 | E18: FI-01027 | F18: DOME | G18: GENERAL AFFAIR | H18: IT LEGAL DEPT | I18: LORONG OFFICE 1 | J18: PIK1CAM014 | K18: 172.17.101.19 | L18: 2025 | M18: =L18+5 -> 2030 | N18: =M18+1 -> 2031 | O18: ACTIVE | P18: 48030 | Q18: PILAR TEKNOLOGI SOLUSI | R18: 065/PO/HR&GA/GA/IX/2024 | S18: 45658 | T18: ARGAN | U18: 085711148741
B19: 15 | C19: ZONA 1 | D19: CAM-15 | E19: BELUM AKUSISI | F19: OUTDOOR | G19: GENERAL AFFAIR | H19: IT LEGAL DEPT | I19: FINISH GOOD | J19: PIK1CAM015 | K19: 172.17.101.17 | L19: 2025 | M19: =L19+5 -> 2030 | N19: =M19+1 -> 2031 | O19: ACTIVE | P19: 45809 | Q19: PILAR TEKNOLOGI SOLUSI | R19: 072/PO/HR&GA/GA/VI/2025 | T19: ARGAN | U19: 085711148741 | V19: WV-S1136A | W19: YHV18108
B20: 16 | C20: ZONA 1 | D20: CAM-16 | E20: FI-01028 | F20: DOME | G20: GENERAL AFFAIR | H20: IT LEGAL DEPT | I20: OFFICE PROD | J20: PIK1CAM016 | K20: 172.17.101.21 | L20: 2025 | M20: =L20+5 -> 2030 | N20: =M20+1 -> 2031 | O20: ACTIVE | P20: 48061 | Q20: PILAR TEKNOLOGI SOLUSI | R20: 065/PO/HR&GA/GA/IX/2024 | S20: 45658 | T20: ARGAN | U20: 085711148741
B21: 17 | C21: ZONA 1 | D21: CAM-17 | E21: FI-00114 | F21: DOME | G21: GENERAL AFFAIR | H21: IT LEGAL DEPT | I21: TEST ROOM | J21: PIK1CAM017 | K21: 172.17.101.26 | L21: 2012 | M21: =L21+5 -> 2017 | N21: =M21+1 -> 2018 | O21: ACTIVE | P21: 46113 | Q21: SECOM INDOPRATAMA | R21: 010/GA/XII/2010REV | S21: 41000
B22: 18 | C22: ZONA 1 | D22: CAM-18 | E22: BELUM AKUSISI | F22: OUTDOOR | G22: GENERAL AFFAIR | H22: IT LEGAL DEPT | I22: AREA MTC | J22: PIK1CAM018 | K22: 172.17.101.12 | L22: 2025 | M22: =L22+5 -> 2030 | N22: =M22+1 -> 2031 | O22: ACTIVE | P22: 45748 | Q22: PILAR TEKNOLOGI SOLUSI | R22: 010/PO/HR&GA/GA/VI/2025 | T22: ARGAN | U22: 085711148741 | V22: WV-S1136A | W22: YHV8154
B23: 19 | C23: ZONA 1 | D23: CAM-19 | E23: FI-00114 | F23: OUTDOOR | G23: GENERAL AFFAIR | H23: IT LEGAL DEPT | I23: LORONG MEZANINE | J23: PIK1CAM019 | K23: 172.17.101.35 | L23: 2012 | M23: =L23+5 -> 2017 | N23: =M23+1 -> 2018 | O23: ACTIVE | P23: 46113 | Q23: SECOM INDOPRATAMA | R23: 010/GA/XII/2010REV | S23: 41000 | V23: WV-SP305
B24: 20 | C24: ZONA 1 | D24: CAM-20 | E24: FI-00114 | F24: OUTDOOR | G24: GENERAL AFFAIR | H24: IT LEGAL DEPT | I24: MEZANI STORE | J24: PIK1CAM020 | K24: 172.17.101.36 | L24: 2012 | M24: =L24+5 -> 2017 | N24: =M24+1 -> 2018 | O24: ACTIVE | P24: 46082 | Q24: SECOM INDOPRATAMA | R24: 010/GA/XII/2010REV | S24: 41000 | V24: WV-SP305
B25: 21 | C25: ZONA 1 | D25: CAM-21 | E25: FI-00114 | F25: OUTDOOR | G25: GENERAL AFFAIR | H25: IT LEGAL DEPT | I25: MEZANI LIFT | J25: PIK1CAM021 | K25: 172.17.101.33 | L25: 2012 | M25: =L25+5 -> 2017 | N25: =M25+1 -> 2018 | O25: ACTIVE | P25: 46143 | Q25: SECOM INDOPRATAMA | R25: 010/GA/XII/2010REV | S25: 41000 | V25: WV-SP305
B26: 22 | C26: ZONA 1 | D26: CAM-22 | E26: FI-00114 | F26: OUTDOOR | G26: GENERAL AFFAIR | H26: IT LEGAL DEPT | I26: INJ MULTI COLOR | J26: PIK1CAM022 | K26: 172.17.101.25 | L26: 2012 | M26: =L26+5 -> 2017 | N26: =M26+1 -> 2018 | O26: ACTIVE | P26: 46143 | Q26: SECOM INDOPRATAMA | R26: 010/GA/XII/2010REV | S26: 41000 | V26: WV-SP305
B27: 23 | C27: ZONA 1 | D27: CAM-23 | E27: FI-00114 | F27: OUTDOOR | G27: GENERAL AFFAIR | H27: IT LEGAL DEPT | I27: INJECTION LENSA | J27: PIK1CAM023 | K27: 172.17.101.24 | L27: 2012 | M27: =L27+5 -> 2017 | N27: =M27+1 -> 2018 | O27: ACTIVE | P27: 46174 | Q27: SECOM INDOPRATAMA | R27: 010/GA/XII/2010REV | S27: 41000 | V27: WV-SP305
B28: 24 | C28: ZONA 1 | D28: CAM-24 | E28: BELUM AKUSISI | F28: OUTDOOR | G28: GENERAL AFFAIR | H28: IT LEGAL DEPT | I28: INJECT BMC | J28: PIK1CAM024 | K28: 172.17.101.40 | L28: 2025 | M28: =L28+5 -> 2030 | N28: =M28+1 -> 2031 | O28: ACTIVE | P28: 45809 | Q28: PILAR TEKNOLOGI SOLUSI | R28: 072/PO/HR&GA/GA/VI/2025 | T28: ARGAN | U28: 085711148741 | V28: WV-S1136A | W28: YHV18109
B29: 25 | C29: ZONA 1 | D29: CAM-25 | E29: FI-00333 | F29: OUTDOOR | G29: GENERAL AFFAIR | H29: IT LEGAL DEPT | I29: MATERIAL RESIN 1 | J29: PIK1CAM025 | K29: 172.17.101.27 | L29: 2016 | M29: =L29+5 -> 2021 | N29: =M29+1 -> 2022 | O29: ACTIVE | P29: 46235
B30: 26 | C30: ZONA 1 | D30: CAM-26 | E30: FI-01045 | F30: DOME | G30: GENERAL AFFAIR | H30: IT LEGAL DEPT | I30: MATERIAL RESIN 2 | J30: PIK1CAM026 | K30: 172.17.101.6 | L30: 2025 | M30: =L30+5 -> 2030 | N30: =M30+1 -> 2031 | O30: ACTIVE | P30: 48061 | Q30: PILAR TEKNOLOGI SOLUSI | R30: 020/PO/HR&GA/GA/XI/2024 | S30: 45689 | T30: ARGAN | U30: 085711148741
B31: 27 | C31: ZONA 1 | D31: CAM-27 | E31: FI-00114 | F31: OUTDOOR | G31: GENERAL AFFAIR | H31: IT LEGAL DEPT | I31: PART STORE | J31: PIK1CAM027 | K31: 172.17.101.7 | L31: 2012 | M31: =L31+5 -> 2017 | N31: =M31+1 -> 2018 | O31: ACTIVE | P31: 46054 | Q31: SECOM INDOPRATAMA | R31: 010/GA/XII/2010REV | S31: 41000 | V31: WV-SP305
B32: 28 | C32: ZONA 1 | D32: CAM-28 | E32: FI-00184 | F32: OUTDOOR | G32: GENERAL AFFAIR | H32: IT LEGAL DEPT | I32: LOADING 1 | J32: PIK1CAM028 | K32: 172.17.101.18 | L32: 2014 | M32: =L32+5 -> 2019 | N32: =M32+1 -> 2020 | O32: ACTIVE | P32: 46082 | Q32: SECOM INDONESIA | R32: 22/HRGA/PO/IX/2014 | S32: 42004
B33: 29 | C33: ZONA 1 | D33: CAM-29 | E33: FI-00185 | F33: OUTDOOR | G33: GENERAL AFFAIR | H33: IT LEGAL DEPT | I33: LOADING 2 | J33: PIK1CAM029 | K33: 172.17.101.23 | L33: 2014 | M33: =L33+5 -> 2019 | N33: =M33+1 -> 2020 | O33: ACTIVE | P33: 45901 | Q33: SECOM INDONESIA | R33: 22/HRGA/PO/IX/2014 | S33: 42004
B34: 30 | C34: ZONA 1 | D34: CAM-30 | E34: FI-00186 | F34: OUTDOOR | G34: GENERAL AFFAIR | H34: IT LEGAL DEPT | I34: LOADING 3 | J34: PIK1CAM030 | K34: 172.17.101.30 | L34: 2014 | M34: =L34+5 -> 2019 | N34: =M34+1 -> 2020 | O34: ACTIVE | P34: 45931 | Q34: SECOM INDONESIA | R34: 22/HRGA/PO/IX/2014 | S34: 42004
B35: 31 | C35: ZONA 1 | D35: CAM-31 | E35: FI-00111 | F35: OUTDOOR | G35: GENERAL AFFAIR | H35: IT LEGAL DEPT | I35: INCOME STORE | J35: PIK1CAM031 | K35: 172.17.101.9 | L35: 2012 | M35: =L35+5 -> 2017 | N35: =M35+1 -> 2018 | O35: ACTIVE | P35: 46174 | Q35: SECOM INDOPRATAMA | R35: 010/GA/XII/2010REV | S35: 41000 | V35: WV-SF335
B36: 32 | C36: ZONA 1 | D36: CAM-32 | E36: FI-00923 | F36: DOME | G36: GENERAL AFFAIR | H36: IT LEGAL DEPT | I36: OFFICE QLTY1 | J36: PIK1CAM032 | K36: 172.17.101.65 | L36: 2023 | M36: =L36+5 -> 2028 | N36: =M36+1 -> 2029 | O36: ACTIVE | P36: 47119 | Q36: SECOM INDONESIA | R36: 026/PO/HR&GA/GA/IX/2023 | S36: 45289 | T36: CAHYO | V36: WV-U2130L
B37: 33 | C37: ZONA 1 | D37: CAM-33 | E37: FI-01047 | F37: DOME | G37: GENERAL AFFAIR | H37: IT LEGAL DEPT | I37: OFFICE QLTY2 | J37: PIK1CAM033 | K37: 172.17.101.64 | L37: 2025 | M37: =L37+5 -> 2030 | N37: =M37+1 -> 2031 | O37: ACTIVE | P37: 48092 | Q37: PILAR TEKNOLOGI SOLUSI | R37: 006/PO/HR&GA/GA/XI/2024 | S37: 45689 | T37: ARGAN | U37: 085711148741
B38: 34 | C38: ZONA 1 | D38: CAM-34 | E38: FI-01008 | F38: DOME | G38: GENERAL AFFAIR | H38: IT LEGAL DEPT | I38: LORONG QLTY | J38: PIK1CAM034 | K38: 172.17.101.63 | L38: 2025 | M38: =L38+5 -> 2030 | N38: =M38+1 -> 2031 | O38: ACTIVE | P38: 48092 | Q38: PILAR TEKNOLOGI SOLUSI | R38: 039/PO/HR&GA/GA/VIII/2024 | S38: 45962 | T38: ARGAN | U38: 085711148741
B39: 35 | C39: ZONA 1 | D39: CAM-35 | E39: BELUM AKUSISI | F39: OUTDOOR | G39: GENERAL AFFAIR | H39: IT LEGAL DEPT | I39: VIBRASI ROOM | J39: PIK1CAM035 | K39: 172.17.101.44 | L39: 2025 | M39: =L39+5 -> 2030 | N39: =M39+1 -> 2031 | O39: ACTIVE | P39: 45778 | Q39: PILAR TEKNOLOGI SOLUSI | R39: 010/PO/HR&GA/GA/VI/2025 | T39: ARGAN | U39: 085711148741 | V39: WV-S1136A | W39: YHV18105
B40: 36 | C40: ZONA 1 | D40: CAM-36 | E40: FI-01078 | F40: DOME | G40: GENERAL AFFAIR | H40: IT LEGAL DEPT | I40: SERVER ROOM2 | J40: PIK1CAM036 | K40: 172.17.101.50 | L40: 2025 | M40: =L40+5 -> 2030 | N40: =M40+1 -> 2031 | O40: ACTIVE | P40: 48122 | Q40: PILAR TEKNOLOGI SOLUSI | R40: 038/PO/HR&GA/GA/VII/2024 | S40: 45778 | T40: ARGAN | U40: 085711148741
B41: 37 | C41: ZONA 1 | D41: CAM-37 | E41: BELUM AKUSISI | F41: OUTDOOR | G41: GENERAL AFFAIR | H41: IT LEGAL DEPT | I41: MESIN SCRAP | J41: PIK1CAM037 | K41: 172.17.101.54 | L41: 2025 | M41: =L41+5 -> 2030 | N41: =M41+1 -> 2031 | O41: ACTIVE | P41: 45809 | Q41: PILAR TEKNOLOGI SOLUSI | R41: 072/PO/HR&GA/GA/VI/2025 | T41: ARGAN | U41: 085711148741 | V41: WV-S1136A | W41: YHV18104
B42: 38 | C42: ZONA 1 | D42: CAM-38 | E42: FI-00629 | F42: OUTDOOR | G42: GENERAL AFFAIR | H42: IT LEGAL DEPT | I42: TENTHOUSE 1 | J42: PIK1CAM038 | K42: 172.17.101.94 | L42: 2021 | M42: =L42+5 -> 2026 | N42: =M42+1 -> 2027 | O42: ACTIVE | P42: 46692 | Q42: CLARUS INNOVANCE TEKNOLOGI | R42: 012/PO/HR&GA/GA/VII/2021 | S42: 44530 | T42: TUSLAM
B43: 39 | C43: ZONA 1 | D43: CAM-39 | E43: FI-00114 | F43: OUTDOOR | G43: GENERAL AFFAIR | H43: IT LEGAL DEPT | I43: PAINT STORE | J43: PIK1CAM039 | K43: 172.17.101.15 | L43: 2012 | M43: =L43+5 -> 2017 | N43: =M43+1 -> 2018 | O43: ACTIVE | P43: 46054 | Q43: SECOM INDOPRATAMA | R43: 010/GA/XII/2010REV | S43: 41000 | V43: WV-SP305
B44: 40 | C44: ZONA 2 | D44: CAM-01 | E44: FI-00498 | F44: OUTDOOR | G44: GENERAL AFFAIR | H44: IT LEGAL DEPT | I44: GATE POS 1 | J44: PIK1CAM040 | K44: 172.17.101.61 | L44: 2019 | M44: =L44+5 -> 2024 | N44: =M44+1 -> 2025 | O44: ACTIVE | P44: 45870 | Q44: SECOM INDONESIA | R44: '026/PO/HR&GA/GA/I/2019 | S44: 43707
B45: 41 | C45: ZONA 2 | D45: CAM-02 | E45: FI-00498 | F45: OUTDOOR | G45: GENERAL AFFAIR | H45: IT LEGAL DEPT | I45: JALAN POS 1 | J45: PIK1CAM041 | K45: 172.17.101.62 | L45: 2019 | M45: =L45+5 -> 2024 | N45: =M45+1 -> 2025 | O45: ACTIVE | P45: 45870 | Q45: SECOM INDONESIA | R45: '026/PO/HR&GA/GA/I/2019 | S45: 43707
B46: 42 | C46: ZONA 2 | D46: CAM-03 | E46: FI-00498 | F46: OUTDOOR | G46: GENERAL AFFAIR | H46: IT LEGAL DEPT | I46: TPS DEPAN | J46: PIK1CAM042 | K46: 172.17.101.85 | L46: 2019 | M46: =L46+5 -> 2024 | N46: =M46+1 -> 2025 | O46: ACTIVE | P46: 46054 | Q46: SECOM INDONESIA | R46: '026/PO/HR&GA/GA/I/2019 | S46: 43707
B47: 43 | C47: ZONA 2 | D47: CAM-04 | E47: FI-00498 | F47: OUTDOOR | G47: GENERAL AFFAIR | H47: IT LEGAL DEPT | I47: TPS BELAKANG 1 | J47: PIK1CAM043 | K47: 172.17.101.86 | L47: 2019 | M47: =L47+5 -> 2024 | N47: =M47+1 -> 2025 | O47: ACTIVE | P47: 45931 | Q47: SECOM INDONESIA | R47: '026/PO/HR&GA/GA/I/2019 | S47: 43707
B48: 44 | C48: ZONA 2 | D48: CAM-05 | E48: FI-00498 | F48: OUTDOOR | G48: GENERAL AFFAIR | H48: IT LEGAL DEPT | I48: TPS BELAKANG 2 | J48: PIK1CAM044 | K48: 172.17.101.87 | L48: 2019 | M48: =L48+5 -> 2024 | N48: =M48+1 -> 2025 | O48: ACTIVE | P48: 45931 | Q48: SECOM INDONESIA | R48: '026/PO/HR&GA/GA/I/2019 | S48: 43707
B49: 45 | C49: ZONA 2 | D49: CAM-06 | E49: FI-00498 | F49: OUTDOOR | G49: GENERAL AFFAIR | H49: IT LEGAL DEPT | I49: POS BELAKANG | J49: PIK1CAM045 | K49: 172.17.101.82 | L49: 2019 | M49: =L49+5 -> 2024 | N49: =M49+1 -> 2025 | O49: ACTIVE | P49: 46023 | Q49: SECOM INDONESIA | R49: '026/PO/HR&GA/GA/I/2019 | S49: 43707
B50: 46 | C50: ZONA 2 | D50: CAM-07 | E50: FI-00498 | F50: OUTDOOR | G50: GENERAL AFFAIR | H50: IT LEGAL DEPT | I50: FENCE BELAKANG | J50: PIK1CAM046 | K50: 172.17.101.81 | L50: 2019 | M50: =L50+5 -> 2024 | N50: =M50+1 -> 2025 | O50: ACTIVE | P50: 46023 | Q50: SECOM INDONESIA | R50: '026/PO/HR&GA/GA/I/2019 | S50: 43707
B51: 47 | C51: ZONA 2 | D51: CAM-08 | E51: FI-01086 | F51: DOME 360 | G51: GENERAL AFFAIR | H51: IT LEGAL DEPT | I51: LORONG LOKER 1 | J51: PIK1CAM047 | K51: 172.17.101.58 | L51: 2025 | M51: =L51+5 -> 2030 | N51: =M51+1 -> 2031 | O51: ACTIVE | P51: 47849 | Q51: PILAR TEKNOLOGI SOLUSI | R51: 017/PO/HR&GA/GA/XIII/2024 | S51: 45839 | T51: ARGAN | U51: 085711148741
B52: 48 | C52: ZONA 2 | D52: CAM-09 | E52: FI-01087 | F52: DOME 360 | G52: GENERAL AFFAIR | H52: IT LEGAL DEPT | I52: LORONG LOKER 2 | J52: PIK1CAM048 | K52: 172.17.101.57 | L52: 2025 | M52: =L52+5 -> 2030 | N52: =M52+1 -> 2031 | O52: ACTIVE | P52: 47849 | Q52: PILAR TEKNOLOGI SOLUSI | R52: 017/PO/HR&GA/GA/XIII/2024 | S52: 45839 | T52: ARGAN | U52: 085711148741
B53: 49 | C53: ZONA 2 | D53: CAM-10 | E53: FI-00498 | F53: OUTDOOR | G53: GENERAL AFFAIR | H53: IT LEGAL DEPT | I53: ABSENSI MALE | J53: PIK1CAM049 | K53: 172.17.101.55 | L53: 2019 | M53: =L53+5 -> 2024 | N53: =M53+1 -> 2025 | O53: ACTIVE | P53: 45931 | Q53: SECOM INDONESIA | R53: '026/PO/HR&GA/GA/I/2019 | S53: 43707
B54: 50 | C54: ZONA 2 | D54: CAM-11 | E54: FI-00498 | F54: OUTDOOR | G54: GENERAL AFFAIR | H54: IT LEGAL DEPT | I54: DOUBLE CHECK | J54: PIK1CAM050 | K54: 172.17.101.16 | L54: 2019 | M54: =L54+5 -> 2024 | N54: =M54+1 -> 2025 | O54: ACTIVE | P54: 45992 | Q54: SECOM INDONESIA | R54: '026/PO/HR&GA/GA/I/2019 | S54: 43707
B55: 51 | C55: ZONA 2 | D55: CAM-12 | E55: FI-00498 | F55: OUTDOOR | G55: GENERAL AFFAIR | H55: IT LEGAL DEPT | I55: LORONG PART MTRL | J55: PIK1CAM051 | K55: 172.17.101.69 | L55: 2019 | M55: =L55+5 -> 2024 | N55: =M55+1 -> 2025 | O55: ACTIVE | P55: 45962 | Q55: SECOM INDONESIA | R55: '026/PO/HR&GA/GA/I/2019 | S55: 43707
B56: 52 | C56: ZONA 2 | D56: CAM-13 | E56: FI-00498 | F56: OUTDOOR | G56: GENERAL AFFAIR | H56: IT LEGAL DEPT | I56: TANGGA BAWAH KTN | J56: PIK1CAM052 | K56: 172.17.101.53 | L56: 2019 | M56: =L56+5 -> 2024 | N56: =M56+1 -> 2025 | O56: ACTIVE | P56: 45931 | Q56: SECOM INDONESIA | R56: '026/PO/HR&GA/GA/I/2019 | S56: 43707
B57: 53 | C57: ZONA 2 | D57: CAM-14 | E57: FI-01051 | F57: DOME | G57: GENERAL AFFAIR | H57: IT LEGAL DEPT | I57: TANGGA KANTIN 1 | J57: PIK1CAM053 | K57: 172.17.101.49 | L57: 2025 | M57: =L57+5 -> 2030 | N57: =M57+1 -> 2031 | O57: ACTIVE | P57: 48122 | Q57: PILAR TEKNOLOGI SOLUSI | R57: 016/PO/HR&GA/GA/XII/2024 | S57: 45748 | T57: ARGAN | U57: 085711148741
B58: 54 | C58: ZONA 2 | D58: CAM-15 | E58: FI-01052 | F58: DOME | G58: GENERAL AFFAIR | H58: IT LEGAL DEPT | I58: TANGGA KANTIN 2 | J58: PIK1CAM054 | K58: 172.17.101.56 | L58: 2025 | M58: =L58+5 -> 2030 | N58: =M58+1 -> 2031 | O58: ACTIVE | P58: 48153 | Q58: PILAR TEKNOLOGI SOLUSI | R58: 029/PO/HR&GA/GA/XI/2024 | S58: 45748 | T58: ARGAN | U58: 085711148741
B59: 55 | C59: ZONA 2 | D59: CAM-16 | E59: FI-00498 | F59: OUTDOOR | G59: GENERAL AFFAIR | H59: IT LEGAL DEPT | I59: LIFT KANTIN BWH | J59: PIK1CAM055 | K59: 172.17.101.62 | L59: 2019 | M59: =L59+5 -> 2024 | N59: =M59+1 -> 2025 | O59: ACTIVE | P59: 46266 | Q59: SECOM INDONESIA | R59: '026/PO/HR&GA/GA/I/2019 | S59: 43707
B60: 56 | C60: ZONA 2 | D60: CAM-17 | E60: FI-01057 | F60: DOME | G60: GENERAL AFFAIR | H60: IT LEGAL DEPT | I60: KANTIN LIFT | J60: PIK1CAM056 | K60: 172.17.101.47 | L60: 2025 | M60: =L60+5 -> 2030 | N60: =M60+1 -> 2031 | O60: ACTIVE | P60: 48153 | Q60: PILAR TEKNOLOGI SOLUSI | R60: 028/PO/HR&GA/GA/XI/2024 | S60: 45748 | T60: ARGAN | U60: 085711148741
B61: 57 | C61: ZONA 2 | D61: CAM-18 | E61: FI-01058 | F61: DOME | G61: GENERAL AFFAIR | H61: IT LEGAL DEPT | I61: KANTIN SPM | J61: PIK1CAM057 | K61: 172.17.101.48 | L61: 2025 | M61: =L61+5 -> 2030 | N61: =M61+1 -> 2031 | O61: ACTIVE | P61: 48183 | Q61: PILAR TEKNOLOGI SOLUSI | R61: 028/PO/HR&GA/GA/XI/2024 | S61: 45748 | T61: ARGAN | U61: 085711148741
B62: 58 | C62: ZONA 2 | D62: CAM-19 | E62: FI-01052 | F62: DOME | G62: GENERAL AFFAIR | H62: IT LEGAL DEPT | I62: KANTIN TC | J62: PIK1CAM058 | K62: 172.17.101.45 | L62: 2025 | M62: =L62+5 -> 2030 | N62: =M62+1 -> 2031 | O62: ACTIVE | P62: 48183 | Q62: PILAR TEKNOLOGI SOLUSI | R62: 016/PO/HR&GA/GA/XII/2024 | S62: 45748 | T62: ARGAN | U62: 085711148741
B63: 59 | C63: ZONA 2 | D63: CAM-20 | E63: BELUM AKUSISI | F63: OUTDOOR | G63: GENERAL AFFAIR | H63: IT LEGAL DEPT | I63: TNGGA MEZANIN TC | J63: PIK1CAM059 | K63: 172.17.101.68 | L63: 2025 | M63: =L63+5 -> 2030 | N63: =M63+1 -> 2031 | O63: ACTIVE | P63: 45839 | Q63: PILAR TEKNOLOGI SOLUSI | R63: 022/PO/HR&GA/GA/VII/2025 | T63: ARGAN | U63: 085711148741 | V63: WV-S1136A | W63: YHV18156
B64: 60 | C64: ZONA 2 | D64: CAM-21 | E64: FI-00498 | F64: OUTDOOR | G64: GENERAL AFFAIR | H64: IT LEGAL DEPT | I64: LORONG MUSHOLA 1 | J64: PIK1CAM060 | K64: 172.17.101.59 | L64: 2019 | M64: =L64+5 -> 2024 | N64: =M64+1 -> 2025 | O64: ACTIVE | P64: 45931 | Q64: SECOM INDONESIA | R64: '026/PO/HR&GA/GA/I/2019 | S64: 43707
B65: 61 | C65: ZONA 2 | D65: CAM-22 | E65: FI-01056 | F65: DOME | G65: GENERAL AFFAIR | H65: IT LEGAL DEPT | I65: MUSHOLA DALAM | J65: PIK1CAM061 | K65: 172.17.101.46 | L65: 2025 | M65: =L65+5 -> 2030 | N65: =M65+1 -> 2031 | O65: ACTIVE | P65: 48214 | Q65: PILAR TEKNOLOGI SOLUSI | R65: 029/PO/HR&GA/GA/XI/2024 | S65: 45748 | T65: ARGAN | U65: 085711148741
B66: 62 | C66: - | D66: CAM-23 | E66: - | F66: - | G66: - | H66: - | I66: NO CAM | J66: - | K66: - | L66: - | M66: - | N66: - | O66: - | P66: -
B67: 63 | C67: ZONA 2 | D67: CAM-24 | E67: FI-00498 | F67: OUTDOOR | G67: GENERAL AFFAIR | H67: IT LEGAL DEPT | I67: TANGGA MUSHOLA | J67: PIK1CAM063 | K67: 172.17.101.52 | L67: 2019 | M67: =L67+5 -> 2024 | N67: =M67+1 -> 2025 | O67: ACTIVE | P67: 46266 | Q67: SECOM INDONESIA | R67: '026/PO/HR&GA/GA/I/2019 | S67: 43707
B68: 64 | C68: ZONA 2 | D68: CAM-25 | E68: FI-00498 | F68: OUTDOOR | G68: GENERAL AFFAIR | H68: IT LEGAL DEPT | I68: LORONG HUB ZONA | J68: PIK1CAM064 | K68: 172.17.101.70 | L68: 2019 | M68: =L68+5 -> 2024 | N68: =M68+1 -> 2025 | O68: ACTIVE | P68: 46296 | Q68: SECOM INDONESIA | R68: '026/PO/HR&GA/GA/I/2019 | S68: 43707
B69: 65 | C69: ZONA 2 | D69: CAM-26 | E69: FI-00498 | F69: OUTDOOR | G69: GENERAL AFFAIR | H69: IT LEGAL DEPT | I69: PART INVENTORY 1 | J69: PIK1CAM065 | K69: 172.17.101.71 | L69: 2019 | M69: =L69+5 -> 2024 | N69: =M69+1 -> 2025 | O69: ACTIVE | P69: 46296 | Q69: SECOM INDONESIA | R69: '026/PO/HR&GA/GA/I/2019 | S69: 43707
B70: 66 | C70: ZONA 2 | D70: CAM-27 | E70: FI-00498 | F70: OUTDOOR | G70: GENERAL AFFAIR | H70: IT LEGAL DEPT | I70: PART ASSY 1 | J70: PIK1CAM066 | K70: 172.17.101.72 | L70: 2019 | M70: =L70+5 -> 2024 | N70: =M70+1 -> 2025 | O70: ACTIVE | P70: 46327 | Q70: SECOM INDONESIA | R70: '026/PO/HR&GA/GA/I/2019 | S70: 43707
B71: 67 | C71: ZONA 2 | D71: CAM-28 | E71: FI-00498 | F71: OUTDOOR | G71: GENERAL AFFAIR | H71: IT LEGAL DEPT | I71: PART ASSY 2 | J71: PIK1CAM067 | K71: 172.17.101.73 | L71: 2019 | M71: =L71+5 -> 2024 | N71: =M71+1 -> 2025 | O71: ACTIVE | P71: 46327 | Q71: SECOM INDONESIA | R71: '026/PO/HR&GA/GA/I/2019 | S71: 43707
B72: 68 | C72: ZONA 2 | D72: CAM-29 | E72: FI-00498 | F72: OUTDOOR | G72: GENERAL AFFAIR | H72: IT LEGAL DEPT | I72: PART INVENTORY 2 | J72: PIK1CAM068 | K72: 172.17.101.74 | L72: 2019 | M72: =L72+5 -> 2024 | N72: =M72+1 -> 2025 | O72: ACTIVE | P72: 46357 | Q72: SECOM INDONESIA | R72: '026/PO/HR&GA/GA/I/2019 | S72: 43707
B73: 69 | C73: ZONA 2 | D73: CAM-30 | E73: FI-00498 | F73: OUTDOOR | G73: GENERAL AFFAIR | H73: IT LEGAL DEPT | I73: PART INVENTORY 3 | J73: PIK1CAM069 | K73: 172.17.101.75 | L73: 2019 | M73: =L73+5 -> 2024 | N73: =M73+1 -> 2025 | O73: ACTIVE | P73: 46357 | Q73: SECOM INDONESIA | R73: '026/PO/HR&GA/GA/I/2019 | S73: 43707
B74: 70 | C74: ZONA 2 | D74: CAM-31 | E74: FI-00498 | F74: OUTDOOR | G74: GENERAL AFFAIR | H74: IT LEGAL DEPT | I74: PART INVENTORY 4 | J74: PIK1CAM070 | K74: 172.17.101.76 | L74: 2019 | M74: =L74+5 -> 2024 | N74: =M74+1 -> 2025 | O74: ACTIVE | P74: 46388 | Q74: SECOM INDONESIA | R74: '026/PO/HR&GA/GA/I/2019 | S74: 43707
B75: 71 | C75: ZONA 2 | D75: CAM-32 | E75: FI-00498 | F75: OUTDOOR | G75: GENERAL AFFAIR | H75: IT LEGAL DEPT | I75: PART INVENTORY 5 | J75: PIK1CAM071 | K75: 172.17.101.77 | L75: 2019 | M75: =L75+5 -> 2024 | N75: =M75+1 -> 2025 | O75: ACTIVE | P75: 46388 | Q75: SECOM INDONESIA | R75: '026/PO/HR&GA/GA/I/2019 | S75: 43707
B76: 72 | C76: ZONA 2 | D76: CAM-33 | E76: FI-00498 | F76: OUTDOOR | G76: GENERAL AFFAIR | H76: IT LEGAL DEPT | I76: PART INVENTORY 6 | J76: PIK1CAM072 | K76: 172.17.101.78 | L76: 2019 | M76: =L76+5 -> 2024 | N76: =M76+1 -> 2025 | O76: ACTIVE | P76: 46419 | Q76: SECOM INDONESIA | R76: '026/PO/HR&GA/GA/I/2019 | S76: 43707
B77: 73 | C77: ZONA 2 | D77: CAM-34 | E77: FI-00498 | F77: OUTDOOR | G77: GENERAL AFFAIR | H77: IT LEGAL DEPT | I77: GATE ANTAR ZONA | J77: PIK1CAM073 | K77: 172.17.101.80 | L77: 2019 | M77: =L77+5 -> 2024 | N77: =M77+1 -> 2025 | O77: ACTIVE | P77: 46419 | Q77: SECOM INDONESIA | R77: '026/PO/HR&GA/GA/I/2019 | S77: 43707
B78: 74 | C78: ZONA 2 | D78: CAM-35 | E78: FI-00498 | F78: OUTDOOR | G78: GENERAL AFFAIR | H78: IT LEGAL DEPT | I78: INVENTORY TENGAH | J78: PIK1CAM074 | K78: 172.17.101.79 | L78: 2019 | M78: =L78+5 -> 2024 | N78: =M78+1 -> 2025 | O78: ACTIVE | P78: 46447 | Q78: SECOM INDONESIA | R78: '026/PO/HR&GA/GA/I/2019 | S78: 43707
... B80: 76 | C80: ZONA 2 | D80: CAM-37 | E80: FI-00498 | F80: OUTDOOR | G80: GENERAL AFFAIR | H80: IT LEGAL DEPT | I80: LOAD INVENTORY 2 | J80: PIK1CAM076 | K80: 172.17.101.29 | L80: 2019 | M80: =L80+5 -> 2024 | N80: =M80+1 -> 2025 | O80: ACTIVE | P80: 46478 | Q80: SECOM INDONESIA | R80: '026/PO/HR&GA/GA/I/2019 | S80: 43707
B81: 77 | C81: ZONA 2 | D81: CAM-38 | E81: FI-00268 | F81: OUTDOOR | G81: GENERAL AFFAIR | H81: IT LEGAL DEPT | I81: LOADING DOCK 1 | J81: PIK1CAM077 | K81: 172.17.101.38 | L81: 2019 | M81: =L81+5 -> 2024 | N81: =M81+1 -> 2025 | O81: ACTIVE | P81: 46478 | Q81: SECOM INDONESIA | R81: 302/PO/HR&GA/GA/XII/2015 | S81: 42521 | T81: CAHYO | V81: WV-SPN310
B82: 78 | C82: ZONA 2 | D82: CAM-39 | E82: FI-00268 | F82: OUTDOOR | G82: GENERAL AFFAIR | H82: IT LEGAL DEPT | I82: LOADING DOCK 3 | J82: PIK1CAM078 | K82: 172.17.101.28 | L82: 2019 | M82: =L82+5 -> 2024 | N82: =M82+1 -> 2025 | O82: ACTIVE | P82: 46508 | Q82: SECOM INDONESIA | R82: 302/PO/HR&GA/GA/XII/2015 | S82: 42521 | T82: CAHYO | V82: WV-SPN310
B83: 79 | C83: ZONA 2 | D83: CAM-40 | E83: FI-00268 | F83: OUTDOOR | G83: GENERAL AFFAIR | H83: IT LEGAL DEPT | I83: LOADING DOCK 4 | J83: PIK1CAM079 | K83: 172.17.101.37 | L83: 2019 | M83: =L83+5 -> 2024 | N83: =M83+1 -> 2025 | O83: ACTIVE | P83: 46508 | Q83: SECOM INDONESIA | R83: 302/PO/HR&GA/GA/XII/2015 | S83: 42521 | T83: CAHYO | V83: WV-SPN310
B84: 80 | C84: ZONA 2 | D84: CAM-41 | E84: FI-00268 | F84: OUTDOOR | G84: GENERAL AFFAIR | H84: IT LEGAL DEPT | I84: LOADING DOCK 5-6 | J84: PIK1CAM080 | K84: 172.17.101.8 | L84: 2019 | M84: =L84+5 -> 2024 | N84: =M84+1 -> 2025 | O84: ACTIVE | P84: 46539 | Q84: SECOM INDONESIA | R84: 302/PO/HR&GA/GA/XII/2015 | S84: 42521 | T84: CAHYO | V84: WV-SPN310
B85: 81 | C85: ZONA 2 | D85: CAM-42 | E85: FI-00498 | F85: OUTDOOR | G85: GENERAL AFFAIR | H85: IT LEGAL DEPT | I85: INJECTION 1 | J85: PIK1CAM081 | K85: 172.17.101.83 | L85: 2019 | M85: =L85+5 -> 2024 | N85: =M85+1 -> 2025 | O85: ACTIVE | P85: 46539 | Q85: SECOM INDONESIA | R85: '026/PO/HR&GA/GA/I/2019 | S85: 43707
B86: 82 | C86: ZONA 2 | D86: CAM-43 | E86: FI-00498 | F86: OUTDOOR | G86: GENERAL AFFAIR | H86: IT LEGAL DEPT | I86: INJECTION 2 | J86: PIK1CAM082 | K86: 172.17.101.84 | L86: 2019 | M86: =L86+5 -> 2024 | N86: =M86+1 -> 2025 | O86: ACTIVE | P86: 46569 | Q86: SECOM INDONESIA | R86: '026/PO/HR&GA/GA/I/2019 | S86: 43707
B87: 83 | C87: ZONA 2 | D87: CAM-44 | E87: FI-00498 | F87: OUTDOOR | G87: GENERAL AFFAIR | H87: IT LEGAL DEPT | I87: INJECTION 3 | J87: PIK1CAM083 | K87: 172.17.101.89 | L87: 2019 | M87: =L87+5 -> 2024 | N87: =M87+1 -> 2025 | O87: ACTIVE | P87: 46569 | Q87: SECOM INDONESIA | R87: '026/PO/HR&GA/GA/I/2019 | S87: 43707
B88: 84 | C88: ZONA 2 | D88: CAM-45 | E88: FI-00498 | F88: OUTDOOR | G88: GENERAL AFFAIR | H88: IT LEGAL DEPT | I88: MOLDING CNC | J88: PIK1CAM084 | K88: 172.17.101.90 | L88: 2019 | M88: =L88+5 -> 2024 | N88: =M88+1 -> 2025 | O88: ACTIVE | P88: 46600 | Q88: SECOM INDONESIA | R88: '026/PO/HR&GA/GA/I/2019 | S88: 43707
B89: 85 | C89: ZONA 2 | D89: CAM-46 | E89: FI-00498 | F89: OUTDOOR | G89: GENERAL AFFAIR | H89: IT LEGAL DEPT | I89: PART ASSY LOR | J89: PIK1CAM085 | K89: 172.17.101.67 | L89: 2019 | M89: =L89+5 -> 2024 | N89: =M89+1 -> 2025 | O89: ACTIVE | P89: 46600 | Q89: SECOM INDONESIA | R89: '026/PO/HR&GA/GA/I/2019 | S89: 43707
B90: 86 | C90: ZONA 2 | D90: CAM-47 | E90: FI-00498 | F90: OUTDOOR | G90: GENERAL AFFAIR | H90: IT LEGAL DEPT | I90: STORAGE PART PRO | J90: PIK1CAM086 | K90: 172.17.101.91 | L90: 2019 | M90: =L90+5 -> 2024 | N90: =M90+1 -> 2025 | O90: ACTIVE | P90: 46631 | Q90: SECOM INDONESIA | R90: '026/PO/HR&GA/GA/I/2019 | S90: 43707
B91: 87 | C91: ZONA 2 | D91: CAM-48 | E91: FI-00498 | F91: OUTDOOR | G91: GENERAL AFFAIR | H91: IT LEGAL DEPT | I91: BMC STORAGE | J91: PIK1CAM087 | K91: 172.17.101.93 | L91: 2019 | M91: =L91+5 -> 2024 | N91: =M91+1 -> 2025 | O91: ACTIVE | P91: 46631 | Q91: SECOM INDONESIA | R91: '026/PO/HR&GA/GA/I/2019 | S91: 43707
B92: 88 | C92: ZONA 2 | D92: CAM-49 | E92: FI-00498 | F92: OUTDOOR | G92: GENERAL AFFAIR | H92: IT LEGAL DEPT | I92: MEZANIN LIFT | J92: PIK1CAM088 | K92: 172.17.101.92 | L92: 2019 | M92: =L92+5 -> 2024 | N92: =M92+1 -> 2025 | O92: ACTIVE | P92: 46661 | Q92: SECOM INDONESIA | R92: '026/PO/HR&GA/GA/I/2019 | S92: 43707
B93: 89 | C93: ZONA 2 | D93: CAM-50 | E93: FI-00498 | F93: DOME | G93: GENERAL AFFAIR | H93: IT LEGAL DEPT | I93: LIFT DALAM | J93: PIK1CAM089 | K93: 172.17.101.66 | L93: 2019 | M93: =L93+5 -> 2024 | N93: =M93+1 -> 2025 | O93: ACTIVE | P93: 46661 | Q93: SECOM INDONESIA | R93: '026/PO/HR&GA/GA/I/2019 | S93: 43707
B94: 90 | C94: ZONA 2 | D94: CAM-51 | E94: FI-00498 | F94: OUTDOOR | G94: GENERAL AFFAIR | H94: IT LEGAL DEPT | I94: MEZANIN ELECTRIC | J94: PIK1CAM090 | K94: 172.17.101.88 | L94: 2019 | M94: =L94+5 -> 2024 | N94: =M94+1 -> 2025 | O94: ACTIVE | P94: 46692 | Q94: SECOM INDONESIA | R94: '026/PO/HR&GA/GA/I/2019 | S94: 43707
B95: 91 | C95: ZONA 2 | D95: CAM-52 | E95: FI-00114 | F95: OUTDOOR | G95: GENERAL AFFAIR | H95: IT LEGAL DEPT | I95: CLEANING BOX DC2 | J95: PIK1CAM091 | K95: 172.17.101.95 | L95: 2012 | M95: =L95+5 -> 2017 | N95: =M95+1 -> 2018 | O95: ACTIVE | P95: 46204 | Q95: SECOM INDOPRATAMA | R95: 010/GA/XII/2010REV | S95: 41000 | V95: WV-SP305
B96: 92 | C96: ZONA 2 | D96: CAM-53 | E96: FI-00114 | F96: OUTDOOR | G96: GENERAL AFFAIR | H96: IT LEGAL DEPT | I96: CLEANING BOX DC3 | J96: PIK1CAM092 | K96: 172.17.101.51 | L96: 2012 | M96: =L96+5 -> 2017 | N96: =M96+1 -> 2018 | O96: ACTIVE | P96: 46204 | Q96: SECOM INDOPRATAMA | R96: 010/GA/XII/2010REV | S96: 41000 | V96: WV-SP305
B97: 93 | C97: ZONA 2 | D97: CAM-54 | E97: FI-01044 | F97: DOME | G97: GENERAL AFFAIR | H97: IT LEGAL DEPT | I97: CNC | J97: PIK1CAM093 | K97: 172.17.101.96 | L97: 2025 | M97: =L97+5 -> 2030 | N97: =M97+1 -> 2031 | O97: ACTIVE | P97: 48214 | Q97: PILAR TEKNOLOGI SOLUSI | R97: 020/PO/HR&GA/GA/XI/2024 | S97: 45689 | T97: ARGAN | U97: 085711148741
B98: 94 | C98: ZONA 2 | D98: CAM-55 | E98: FI-01079 | F98: OUTDOOR | G98: GENERAL AFFAIR | H98: IT LEGAL DEPT | I98: ELECTRIC ROOM ZONA 2 | J98: PIK1CAM097 | K98: 172.17.101.97 | L98: 2025 | M98: =L98+5 -> 2030 | N98: =M98+1 -> 2031 | O98: ACTIVE | P98: 48245 | Q98: PILAR TEKNOLOGI SOLUSI | R98: 038/PO/HR&GA/GA/VII/2024 | S98: 45778 | T98: ARGAN | U98: 085711148741

Sheet CCTV2026-ori
B1: CCTV CAMERA ASSET LIST
B2: NO URUT | C2: NO CAM | D2: NO.ASSET | E2: TYPE | H2: NAMA | K2: IP ADDRESS MAIN | L2: IP ADDRESS BACKUP | M2: Tahun | P2: Status | Q2: AREA | R2: LISENSI | S2: Windows | T2: Trend Micro (Max PC & Svr 265) | U2: Cybereason (Max PC & Svr 245) | AC2: Plan mapping depresiasi | AD2: 2026 | AM2: 2027 | AY2: 2028 | BK2: 2029 | BW2: 2030
F3: DIVISI | G3: DEPT | I3: NIK | J3: HOSTNAME | M3: Pembelian | N3: Batas Depresiasi (5 Tahun) | O3: Batas Extend (+1 Tahun) | V3: SUPPLIER | W3: NO PO | X3: TAHUN BELI | Y3: BULAN DEPRESIASI | Z3: PIC SUPPLIER | AA3: KONTAK SUPPLIER | AB3: REMARKS | AD3: APR | AE3: MEI | AF3: JUN | AG3: JUL | AH3: AUG | AI3: SEP | AJ3: OKT | AK3: NOV | AL3: DES | AM3: JAN | AN3: FEB | AO3: MAR | AP3: APR | AQ3: MEI | AR3: JUN | AS3: JUL | AT3: AUG | AU3: SEP | AV3: OKT | AW3: NOV | AX3: DES | AY3: JAN | AZ3: FEB | BA3: MAR | BB3: APR | BC3: MEI | BD3: JUN | BE3: JUL | BF3: AUG | BG3: SEP | BH3: OKT | BI3: NOV | BJ3: DES | BK3: JAN | BL3: FEB | BM3: MAR | BN3: APR | BO3: MEI | BP3: JUN | BQ3: JUL | BR3: AUG | BS3: SEP | BT3: OKT | BU3: NOV | BV3: DES | BW3: JAN | BX3: FEB
B4: 1 | C4: 17 | D4: FI-00114 | E4: DOME | F4: GENERAL AFFAIR | G4: IT LEGAL DEPT | H4: TEST ROOM | I4: 1205001 | J4: PIK1CAM017 | K4: 172.17.101.26 | L4: - | M4: 2012 | N4: =M4+5 -> 2017 | O4: =N4+1 -> 2018 | P4: ACTIVE | Q4: ZONA 1 | R4: - | S4: - | T4: - | U4: - | V4: SECOM INDOPRATAMA | W4: 010/GA/XII/2010REV | X4: 41000 | Y4: =+X4+2195 -> 43195 | AC4: 46113 | AD4: O
B5: 2 | C5: 19 | D5: FI-00114 | E5: OUTDOOR | F5: GENERAL AFFAIR | G5: IT LEGAL DEPT | H5: LORONG MEZANINE | I5: 1205001 | J5: PIK1CAM019 | K5: 172.17.101.35 | L5: - | M5: 2012 | N5: =M5+5 -> 2017 | O5: =N5+1 -> 2018 | P5: ACTIVE | Q5: ZONA 1 | R5: - | S5: - | T5: - | U5: - | V5: SECOM INDOPRATAMA | W5: 010/GA/XII/2010REV | X5: 41000 | Y5: =+X5+2195 -> 43195 | AC5: 46113 | AD5: O
B6: 3 | C6: 20 | D6: FI-00114 | E6: OUTDOOR | F6: GENERAL AFFAIR | G6: IT LEGAL DEPT | H6: MEZANI STORE | I6: 1205001 | J6: PIK1CAM020 | K6: 172.17.101.36 | L6: - | M6: 2012 | N6: =M6+5 -> 2017 | O6: =N6+1 -> 2018 | P6: ACTIVE | Q6: ZONA 1 | R6: - | S6: - | T6: - | U6: - | V6: SECOM INDOPRATAMA | W6: 010/GA/XII/2010REV | X6: 41000 | Y6: =+X6+2195 -> 43195 | AC6: 46143 | AE6: O
B7: 4 | C7: 21 | D7: FI-00114 | E7: OUTDOOR | F7: GENERAL AFFAIR | G7: IT LEGAL DEPT | H7: MEZANI LIFT | I7: 1205001 | J7: PIK1CAM021 | K7: 172.17.101.33 | L7: - | M7: 2012 | N7: =M7+5 -> 2017 | O7: =N7+1 -> 2018 | P7: ACTIVE | Q7: ZONA 1 | R7: - | S7: - | T7: - | U7: - | V7: SECOM INDOPRATAMA | W7: 010/GA/XII/2010REV | X7: 41000 | Y7: =+X7+2195 -> 43195 | AC7: 46143 | AE7: O
B8: 5 | C8: 22 | D8: FI-00114 | E8: OUTDOOR | F8: GENERAL AFFAIR | G8: IT LEGAL DEPT | H8: INJ MULTI COLOR | I8: 1205001 | J8: PIK1CAM022 | K8: 172.17.101.25 | L8: - | M8: 2012 | N8: =M8+5 -> 2017 | O8: =N8+1 -> 2018 | P8: ACTIVE | Q8: ZONA 1 | R8: - | S8: - | T8: - | U8: - | V8: SECOM INDOPRATAMA | W8: 010/GA/XII/2010REV | X8: 41000 | Y8: =+X8+2195 -> 43195 | AC8: 46174 | AF8: O
B9: 6 | C9: 23 | D9: FI-00114 | E9: OUTDOOR | F9: GENERAL AFFAIR | G9: IT LEGAL DEPT | H9: INJECTION LENSA | I9: 1205001 | J9: PIK1CAM023 | K9: 172.17.101.24 | L9: - | M9: 2012 | N9: =M9+5 -> 2017 | O9: =N9+1 -> 2018 | P9: ACTIVE | Q9: ZONA 1 | R9: - | S9: - | T9: - | U9: - | V9: SECOM INDOPRATAMA | W9: 010/GA/XII/2010REV | X9: 41000 | Y9: =+X9+2195 -> 43195 | AC9: 46174 | AF9: O
B10: 7 | C10: 27 | D10: FI-00114 | E10: OUTDOOR | F10: GENERAL AFFAIR | G10: IT LEGAL DEPT | H10: PART STORE | I10: 1205001 | J10: PIK1CAM027 | K10: 172.17.101.7 | L10: - | M10: 2012 | N10: =M10+5 -> 2017 | O10: =N10+1 -> 2018 | P10: ACTIVE | Q10: ZONA 1 | R10: - | S10: - | T10: - | U10: - | V10: SECOM INDOPRATAMA | W10: 010/GA/XII/2010REV | X10: 41000 | Y10: =+X10+2195 -> 43195 | AC10: 46204 | AG10: O
B11: 8 | C11: 31 | D11: FI-00111 | E11: OUTDOOR | F11: GENERAL AFFAIR | G11: IT LEGAL DEPT | H11: INCOME STORE | I11: 1205001 | J11: PIK1CAM031 | K11: 172.17.101.9 | L11: - | M11: 2012 | N11: =M11+5 -> 2017 | O11: =N11+1 -> 2018 | P11: ACTIVE | Q11: ZONA 1 | R11: - | S11: - | T11: - | U11: - | V11: SECOM INDOPRATAMA | W11: 010/GA/XII/2010REV | X11: 41000 | Y11: =+X11+2195 -> 43195 | AC11: 46204 | AG11: O
B12: 9 | C12: 39 | D12: FI-00114 | E12: OUTDOOR | F12: GENERAL AFFAIR | G12: IT LEGAL DEPT | H12: PAINT STORE | I12: 1205001 | J12: PIK1CAM039 | K12: 172.17.101.15 | L12: - | M12: 2012 | N12: =M12+5 -> 2017 | O12: =N12+1 -> 2018 | P12: ACTIVE | Q12: ZONA 1 | R12: - | S12: - | T12: - | U12: - | V12: SECOM INDOPRATAMA | W12: 010/GA/XII/2010REV | X12: 41000 | Y12: =+X12+2195 -> 43195 | AC12: 46235 | AH12: O
B13: 10 | C13: 91 | D13: FI-00114 | E13: OUTDOOR | F13: GENERAL AFFAIR | G13: IT LEGAL DEPT | H13: CLEANING BOX DC2 ( Ex Absen Zona 1) | I13: 1205001 | J13: PIK1CAM091 | K13: 172.17.101.95 | L13: - | M13: 2012 | N13: =M13+5 -> 2017 | O13: =N13+1 -> 2018 | P13: ACTIVE | Q13: ZONA 2 | R13: - | S13: - | T13: - | U13: - | V13: SECOM INDOPRATAMA | W13: 010/GA/XII/2010REV | X13: 41000 | Y13: =+X13+2195 -> 43195 | AC13: 46235 | AH13: O
B14: 11 | C14: 92 | D14: FI-00114 | E14: OUTDOOR | F14: GENERAL AFFAIR | G14: IT LEGAL DEPT | H14: CLEANING BOX DC3 ( Ex Cam 3 depan posko ) Zona 1 | I14: 1205001 | J14: PIK1CAM092 | K14: 172.17.101.51 | L14: - | M14: 2012 | N14: =M14+5 -> 2017 | O14: =N14+1 -> 2018 | P14: ACTIVE | Q14: ZONA 2 | R14: - | S14: - | T14: - | U14: - | V14: SECOM INDOPRATAMA | W14: 010/GA/XII/2010REV | X14: 41000 | Y14: =+X14+2195 -> 43195 | AC14: 46266 | AI14: O
B15: 12 | C15: 28 | D15: FI-00184 | E15: OUTDOOR | F15: GENERAL AFFAIR | G15: IT LEGAL DEPT | H15: LOADING 1 | I15: 1205001 | J15: PIK1CAM028 | K15: 172.17.101.18 | L15: - | M15: 2014 | N15: =M15+5 -> 2019 | O15: =N15+1 -> 2020 | P15: ACTIVE | Q15: ZONA 1 | R15: - | S15: - | T15: - | U15: - | V15: SECOM INDONESIA | W15: 22/HRGA/PO/IX/2014 | X15: 42004 | Y15: =+X15+2190 -> 44194 | Z15: CAHYO | AA15: 0857-7112-2277 | AC15: 46266 | AI15: O
B16: 13 | C16: 29 | D16: FI-00185 | E16: OUTDOOR | F16: GENERAL AFFAIR | G16: IT LEGAL DEPT | H16: LOADING 2 | I16: 1205001 | J16: PIK1CAM029 | K16: 172.17.101.23 | L16: - | M16: 2014 | N16: =M16+5 -> 2019 | O16: =N16+1 -> 2020 | P16: ACTIVE | Q16: ZONA 1 | R16: - | S16: - | T16: - | U16: - | V16: SECOM INDONESIA | W16: 22/HRGA/PO/IX/2014 | X16: 42004 | Y16: =+X16+2190 -> 44194 | Z16: CAHYO | AA16: 0857-7112-2277 | AC16: 46296 | AJ16: O
B17: 14 | C17: 30 | D17: FI-00186 | E17: OUTDOOR | F17: GENERAL AFFAIR | G17: IT LEGAL DEPT | H17: LOADING 3 | I17: 1205001 | J17: PIK1CAM030 | K17: 172.17.101.30 | L17: - | M17: 2014 | N17: =M17+5 -> 2019 | O17: =N17+1 -> 2020 | P17: ACTIVE | Q17: ZONA 1 | R17: - | S17: - | T17: - | U17: - | V17: SECOM INDONESIA | W17: 22/HRGA/PO/IX/2014 | X17: 42004 | Y17: =+X17+2190 -> 44194 | Z17: CAHYO | AA17: 0857-7112-2277 | AC17: 46296 | AJ17: O
B18: 15 | C18: 25 | D18: FI-00333 | E18: OUTDOOR | F18: GENERAL AFFAIR | G18: IT LEGAL DEPT | H18: MATERIAL RESIN 1 | I18: 1205001 | J18: PIK1CAM025 | K18: 172.17.101.27 | L18: - | M18: 2016 | N18: =M18+5 -> 2021 | O18: =N18+1 -> 2022 | P18: ACTIVE | Q18: ZONA 1 | R18: - | S18: - | T18: - | U18: - | V18: SECOM INDONESIA | W18: 393/PO/HR&GA/GA/X20216 | X18: 42724 | Y18: =+X18+2190 -> 44914 | Z18: CAHYO | AA18: 0857-7112-2277 | AC18: 46327 | AK18: O
B19: 16 | C19: 75 | D19: FI-00264 | E19: OUTDOOR | F19: GENERAL AFFAIR | G19: IT LEGAL DEPT | H19: LOAD INVENTORY 1 | I19: 1205001 | J19: PIK1CAM075 | K19: 172.17.101.36 | L19: - | M19: 2016 | N19: =M19+5 -> 2021 | O19: =N19+1 -> 2022 | P19: ACTIVE | Q19: ZONA 2 | R19: - | S19: - | T19: - | U19: - | V19: SECOM INDONESIA | W19: '026/PO/HR&GA/GA/I/2019 | X19: 43707 | Y19: =+X19+2190 -> 45897 | Z19: CAHYO | AA19: 0857-7112-2277 | AC19: 46327 | AK19: O
B20: 17 | C20: 76 | D20: FI-00265 | E20: OUTDOOR | F20: GENERAL AFFAIR | G20: IT LEGAL DEPT | H20: LOAD INVENTORY 2 | I20: 1205001 | J20: PIK1CAM076 | K20: 172.17.101.29 | L20: - | M20: 2016 | N20: =M20+5 -> 2021 | O20: =N20+1 -> 2022 | P20: ACTIVE | Q20: ZONA 2 | R20: - | S20: - | T20: - | U20: - | V20: SECOM INDONESIA | W20: '026/PO/HR&GA/GA/I/2019 | X20: 43707 | Y20: =+X20+2190 -> 45897 | Z20: CAHYO | AA20: 0857-7112-2277 | AC20: 46357 | AL20: O
B21: 18 | C21: 77 | D21: FI-00268 | E21: OUTDOOR | F21: GENERAL AFFAIR | G21: IT LEGAL DEPT | H21: LOADING DOCK 1 | I21: 1205001 | J21: PIK1CAM077 | K21: 172.17.101.38 | L21: - | M21: 2016 | N21: =M21+5 -> 2021 | O21: =N21+1 -> 2022 | P21: ACTIVE | Q21: ZONA 2 | R21: - | S21: - | T21: - | U21: - | V21: SECOM INDONESIA | W21: 302/PO/HR&GA/GA/XII/2015 | X21: 42521 | Y21: =+X21+2190 -> 44711 | Z21: CAHYO | AA21: 0857-7112-2277 | AC21: 46357 | AL21: O
B22: 19 | C22: 78 | D22: FI-00268 | E22: OUTDOOR | F22: GENERAL AFFAIR | G22: IT LEGAL DEPT | H22: LOADING DOCK 3 | I22: 1205001 | J22: PIK1CAM078 | K22: 172.17.101.28 | L22: - | M22: 2016 | N22: =M22+5 -> 2021 | O22: =N22+1 -> 2022 | P22: ACTIVE | Q22: ZONA 2 | R22: - | S22: - | T22: - | U22: - | V22: SECOM INDONESIA | W22: 302/PO/HR&GA/GA/XII/2015 | X22: 42521 | Y22: =+X22+2190 -> 44711 | Z22: CAHYO | AA22: 0857-7112-2277 | AC22: 46388 | AM22: O
B23: 20 | C23: 79 | D23: FI-00268 | E23: OUTDOOR | F23: GENERAL AFFAIR | G23: IT LEGAL DEPT | H23: LOADING DOCK 4 | I23: 1205001 | J23: PIK1CAM079 | K23: 172.17.101.37 | L23: - | M23: 2016 | N23: =M23+5 -> 2021 | O23: =N23+1 -> 2022 | P23: ACTIVE | Q23: ZONA 2 | R23: - | S23: - | T23: - | U23: - | V23: SECOM INDONESIA | W23: 302/PO/HR&GA/GA/XII/2015 | X23: 42521 | Y23: =+X23+2190 -> 44711 | Z23: CAHYO | AA23: 0857-7112-2277 | AC23: 46388 | AM23: O
B24: 21 | C24: 80 | D24: FI-00268 | E24: OUTDOOR | F24: GENERAL AFFAIR | G24: IT LEGAL DEPT | H24: LOADING DOCK 5-6 | I24: 1205001 | J24: PIK1CAM080 | K24: 172.17.101.8 | L24: - | M24: 2016 | N24: =M24+5 -> 2021 | O24: =N24+1 -> 2022 | P24: ACTIVE | Q24: ZONA 2 | R24: - | S24: - | T24: - | U24: - | V24: SECOM INDONESIA | W24: 302/PO/HR&GA/GA/XII/2015 | X24: 42521 | Y24: =+X24+2190 -> 44711 | Z24: CAHYO | AA24: 0857-7112-2277 | AC24: 46419 | AN24: O
B25: 22 | C25: 42 | D25: FI-00498 | E25: OUTDOOR | F25: GENERAL AFFAIR | G25: IT LEGAL DEPT | H25: TPS DEPAN | I25: 1205001 | J25: PIK1CAM042 | K25: 172.17.101.85 | L25: - | M25: 2019 | N25: =M25+5 -> 2024 | O25: =N25+1 -> 2025 | P25: ACTIVE | Q25: ZONA 2 | R25: - | S25: - | T25: - | U25: - | V25: SECOM INDONESIA | W25: '026/PO/HR&GA/GA/I/2019 | X25: 43707 | Y25: =+X25+2190 -> 45897 | Z25: CAHYO | AA25: 0857-7112-2277 | AC25: 46419 | AN25: O
B26: 23 | C26: 43 | D26: FI-00498 | E26: OUTDOOR | F26: GENERAL AFFAIR | G26: IT LEGAL DEPT | H26: TPS BELAKANG 1 | I26: 1205001 | J26: PIK1CAM043 | K26: 172.17.101.86 | L26: - | M26: 2019 | N26: =M26+5 -> 2024 | O26: =N26+1 -> 2025 | P26: ACTIVE | Q26: ZONA 2 | R26: - | S26: - | T26: - | U26: - | V26: SECOM INDONESIA | W26: '026/PO/HR&GA/GA/I/2019 | X26: 43707 | Y26: =+X26+2190 -> 45897 | Z26: CAHYO | AA26: 0857-7112-2277 | AC26: 46447 | AO26: O
B27: 24 | C27: 44 | D27: FI-00498 | E27: OUTDOOR | F27: GENERAL AFFAIR | G27: IT LEGAL DEPT | H27: TPS BELAKANG 2 | I27: 1205001 | J27: PIK1CAM044 | K27: 172.17.101.87 | L27: - | M27: 2019 | N27: =M27+5 -> 2024 | O27: =N27+1 -> 2025 | P27: ACTIVE | Q27: ZONA 2 | R27: - | S27: - | T27: - | U27: - | V27: SECOM INDONESIA | W27: '026/PO/HR&GA/GA/I/2019 | X27: 43707 | Y27: =+X27+2190 -> 45897 | Z27: CAHYO | AA27: 0857-7112-2277 | AC27: 46447 | AO27: O
B28: 25 | C28: 45 | D28: FI-00498 | E28: OUTDOOR | F28: GENERAL AFFAIR | G28: IT LEGAL DEPT | H28: POS BELAKANG | I28: 1205001 | J28: PIK1CAM045 | K28: 172.17.101.82 | L28: - | M28: 2019 | N28: =M28+5 -> 2024 | O28: =N28+1 -> 2025 | P28: ACTIVE | Q28: ZONA 2 | R28: - | S28: - | T28: - | U28: - | V28: SECOM INDONESIA | W28: '026/PO/HR&GA/GA/I/2019 | X28: 43707 | Y28: =+X28+2190 -> 45897 | Z28: CAHYO | AA28: 0857-7112-2277 | AC28: 46478 | AP28: O
B29: 26 | C29: 46 | D29: FI-00498 | E29: OUTDOOR | F29: GENERAL AFFAIR | G29: IT LEGAL DEPT | H29: FENCE BELAKANG | I29: 1205001 | J29: PIK1CAM046 | K29: 172.17.101.81 | L29: - | M29: 2019 | N29: =M29+5 -> 2024 | O29: =N29+1 -> 2025 | P29: ACTIVE | Q29: ZONA 2 | R29: - | S29: - | T29: - | U29: - | V29: SECOM INDONESIA | W29: '026/PO/HR&GA/GA/I/2019 | X29: 43707 | Y29: =+X29+2190 -> 45897 | Z29: CAHYO | AA29: 0857-7112-2277 | AC29: 46478 | AP29: O
B30: 27 | C30: 49 | D30: FI-00498 | E30: OUTDOOR | F30: GENERAL AFFAIR | G30: IT LEGAL DEPT | H30: ABSENSI MALE | I30: 1205001 | J30: PIK1CAM049 | K30: 172.17.101.55 | L30: - | M30: 2019 | N30: =M30+5 -> 2024 | O30: =N30+1 -> 2025 | P30: ACTIVE | Q30: ZONA 2 | R30: - | S30: - | T30: - | U30: - | V30: SECOM INDONESIA | W30: '026/PO/HR&GA/GA/I/2019 | X30: 43707 | Y30: =+X30+2190 -> 45897 | Z30: CAHYO | AA30: 0857-7112-2277 | AC30: 46508 | AQ30: O
B31: 28 | C31: 50 | D31: FI-00498 | E31: OUTDOOR | F31: GENERAL AFFAIR | G31: IT LEGAL DEPT | H31: DOUBLE CHECK | I31: 1205001 | J31: PIK1CAM050 | K31: 172.17.101.16 | L31: - | M31: 2019 | N31: =M31+5 -> 2024 | O31: =N31+1 -> 2025 | P31: ACTIVE | Q31: ZONA 2 | R31: - | S31: - | T31: - | U31: - | V31: SECOM INDONESIA | W31: '026/PO/HR&GA/GA/I/2019 | X31: 43707 | Y31: =+X31+2190 -> 45897 | Z31: CAHYO | AA31: 0857-7112-2277 | AC31: 46508 | AQ31: O
B32: 29 | C32: 51 | D32: FI-00498 | E32: OUTDOOR | F32: GENERAL AFFAIR | G32: IT LEGAL DEPT | H32: LORONG PART MTRL | I32: 1205001 | J32: PIK1CAM051 | K32: 172.17.101.69 | L32: - | M32: 2019 | N32: =M32+5 -> 2024 | O32: =N32+1 -> 2025 | P32: ACTIVE | Q32: ZONA 2 | R32: - | S32: - | T32: - | U32: - | V32: SECOM INDONESIA | W32: '026/PO/HR&GA/GA/I/2019 | X32: 43707 | Y32: =+X32+2190 -> 45897 | Z32: CAHYO | AA32: 0857-7112-2277 | AC32: 46539 | AR32: O
B33: 30 | C33: 52 | D33: FI-00498 | E33: OUTDOOR | F33: GENERAL AFFAIR | G33: IT LEGAL DEPT | H33: TANGGA BAWAH KTN | I33: 1205001 | J33: PIK1CAM052 | K33: 172.17.101.53 | L33: - | M33: 2019 | N33: =M33+5 -> 2024 | O33: =N33+1 -> 2025 | P33: ACTIVE | Q33: ZONA 2 | R33: - | S33: - | T33: - | U33: - | V33: SECOM INDONESIA | W33: '026/PO/HR&GA/GA/I/2019 | X33: 43707 | Y33: =+X33+2190 -> 45897 | Z33: CAHYO | AA33: 0857-7112-2277 | AC33: 46539 | AR33: O
B34: 31 | C34: 55 | D34: FI-00498 | E34: OUTDOOR | F34: GENERAL AFFAIR | G34: IT LEGAL DEPT | H34: LIFT KANTIN BWH | I34: 1205001 | J34: PIK1CAM055 | K34: 172.17.101.62 | L34: - | M34: 2019 | N34: =M34+5 -> 2024 | O34: =N34+1 -> 2025 | P34: ACTIVE | Q34: ZONA 2 | R34: - | S34: - | T34: - | U34: - | V34: SECOM INDONESIA | W34: '026/PO/HR&GA/GA/I/2019 | X34: 43707 | Y34: =+X34+2190 -> 45897 | Z34: CAHYO | AA34: 0857-7112-2277 | AC34: 46569 | AS34: O
B35: 32 | C35: 60 | D35: FI-00498 | E35: OUTDOOR | F35: GENERAL AFFAIR | G35: IT LEGAL DEPT | H35: LORONG MUSHOLA 1 | I35: 1205001 | J35: PIK1CAM060 | K35: 172.17.101.59 | L35: - | M35: 2019 | N35: =M35+5 -> 2024 | O35: =N35+1 -> 2025 | P35: ACTIVE | Q35: ZONA 2 | R35: - | S35: - | T35: - | U35: - | V35: SECOM INDONESIA | W35: '026/PO/HR&GA/GA/I/2019 | X35: 43707 | Y35: =+X35+2190 -> 45897 | Z35: CAHYO | AA35: 0857-7112-2277 | AC35: 46569 | AS35: O
B36: 33 | C36: 63 | D36: FI-00498 | E36: OUTDOOR | F36: GENERAL AFFAIR | G36: IT LEGAL DEPT | H36: TANGGA MUSHOLA | I36: 1205001 | J36: PIK1CAM063 | K36: 172.17.101.52 | L36: - | M36: 2019 | N36: =M36+5 -> 2024 | O36: =N36+1 -> 2025 | P36: ACTIVE | Q36: ZONA 2 | R36: - | S36: - | T36: - | U36: - | V36: SECOM INDONESIA | W36: '026/PO/HR&GA/GA/I/2019 | X36: 43707 | Y36: =+X36+2190 -> 45897 | Z36: CAHYO | AA36: 0857-7112-2277 | AC36: 46600 | AT36: O
B37: 34 | C37: 64 | D37: FI-00498 | E37: OUTDOOR | F37: GENERAL AFFAIR | G37: IT LEGAL DEPT | H37: LORONG HUB ZONA | I37: 1205001 | J37: PIK1CAM064 | K37: 172.17.101.70 | L37: - | M37: 2019 | N37: =M37+5 -> 2024 | O37: =N37+1 -> 2025 | P37: ACTIVE | Q37: ZONA 2 | R37: - | S37: - | T37: - | U37: - | V37: SECOM INDONESIA | W37: '026/PO/HR&GA/GA/I/2019 | X37: 43707 | Y37: =+X37+2190 -> 45897 | Z37: CAHYO | AA37: 0857-7112-2277 | AC37: 46600 | AT37: O
B38: 35 | C38: 65 | D38: FI-00498 | E38: OUTDOOR | F38: GENERAL AFFAIR | G38: IT LEGAL DEPT | H38: PART INVENTORY 1 | I38: 1205001 | J38: PIK1CAM065 | K38: 172.17.101.71 | L38: - | M38: 2019 | N38: =M38+5 -> 2024 | O38: =N38+1 -> 2025 | P38: ACTIVE | Q38: ZONA 2 | R38: - | S38: - | T38: - | U38: - | V38: SECOM INDONESIA | W38: '026/PO/HR&GA/GA/I/2019 | X38: 43707 | Y38: =+X38+2190 -> 45897 | Z38: CAHYO | AA38: 0857-7112-2277 | AC38: 46631 | AU38: O
B39: 36 | C39: 66 | D39: FI-00498 | E39: OUTDOOR | F39: GENERAL AFFAIR | G39: IT LEGAL DEPT | H39: PART ASSY 1 | I39: 1205001 | J39: PIK1CAM066 | K39: 172.17.101.72 | L39: - | M39: 2019 | N39: =M39+5 -> 2024 | O39: =N39+1 -> 2025 | P39: ACTIVE | Q39: ZONA 2 | R39: - | S39: - | T39: - | U39: - | V39: SECOM INDONESIA | W39: '026/PO/HR&GA/GA/I/2019 | X39: 43707 | Y39: =+X39+2190 -> 45897 | Z39: CAHYO | AA39: 0857-7112-2277 | AC39: 46631 | AU39: O
B40: 37 | C40: 67 | D40: FI-00498 | E40: OUTDOOR | F40: GENERAL AFFAIR | G40: IT LEGAL DEPT | H40: PART ASSY 2 | I40: 1205001 | J40: PIK1CAM067 | K40: 172.17.101.73 | L40: - | M40: 2019 | N40: =M40+5 -> 2024 | O40: =N40+1 -> 2025 | P40: ACTIVE | Q40: ZONA 2 | R40: - | S40: - | T40: - | U40: - | V40: SECOM INDONESIA | W40: '026/PO/HR&GA/GA/I/2019 | X40: 43707 | Y40: =+X40+2190 -> 45897 | Z40: CAHYO | AA40: 0857-7112-2277 | AC40: 46661 | AV40: O
B41: 38 | C41: 68 | D41: FI-00498 | E41: OUTDOOR | F41: GENERAL AFFAIR | G41: IT LEGAL DEPT | H41: PART INVENTORY 2 | I41: 1205001 | J41: PIK1CAM068 | K41: 172.17.101.74 | L41: - | M41: 2019 | N41: =M41+5 -> 2024 | O41: =N41+1 -> 2025 | P41: ACTIVE | Q41: ZONA 2 | R41: - | S41: - | T41: - | U41: - | V41: SECOM INDONESIA | W41: '026/PO/HR&GA/GA/I/2019 | X41: 43707 | Y41: =+X41+2190 -> 45897 | Z41: CAHYO | AA41: 0857-7112-2277 | AC41: 46661 | AV41: O
B42: 39 | C42: 69 | D42: FI-00498 | E42: OUTDOOR | F42: GENERAL AFFAIR | G42: IT LEGAL DEPT | H42: PART INVENTORY 3 | I42: 1205001 | J42: PIK1CAM069 | K42: 172.17.101.75 | L42: - | M42: 2019 | N42: =M42+5 -> 2024 | O42: =N42+1 -> 2025 | P42: ACTIVE | Q42: ZONA 2 | R42: - | S42: - | T42: - | U42: - | V42: SECOM INDONESIA | W42: '026/PO/HR&GA/GA/I/2019 | X42: 43707 | Y42: =+X42+2190 -> 45897 | Z42: CAHYO | AA42: 0857-7112-2277 | AC42: 46692 | AW42: O
B43: 40 | C43: 70 | D43: FI-00498 | E43: OUTDOOR | F43: GENERAL AFFAIR | G43: IT LEGAL DEPT | H43: PART INVENTORY 4 | I43: 1205001 | J43: PIK1CAM070 | K43: 172.17.101.76 | L43: - | M43: 2019 | N43: =M43+5 -> 2024 | O43: =N43+1 -> 2025 | P43: ACTIVE | Q43: ZONA 2 | R43: - | S43: - | T43: - | U43: - | V43: SECOM INDONESIA | W43: '026/PO/HR&GA/GA/I/2019 | X43: 43707 | Y43: =+X43+2190 -> 45897 | Z43: CAHYO | AA43: 0857-7112-2277 | AC43: 46692 | AW43: O
B44: 41 | C44: 71 | D44: FI-00498 | E44: OUTDOOR | F44: GENERAL AFFAIR | G44: IT LEGAL DEPT | H44: PART INVENTORY 5 | I44: 1205001 | J44: PIK1CAM071 | K44: 172.17.101.77 | L44: - | M44: 2019 | N44: =M44+5 -> 2024 | O44: =N44+1 -> 2025 | P44: ACTIVE | Q44: ZONA 2 | R44: - | S44: - | T44: - | U44: - | V44: SECOM INDONESIA | W44: '026/PO/HR&GA/GA/I/2019 | X44: 43707 | Y44: =+X44+2190 -> 45897 | Z44: CAHYO | AA44: 0857-7112-2277 | AC44: 46722 | AX44: O
B45: 42 | C45: 72 | D45: FI-00498 | E45: OUTDOOR | F45: GENERAL AFFAIR | G45: IT LEGAL DEPT | H45: PART INVENTORY 6 | I45: 1205001 | J45: PIK1CAM072 | K45: 172.17.101.78 | L45: - | M45: 2019 | N45: =M45+5 -> 2024 | O45: =N45+1 -> 2025 | P45: ACTIVE | Q45: ZONA 2 | R45: - | S45: - | T45: - | U45: - | V45: SECOM INDONESIA | W45: '026/PO/HR&GA/GA/I/2019 | X45: 43707 | Y45: =+X45+2190 -> 45897 | Z45: CAHYO | AA45: 0857-7112-2277 | AC45: 46722 | AX45: O
B46: 43 | C46: 73 | D46: FI-00498 | E46: OUTDOOR | F46: GENERAL AFFAIR | G46: IT LEGAL DEPT | H46: GATE ANTAR ZONA | I46: 1205001 | J46: PIK1CAM073 | K46: 172.17.101.80 | L46: - | M46: 2019 | N46: =M46+5 -> 2024 | O46: =N46+1 -> 2025 | P46: ACTIVE | Q46: ZONA 2 | R46: - | S46: - | T46: - | U46: - | V46: SECOM INDONESIA | W46: '026/PO/HR&GA/GA/I/2019 | X46: 43707 | Y46: =+X46+2190 -> 45897 | Z46: CAHYO | AA46: 0857-7112-2277 | AC46: 46753 | AY46: O
B47: 44 | C47: 74 | D47: FI-00498 | E47: OUTDOOR | F47: GENERAL AFFAIR | G47: IT LEGAL DEPT | H47: INVENTORY TENGAH | I47: 1205001 | J47: PIK1CAM074 | K47: 172.17.101.79 | L47: - | M47: 2019 | N47: =M47+5 -> 2024 | O47: =N47+1 -> 2025 | P47: ACTIVE | Q47: ZONA 2 | R47: - | S47: - | T47: - | U47: - | V47: SECOM INDONESIA | W47: '026/PO/HR&GA/GA/I/2019 | X47: 43707 | Y47: =+X47+2190 -> 45897 | Z47: CAHYO | AA47: 0857-7112-2277 | AC47: 46753 | AY47: O
B48: 45 | C48: 81 | D48: FI-00498 | E48: OUTDOOR | F48: GENERAL AFFAIR | G48: IT LEGAL DEPT | H48: INJECTION 1 | I48: 1205001 | J48: PIK1CAM081 | K48: 172.17.101.83 | L48: - | M48: 2019 | N48: =M48+5 -> 2024 | O48: =N48+1 -> 2025 | P48: ACTIVE | Q48: ZONA 2 | R48: - | S48: - | T48: - | U48: - | V48: SECOM INDONESIA | W48: '026/PO/HR&GA/GA/I/2019 | X48: 43707 | Y48: =+X48+2190 -> 45897 | Z48: CAHYO | AA48: 0857-7112-2277 | AC48: 46784 | AZ48: O
B49: 46 | C49: 82 | D49: FI-00498 | E49: OUTDOOR | F49: GENERAL AFFAIR | G49: IT LEGAL DEPT | H49: INJECTION 2 | I49: 1205001 | J49: PIK1CAM082 | K49: 172.17.101.84 | L49: - | M49: 2019 | N49: =M49+5 -> 2024 | O49: =N49+1 -> 2025 | P49: ACTIVE | Q49: ZONA 2 | R49: - | S49: - | T49: - | U49: - | V49: SECOM INDONESIA | W49: '026/PO/HR&GA/GA/I/2019 | X49: 43707 | Y49: =+X49+2190 -> 45897 | Z49: CAHYO | AA49: 0857-7112-2277 | AC49: 46784 | AZ49: O
B50: 47 | C50: 83 | D50: FI-00498 | E50: OUTDOOR | F50: GENERAL AFFAIR | G50: IT LEGAL DEPT | H50: INJECTION 3 | I50: 1205001 | J50: PIK1CAM083 | K50: 172.17.101.89 | L50: - | M50: 2019 | N50: =M50+5 -> 2024 | O50: =N50+1 -> 2025 | P50: ACTIVE | Q50: ZONA 2 | R50: - | S50: - | T50: - | U50: - | V50: SECOM INDONESIA | W50: '026/PO/HR&GA/GA/I/2019 | X50: 43707 | Y50: =+X50+2190 -> 45897 | Z50: CAHYO | AA50: 0857-7112-2277 | AC50: 46813 | BA50: O
B51: 48 | C51: 84 | D51: FI-00498 | E51: OUTDOOR | F51: GENERAL AFFAIR | G51: IT LEGAL DEPT | H51: MOLDING CNC | I51: 1205001 | J51: PIK1CAM084 | K51: 172.17.101.90 | L51: - | M51: 2019 | N51: =M51+5 -> 2024 | O51: =N51+1 -> 2025 | P51: ACTIVE | Q51: ZONA 2 | R51: - | S51: - | T51: - | U51: - | V51: SECOM INDONESIA | W51: '026/PO/HR&GA/GA/I/2019 | X51: 43707 | Y51: =+X51+2190 -> 45897 | Z51: CAHYO | AA51: 0857-7112-2277 | AC51: 46813 | BA51: O
B52: 49 | C52: 85 | D52: FI-00498 | E52: OUTDOOR | F52: GENERAL AFFAIR | G52: IT LEGAL DEPT | H52: PART ASSY LOR | I52: 1205001 | J52: PIK1CAM085 | K52: 172.17.101.67 | L52: - | M52: 2019 | N52: =M52+5 -> 2024 | O52: =N52+1 -> 2025 | P52: ACTIVE | Q52: ZONA 2 | R52: - | S52: - | T52: - | U52: - | V52: SECOM INDONESIA | W52: '026/PO/HR&GA/GA/I/2019 | X52: 43707 | Y52: =+X52+2190 -> 45897 | Z52: CAHYO | AA52: 0857-7112-2277 | AC52: 46844 | BB52: O
B53: 50 | C53: 86 | D53: FI-00498 | E53: OUTDOOR | F53: GENERAL AFFAIR | G53: IT LEGAL DEPT | H53: STORAGE PART PRO | I53: 1205001 | J53: PIK1CAM086 | K53: 172.17.101.91 | L53: - | M53: 2019 | N53: =M53+5 -> 2024 | O53: =N53+1 -> 2025 | P53: ACTIVE | Q53: ZONA 2 | R53: - | S53: - | T53: - | U53: - | V53: SECOM INDONESIA | W53: '026/PO/HR&GA/GA/I/2019 | X53: 43707 | Y53: =+X53+2190 -> 45897 | Z53: CAHYO | AA53: 0857-7112-2277 | AC53: 46844 | BB53: O
B54: 51 | C54: 87 | D54: FI-00498 | E54: OUTDOOR | F54: GENERAL AFFAIR | G54: IT LEGAL DEPT | H54: BMC STORAGE | I54: 1205001 | J54: PIK1CAM087 | K54: 172.17.101.93 | L54: - | M54: 2019 | N54: =M54+5 -> 2024 | O54: =N54+1 -> 2025 | P54: ACTIVE | Q54: ZONA 2 | R54: - | S54: - | T54: - | U54: - | V54: SECOM INDONESIA | W54: '026/PO/HR&GA/GA/I/2019 | X54: 43707 | Y54: =+X54+2190 -> 45897 | Z54: CAHYO | AA54: 0857-7112-2277 | AC54: 46874 | BC54: O
B55: 52 | C55: 88 | D55: FI-00498 | E55: OUTDOOR | F55: GENERAL AFFAIR | G55: IT LEGAL DEPT | H55: MEZANIN LIFT | I55: 1205001 | J55: PIK1CAM088 | K55: 172.17.101.92 | L55: - | M55: 2019 | N55: =M55+5 -> 2024 | O55: =N55+1 -> 2025 | P55: ACTIVE | Q55: ZONA 2 | R55: - | S55: - | T55: - | U55: - | V55: SECOM INDONESIA | W55: '026/PO/HR&GA/GA/I/2019 | X55: 43707 | Y55: =+X55+2190 -> 45897 | Z55: CAHYO | AA55: 0857-7112-2277 | AC55: 46874 | BC55: O
B56: 53 | C56: 89 | D56: FI-00498 | E56: DOME | F56: GENERAL AFFAIR | G56: IT LEGAL DEPT | H56: LIFT DALAM | I56: 1205001 | J56: PIK1CAM089 | K56: 172.17.101.66 | L56: - | M56: 2019 | N56: =M56+5 -> 2024 | O56: =N56+1 -> 2025 | P56: ACTIVE | Q56: ZONA 2 | R56: - | S56: - | T56: - | U56: - | V56: SECOM INDONESIA | W56: '026/PO/HR&GA/GA/I/2019 | X56: 43707 | Y56: =+X56+2190 -> 45897 | Z56: CAHYO | AA56: 0857-7112-2277 | AC56: 46905 | BD56: O
B57: 54 | C57: 90 | D57: FI-00498 | E57: OUTDOOR | F57: GENERAL AFFAIR | G57: IT LEGAL DEPT | H57: MEZANIN ELECTRIC | I57: 1205001 | J57: PIK1CAM090 | K57: 172.17.101.88 | L57: - | M57: 2019 | N57: =M57+5 -> 2024 | O57: =N57+1 -> 2025 | P57: ACTIVE | Q57: ZONA 2 | R57: - | S57: - | T57: - | U57: - | V57: SECOM INDONESIA | W57: '026/PO/HR&GA/GA/I/2019 | X57: 43707 | Y57: =+X57+2190 -> 45897 | Z57: CAHYO | AA57: 0857-7112-2277 | AC57: 46905 | BD57: O
B58: 55 | C58: 38 | D58: FI-00629 | E58: OUTDOOR | F58: GENERAL AFFAIR | G58: IT LEGAL DEPT | H58: TENTHOUSE 1 | I58: 1205001 | J58: PIK1CAM038 | K58: 172.17.101.94 | L58: - | M58: 2021 | N58: =M58+5 -> 2026 | O58: =N58+1 -> 2027 | P58: ACTIVE | Q58: ZONA 1 | R58: - | S58: - | T58: - | U58: - | V58: CLARUS INNOVANCE TEKNOLOGI | W58: 012/PO/HR&GA/GA/VII/2021 | X58: 44530 | Y58: =+X58+2190 -> 46720 | AC58: 46935 | BE58: O
B59: 56 | C59: 5 | D59: FI-00728 | E59: OUTDOOR | F59: GENERAL AFFAIR | G59: IT LEGAL DEPT | H59: PARKIR MOTOR | I59: 1205001 | J59: PIK1CAM005 | K59: 172.17.101.11 | L59: - | M59: 2023 | N59: =M59+5 -> 2028 | O59: =N59+1 -> 2029 | P59: ACTIVE | Q59: ZONA 1 | R59: - | S59: - | T59: - | U59: - | V59: SECOM INDONESIA | W59: 069/PO/HR&GA/GA/XI/2022 | X59: 45044 | Y59: =+X59+2190 -> 47234 | Z59: CAHYO | AA59: 0857-7112-2277 | AC59: 46935 | BE59: O
B60: 57 | C60: 32 | D60: FI-00923 | E60: DOME | F60: GENERAL AFFAIR | G60: IT LEGAL DEPT | H60: OFFICE QLTY1 | I60: 1205001 | J60: PIK1CAM032 | K60: 172.17.101.65 | L60: - | M60: 2023 | N60: =M60+5 -> 2028 | O60: =N60+1 -> 2029 | P60: ACTIVE | Q60: ZONA 1 | R60: - | S60: - | T60: - | U60: - | V60: SECOM INDONESIA | W60: 026/PO/HR&GA/GA/IX/2023 | X60: 45289 | Y60: =+X60+2190 -> 47479 | Z60: CAHYO | AA60: 0857-7112-2277 | AC60: 46966 | BF60: O
B61: 58 | C61: 4 | D61: FI-01056 | E61: OUTDOOR | F61: GENERAL AFFAIR | G61: IT LEGAL DEPT | H61: PARKIR MOBIL 2 | I61: 1205001 | J61: PIK1CAM004 | K61: 172.17.101.32 | L61: - | M61: 2024 | N61: =M61+5 -> 2029 | O61: =N61+1 -> 2030 | P61: ACTIVE | Q61: ZONA 1 | R61: - | S61: - | T61: - | U61: - | V61: PILAR TEKNOLOGI SOLUSI | W61: 038/PO/HR&GA/GA/VII/2024 | X61: 45474 | Y61: =+X61+2190 -> 47664 | Z61: ARGAN | AA61: 085711148741 | AB61: CCTV DEPRE JUL 24 | AC61: 46966 | BF61: O
B62: 59 | C62: 7 | D62: FI-01053 | E62: OUTDOOR | F62: GENERAL AFFAIR | G62: IT LEGAL DEPT | H62: TPS 1 | I62: 1205001 | J62: PIK1CAM007 | K62: 172.17.101.13 | L62: - | M62: 2024 | N62: =M62+5 -> 2029 | O62: =N62+1 -> 2030 | P62: ACTIVE | Q62: ZONA 1 | R62: - | S62: - | T62: - | U62: - | V62: PILAR TEKNOLOGI SOLUSI | W62: 035/PO/HR&GA/GA/ VI/2024 | X62: 45444 | Y62: =+X62+2195 -> 47639 | Z62: ARGAN | AA62: 085711148741 | AB62: CCTV DEPRE JUN 24 | AC62: 46997 | BG62: O
B63: 60 | C63: 8 | D63: FI-01054 | E63: OUTDOOR | F63: GENERAL AFFAIR | G63: IT LEGAL DEPT | H63: TENT HOUSE 2 (BOILEER BELAKANG) | I63: 1205001 | J63: PIK1CAM008 | K63: 172.17.101.20 | L63: - | M63: 2024 | N63: =M63+5 -> 2029 | O63: =N63+1 -> 2030 | P63: ACTIVE | Q63: ZONA 1 | R63: - | S63: - | T63: - | U63: - | V63: PILAR TEKNOLOGI SOLUSI | W63: 035/PO/HR&GA/GA/ VI/2024 | X63: 45444 | Y63: =+X63+2195 -> 47639 | Z63: ARGAN | AA63: 085711148741 | AB63: CCTV DEPRE JUN 24 | AC63: 46997 | BG63: O
B64: 61 | C64: 9 | D64: FI-01007 | E64: DOME | F64: GENERAL AFFAIR | G64: IT LEGAL DEPT | H64: LOBBY DALAM | I64: 1205001 | J64: PIK1CAM009 | K64: 172.17.101.4 | L64: - | M64: 2024 | N64: =M64+5 -> 2029 | O64: =N64+1 -> 2030 | P64: ACTIVE | Q64: ZONA 1 | R64: - | S64: - | T64: - | U64: - | V64: PILAR TEKNOLOGI SOLUSI | W64: 039/PO/HR&GA/GA/VIII/2024 | X64: 45505 | Y64: =+X64+2195 -> 47700 | Z64: ARGAN | AA64: 085711148741 | AB64: CCTV DEPRE AGUS 24 | AC64: 47027 | BH64: O
B65: 62 | C65: 11 | D65: FI-00991 | E65: DOME | F65: GENERAL AFFAIR | G65: IT LEGAL DEPT | H65: OFFICE ADM 1 | I65: 1205001 | J65: PIK1CAM011 | K65: 172.17.101.31 | L65: - | M65: 2024 | N65: =M65+5 -> 2029 | O65: =N65+1 -> 2030 | P65: ACTIVE | Q65: ZONA 1 | R65: - | S65: - | T65: - | U65: - | V65: PILAR TEKNOLOGI SOLUSI | W65: 075/PO/HR&GA/GA/V/2024 | X65: 45413 | Y65: =+X65+2195 -> 47608 | Z65: ARGAN | AA65: 085711148741 | AB65: CCTV ADD MEI 24 | AC65: 47027 | BH65: O
B66: 63 | C66: 12 | D66: FI-00992 | E66: DOME | F66: GENERAL AFFAIR | G66: IT LEGAL DEPT | H66: OFFICE ADM 2 | I66: 1205001 | J66: PIK1CAM012 | K66: 172.17.101.5 | L66: - | M66: =2024 -> 2024 | N66: =M66+5 -> 2029 | O66: =N66+1 -> 2030 | P66: ACTIVE | Q66: ZONA 1 | R66: - | S66: - | T66: - | U66: - | V66: PILAR TEKNOLOGI SOLUSI | W66: 075/PO/HR&GA/GA/V/2024 | X66: 45413 | Y66: =+X66+2195 -> 47608 | Z66: ARGAN | AA66: 085711148741 | AB66: CCTV ADD MEI 24 | AC66: 47058 | BI66: O
B67: 64 | C67: 13 | D67: FI-00993 | E67: DOME | F67: GENERAL AFFAIR | G67: IT LEGAL DEPT | H67: SERVER ROOM | I67: 1205001 | J67: PIK1CAM013 | K67: 172.17.11.43 | L67: - | M67: =2024 -> 2024 | N67: =M67+5 -> 2029 | O67: =N67+1 -> 2030 | P67: ACTIVE | Q67: ZONA 1 | R67: - | S67: - | T67: - | U67: - | V67: PILAR TEKNOLOGI SOLUSI | W67: 075/PO/HR&GA/GA/V/2024 | X67: 45413 | Y67: =+X67+2195 -> 47608 | Z67: ARGAN | AA67: 085711148741 | AB67: CCTV ADD MEI 24 | AC67: 47058 | BI67: O
B68: 65 | C68: 14 | D68: FI-01027 | E68: DOME | F68: GENERAL AFFAIR | G68: IT LEGAL DEPT | H68: LORONG OFFICE 1 | I68: 1205001 | J68: PIK1CAM014 | K68: 172.17.101.19 | L68: - | M68: 2024 | N68: =M68+5 -> 2029 | O68: =N68+1 -> 2030 | P68: ACTIVE | Q68: ZONA 1 | R68: - | S68: - | T68: - | U68: - | V68: PILAR TEKNOLOGI SOLUSI | W68: 065/PO/HR&GA/GA/IX/2024 | X68: 45536 | Y68: =+X68+2195 -> 47731 | Z68: ARGAN | AA68: 085711148741 | AB68: CCTV DEPRE SEP 24 | AC68: 47088 | BJ68: O
B69: 66 | C69: 16 | D69: FI-01028 | E69: DOME | F69: GENERAL AFFAIR | G69: IT LEGAL DEPT | H69: OFFICE PROD | I69: 1205001 | J69: PIK1CAM016 | K69: 172.17.101.21 | L69: - | M69: 2024 | N69: =M69+5 -> 2029 | O69: =N69+1 -> 2030 | P69: ACTIVE | Q69: ZONA 1 | R69: - | S69: - | T69: - | U69: - | V69: PILAR TEKNOLOGI SOLUSI | W69: 065/PO/HR&GA/GA/IX/2024 | X69: 45536 | Y69: =+X69+2195 -> 47731 | Z69: ARGAN | AA69: 085711148741 | AB69: CCTV DEPRE SEP 24 | AC69: 47088 | BJ69: O
B70: 67 | C70: 26 | D70: FI-01046 | E70: DOME | F70: GENERAL AFFAIR | G70: IT LEGAL DEPT | H70: MATERIAL RESIN 2 | I70: 1205001 | J70: PIK1CAM026 | K70: 172.17.101.6 | L70: - | M70: 2024 | N70: =M70+5 -> 2029 | O70: =N70+1 -> 2030 | P70: ACTIVE | Q70: ZONA 1 | R70: - | S70: - | T70: - | U70: - | V70: PILAR TEKNOLOGI SOLUSI | W70: 006/PO/HR&GA/GA/XI/2024 | X70: 45566 | Y70: =+X70+2195 -> 47761 | Z70: ARGAN | AA70: 085711148741 | AB70: CCTV DEPRE OKT 24 | AC70: 47119 | BK70: O
B71: 68 | C71: 33 | D71: FI-01044 | E71: DOME | F71: GENERAL AFFAIR | G71: IT LEGAL DEPT | H71: OFFICE QLTY 2 | I71: 1205001 | J71: PIK1CAM033 | K71: 172.17.101.64 | L71: - | M71: 2024 | N71: =M71+5 -> 2029 | O71: =N71+1 -> 2030 | P71: ACTIVE | Q71: ZONA 1 | R71: - | S71: - | T71: - | U71: - | V71: PILAR TEKNOLOGI SOLUSI | W71: 020/PO/HR&GA/GA/XI/2024 | X71: 45597 | Y71: =+X71+2195 -> 47792 | Z71: ARGAN | AA71: 085711148741 | AB71: CCTV DEPRE NOV 24 | AC71: 47119 | BK71: O
B72: 69 | C72: 34 | D72: FI-01008 | E72: DOME | F72: GENERAL AFFAIR | G72: IT LEGAL DEPT | H72: LORONG QLTY | I72: 1205001 | J72: PIK1CAM034 | K72: 172.17.101.63 | L72: - | M72: 2024 | N72: =M72+5 -> 2029 | O72: =N72+1 -> 2030 | P72: ACTIVE | Q72: ZONA 1 | R72: - | S72: - | T72: - | U72: - | V72: PILAR TEKNOLOGI SOLUSI | W72: 039/PO/HR&GA/GA/VIII/2024 | X72: 45505 | Y72: =+X72+2195 -> 47700 | Z72: ARGAN | AA72: 085711148741 | AB72: CCTV DEPRE AGUS 24 | AC72: 47150 | BL72: O
B73: 70 | C73: 36 | D73: FI-01045 | E73: DOME | F73: GENERAL AFFAIR | G73: IT LEGAL DEPT | H73: SERVER ROOM 2 | I73: 1205001 | J73: PIK1CAM036 | K73: 172.17.101.50 | L73: - | M73: 2024 | N73: =M73+5 -> 2029 | O73: =N73+1 -> 2030 | P73: ACTIVE | Q73: ZONA 1 | R73: - | S73: - | T73: - | U73: - | V73: PILAR TEKNOLOGI SOLUSI | W73: 020/PO/HR&GA/GA/XI/2024 | X73: 45597 | Y73: =+X73+2195 -> 47792 | Z73: ARGAN | AA73: 085711148741 | AB73: CCTV DEPRE NOV 24 | AC73: 47150 | BL73: O
B74: 71 | C74: 53 | D74: FI-01051 | E74: DOME | F74: GENERAL AFFAIR | G74: IT LEGAL DEPT | H74: TANGGA KANTIN 1 | I74: 1205001 | J74: PIK1CAM053 | K74: 172.17.101.49 | L74: - | M74: 2024 | N74: =M74+5 -> 2029 | O74: =N74+1 -> 2030 | P74: ACTIVE | Q74: ZONA 2 | R74: - | S74: - | T74: - | U74: - | V74: PILAR TEKNOLOGI SOLUSI | W74: 016/PO/HR&GA/GA/XII/2024 | X74: 45627 | Y74: =+X74+2195 -> 47822 | Z74: ARGAN | AA74: 085711148741 | AB74: CCTV DEPRE DES 24 | AC74: 47178 | BM74: O
B75: 72 | C75: 58 | D75: FI-01047 | E75: DOME | F75: GENERAL AFFAIR | G75: IT LEGAL DEPT | H75: KANTIN TC | I75: 1205001 | J75: PIK1CAM058 | K75: 172.17.101.45 | L75: - | M75: 2024 | N75: =M75+5 -> 2029 | O75: =N75+1 -> 2030 | P75: ACTIVE | Q75: ZONA 2 | R75: - | S75: - | T75: - | U75: - | V75: PILAR TEKNOLOGI SOLUSI | W75: 006/PO/HR&GA/GA/XI/2024 | X75: 45566 | Y75: =+X75+2195 -> 47761 | Z75: ARGAN | AA75: 085711148741 | AB75: CCTV DEPRE OKT 24 | AC75: 47178 | BM75: O
B76: 73 | C76: 93 | D76: FI-01052 | E76: DOME | F76: GENERAL AFFAIR | G76: IT LEGAL DEPT | H76: CNC | I76: 1205001 | J76: PIK1CAM093 | K76: 172.17.101.96 | L76: - | M76: 2024 | N76: =M76+5 -> 2029 | O76: =N76+1 -> 2030 | P76: ACTIVE | Q76: ZONA 2 | R76: - | S76: - | T76: - | U76: - | V76: PILAR TEKNOLOGI SOLUSI | W76: 016/PO/HR&GA/GA/XII/2024 | X76: 45627 | Y76: =+X76+2195 -> 47822 | Z76: ARGAN | AA76: 085711148741 | AB76: CCTV DEPRE DES 24 | AC76: 47209 | BN76: O
B77: 74 | C77: 1 | D77: FI-00999 | E77: OUTDOOR | F77: GENERAL AFFAIR | G77: IT LEGAL DEPT | H77: PARKIR MOBIL 1 | I77: 1205001 | J77: PIK1CAM001 | K77: 172.17.101.42 | L77: - | M77: 2025 | N77: =M77+5 -> 2030 | O77: =N77+1 -> 2031 | P77: ACTIVE | Q77: ZONA 1 | R77: - | S77: - | T77: - | U77: - | V77: PILAR TEKNOLOGI SOLUSI | W77: 027/PO/HR&GA/GA/V/2024 | X77: 45383 | Y77: =+X77+2195 -> 47578 | Z77: ARGAN | AA77: 085711148741 | AB77: CCTV DEPRE APR 24 | AC77: 47209 | BN77: O
B78: 75 | C78: 2 | D78: FI-01000 | E78: OUTDOOR | F78: GENERAL AFFAIR | G78: IT LEGAL DEPT | H78: LOBY LUAR | I78: 1205001 | J78: PIK1CAM002 | K78: 172.17.101.14 | L78: - | M78: 2025 | N78: =M78+5 -> 2030 | O78: =N78+1 -> 2031 | P78: ACTIVE | Q78: ZONA 1 | R78: - | S78: - | T78: - | U78: - | V78: PILAR TEKNOLOGI SOLUSI | W78: 027/PO/HR&GA/GA/V/2024 | X78: 45383 | Y78: =+X78+2195 -> 47578 | Z78: ARGAN | AA78: 085711148741 | AB78: CCTV DEPRE APR 24 | AC78: 47239 | BO78: O
B79: 76 | C79: 3 | D79: FI-01009 | E79: OUTDOOR | F79: GENERAL AFFAIR | G79: IT LEGAL DEPT | H79: DEPAN POSKO | I79: 1205001 | J79: PIK1CAM003 | K79: 172.17.101.10 | L79: - | M79: 2025 | N79: =M79+5 -> 2030 | O79: =N79+1 -> 2031 | P79: ACTIVE | Q79: ZONA 1 | R79: - | S79: - | T79: - | U79: - | V79: PILAR TEKNOLOGI SOLUSI | W79: 076/PO/HR&GA/GA/V/2024 | X79: 45413 | Y79: =+X79+2195 -> 47608 | Z79: ARGAN | AA79: 085711148741 | AB79: CCTV DEPRE MEI 24 | AC79: 47239 | BO79: O
B80: 77 | C80: 6 | D80: FI-01010 | E80: OUTDOOR | F80: GENERAL AFFAIR | G80: IT LEGAL DEPT | H80: PARKIR MOBIL 3 | I80: 1205001 | J80: PIK1CAM006 | K80: 172.17.101.41 | L80: - | M80: 2025 | N80: =M80+5 -> 2030 | O80: =N80+1 -> 2031 | P80: ACTIVE | Q80: ZONA 1 | R80: - | S80: - | T80: - | U80: - | V80: PILAR TEKNOLOGI SOLUSI | W80: 076/PO/HR&GA/GA/V/2024 | X80: 45413 | Y80: =+X80+2195 -> 47608 | Z80: ARGAN | AA80: 085711148741 | AB80: CCTV DEPRE MEI 24 | AC80: 47270 | BP80: O
B81: 78 | C81: 10 | D81: FI-00922 | E81: DOME | F81: GENERAL AFFAIR | G81: IT LEGAL DEPT | H81: LORONG PANTRY | I81: 1205001 | J81: PIK1CAM010 | K81: 172.17.101.22 | L81: - | M81: 2025 | N81: =M81+5 -> 2030 | O81: =N81+1 -> 2031 | P81: ACTIVE | Q81: ZONA 1 | R81: - | S81: - | T81: - | U81: - | V81: SECOM INDONESIA | W81: 026/PO/HR&GA/GA/IX/2023 | X81: 45170 | Y81: =+X81+2195 -> 47365 | Z81: CAHYO | AA81: 0857-7112-2277 | AC81: 47270 | BP81: O
B82: 79 | C82: 47 | D82: FI-01086 | E82: DOME 360 | F82: GENERAL AFFAIR | G82: IT LEGAL DEPT | H82: LORONG LOKER 1 | I82: 1205001 | J82: PIK1CAM047 | K82: 172.17.101.58 | L82: - | M82: 2025 | N82: =M82+5 -> 2030 | O82: =N82+1 -> 2031 | P82: ACTIVE | Q82: ZONA 2 | R82: - | S82: - | T82: - | U82: - | V82: PILAR TEKNOLOGI SOLUSI | W82: 017/PO/HR&GA/GA/XII/2024 | X82: 45658 | Y82: =+X82+2195 -> 47853 | Z82: ARGAN | AA82: 085711148741 | AB82: CCTV DEPRE JAN 25 | AC82: 47300 | BQ82: O
B83: 80 | C83: 48 | D83: FI-01087 | E83: DOME 360 | F83: GENERAL AFFAIR | G83: IT LEGAL DEPT | H83: LORONG LOKER 2 | I83: 1205001 | J83: PIK1CAM048 | K83: 172.17.101.57 | L83: - | M83: 2025 | N83: =M83+5 -> 2030 | O83: =N83+1 -> 2031 | P83: ACTIVE | Q83: ZONA 2 | R83: - | S83: - | T83: - | U83: - | V83: PILAR TEKNOLOGI SOLUSI | W83: 017/PO/HR&GA/GA/XII/2024 | X83: 45658 | Y83: =+X83+2195 -> 47853 | Z83: ARGAN | AA83: 085711148741 | AB83: CCTV DEPRE JAN 25 | AC83: 47300 | BQ83: O
B84: 81 | C84: 54 | D84: FI-01055 | E84: DOME | F84: GENERAL AFFAIR | G84: IT LEGAL DEPT | H84: TANGGA KANTIN 2 | I84: 1205001 | J84: PIK1CAM054 | K84: 172.17.101.56 | L84: - | M84: 2025 | N84: =M84+5 -> 2030 | O84: =N84+1 -> 2031 | P84: ACTIVE | Q84: ZONA 2 | R84: - | S84: - | T84: - | U84: - | V84: PILAR TEKNOLOGI SOLUSI | W84: 029/PO/HR&GA/GA/XI/2024 | X84: 45717 | Y84: =+X84+2195 -> 47912 | Z84: ARGAN | AA84: 085711148741 | AB84: CCTV DEPRE MAR 25 | AC84: 47331 | BR84: O
B85: 82 | C85: 56 | D85: FI-01057 | E85: DOME | F85: GENERAL AFFAIR | G85: IT LEGAL DEPT | H85: KANTIN LIFT | I85: 1205001 | J85: PIK1CAM056 | K85: 172.17.101.47 | L85: - | M85: 2025 | N85: =M85+5 -> 2030 | O85: =N85+1 -> 2031 | P85: ACTIVE | Q85: ZONA 2 | R85: - | S85: - | T85: - | U85: - | V85: PILAR TEKNOLOGI SOLUSI | W85: 028/PO/HR&GA/GA/XI/2024 | X85: 45689 | Y85: =+X85+2195 -> 47884 | Z85: ARGAN | AA85: 085711148741 | AB85: CCTV DEPRE FEB 25 | AC85: 47331 | BR85: O
B86: 83 | C86: 57 | D86: FI-01058 | E86: DOME | F86: GENERAL AFFAIR | G86: IT LEGAL DEPT | H86: KANTIN SPM | I86: 1205001 | J86: PIK1CAM057 | K86: 172.17.101.48 | L86: - | M86: 2025 | N86: =M86+5 -> 2030 | O86: =N86+1 -> 2031 | P86: ACTIVE | Q86: ZONA 2 | R86: - | S86: - | T86: - | U86: - | V86: PILAR TEKNOLOGI SOLUSI | W86: 028/PO/HR&GA/GA/XI/2024 | X86: 45689 | Y86: =+X86+2195 -> 47884 | Z86: ARGAN | AA86: 085711148741 | AB86: CCTV DEPRE FEB 25 | AC86: 47362 | BS86: O
B87: 84 | C87: 61 | D87: FI-01056 | E87: DOME | F87: GENERAL AFFAIR | G87: IT LEGAL DEPT | H87: MUSHOLA DALAM | I87: 1205001 | J87: PIK1CAM061 | K87: 172.17.101.46 | L87: - | M87: 2025 | N87: =M87+5 -> 2030 | O87: =N87+1 -> 2031 | P87: ACTIVE | Q87: ZONA 2 | R87: - | S87: - | T87: - | U87: - | V87: PILAR TEKNOLOGI SOLUSI | W87: 029/PO/HR&GA/GA/XI/2024 | X87: 45717 | Y87: =+X87+2195 -> 47912 | Z87: ARGAN | AA87: 085711148741 | AB87: CCTV DEPRE MAR 25 | AC87: 47362 | BS87: O
B88: 85 | C88: 94 | D88: FI-01055 | E88: OUTDOOR | F88: GENERAL AFFAIR | G88: IT LEGAL DEPT | H88: ELECTRIC ROOM ZONA 2 | I88: 1205001 | J88: PIK1CAM097 | K88: 172.17.101.97 | L88: - | M88: 2025 | N88: =M88+5 -> 2030 | O88: =N88+1 -> 2031 | P88: ACTIVE | Q88: ZONA 2 | R88: - | S88: - | T88: - | U88: - | V88: PILAR TEKNOLOGI SOLUSI | W88: 038/PO/HR&GA/GA/VII/2024 | X88: 45474 | Y88: =+X88+2195 -> 47669 | Z88: ARGAN | AA88: 085711148741 | AB88: CCTV DEPRE JULI 24 | AC88: 47392 | BT88: O
B89: 86 | C89: 40 | D89: BELUM AKUSISI FINANCE | E89: OUTDOOR | F89: GENERAL AFFAIR | G89: IT LEGAL DEPT | H89: GATE POS 1 | I89: 1205001 | J89: PIK1CAM040 | K89: 172.17.101.61 | L89: - | M89: 2025 | N89: =M89+5 -> 2030 | O89: =N89+1 -> 2031 | P89: ACTIVE | Q89: ZONA 2 | R89: - | S89: - | T89: - | U89: - | V89: PILAR TEKNOLOGI SOLUSI | W89: 029/PO/HR&GA/GA/VIII/2025 | X89: 45870 | Y89: =+X89+2195 -> 48065 | Z89: ARGAN | AA89: 085711148741 | AB89: CCTV DEPRE AGUS 25 | AC89: 47392 | BT89: O
B90: 87 | C90: 41 | D90: BELUM AKUSISI FINANCE | E90: OUTDOOR | F90: GENERAL AFFAIR | G90: IT LEGAL DEPT | H90: JALAN POS 1 | I90: 1205001 | J90: PIK1CAM041 | K90: 172.17.101.62 | L90: - | M90: 2025 | N90: =M90+5 -> 2030 | O90: =N90+1 -> 2031 | P90: ACTIVE | Q90: ZONA 2 | R90: - | S90: - | T90: - | U90: - | V90: PILAR TEKNOLOGI SOLUSI | W90: 029/PO/HR&GA/GA/VIII/2025 | X90: 45870 | Y90: =+X90+2195 -> 48065 | Z90: ARGAN | AA90: 085711148741 | AB90: CCTV DEPRE AGUS 25 | AC90: 47423 | BU90: O
B91: 88 | C91: 59 | D91: BELUM AKUSISI FINANCE | E91: OUTDOOR | F91: GENERAL AFFAIR | G91: IT LEGAL DEPT | H91: TNGGA MEZANIN TC | I91: 1205001 | J91: PIK1CAM059 | K91: 172.17.101.68 | L91: - | M91: 2025 | N91: =M91+5 -> 2030 | O91: =N91+1 -> 2031 | P91: ACTIVE | Q91: ZONA 2 | R91: - | S91: - | T91: - | U91: - | V91: PILAR TEKNOLOGI SOLUSI | W91: 022/PO/HR&GA/GA/VII/2025 | X91: 45839 | Y91: =X91+2195 -> 48034 | Z91: ARGAN | AA91: 085711148741 | AB91: CCTV DEPRE JUL 25 | AC91: 47423 | BU91: O
B92: 89 | C92: 15 | D92: BELUM AKUSISI FINANCE | E92: OUTDOOR | F92: GENERAL AFFAIR | G92: IT LEGAL DEPT | H92: FINISH GOOD | I92: 1205001 | J92: PIK1CAM015 | K92: 172.17.101.17 | L92: - | M92: 2025 | N92: =M92+5 -> 2030 | O92: =N92+1 -> 2031 | P92: ACTIVE | Q92: ZONA 1 | R92: - | S92: - | T92: - | U92: - | V92: PILAR TEKNOLOGI SOLUSI | W92: 072/PO/HR&GA/GA/VI/2025 | X92: 45809 | Y92: =X92+2195 -> 48004 | Z92: ARGAN | AA92: 085711148741 | AB92: CCTV DEPRE JUN 25 | AC92: 47453 | BV92: O
B93: 90 | C93: 18 | D93: BELUM AKUSISI FINANCE | E93: OUTDOOR | F93: GENERAL AFFAIR | G93: IT LEGAL DEPT | H93: AREA MTC | I93: 1205001 | J93: PIK1CAM018 | K93: 172.17.101.12 | L93: - | M93: 2025 | N93: =M93+5 -> 2030 | O93: =N93+1 -> 2031 | P93: ACTIVE | Q93: ZONA 1 | R93: - | S93: - | T93: - | U93: - | V93: PILAR TEKNOLOGI SOLUSI | W93: 010/PO/HR&GA/GA/VI/2025 | X93: 45748 | Y93: =X93+2195 -> 47943 | Z93: ARGAN | AA93: 085711148741 | AB93: CCTV DEPRE APR 25 | AC93: 47453 | BV93: O
B94: 91 | C94: 24 | D94: BELUM AKUSISI FINANCE | E94: OUTDOOR | F94: GENERAL AFFAIR | G94: IT LEGAL DEPT | H94: INJECT BMC | I94: 1205001 | J94: PIK1CAM024 | K94: 172.17.101.40 | L94: - | M94: 2025 | N94: =M94+5 -> 2030 | O94: =N94+1 -> 2031 | P94: ACTIVE | Q94: ZONA 1 | R94: - | S94: - | T94: - | U94: - | V94: PILAR TEKNOLOGI SOLUSI | W94: 072/PO/HR&GA/GA/VI/2025 | X94: 45809 | Y94: =X94+2195 -> 48004 | Z94: ARGAN | AA94: 085711148741 | AB94: CCTV DEPRE JUN 25 | AC94: 47484 | BW94: O
B95: 92 | C95: 35 | D95: BELUM AKUSISI FINANCE | E95: OUTDOOR | F95: GENERAL AFFAIR | G95: IT LEGAL DEPT | H95: VIBRASI ROOM | I95: 1205001 | J95: PIK1CAM035 | K95: 172.17.101.44 | L95: - | M95: 2025 | N95: =M95+5 -> 2030 | O95: =N95+1 -> 2031 | P95: ACTIVE | Q95: ZONA 1 | R95: - | S95: - | T95: - | U95: - | V95: PILAR TEKNOLOGI SOLUSI | W95: 010/PO/HR&GA/GA/VI/2025 | X95: 45748 | Y95: =X95+2195 -> 47943 | Z95: ARGAN | AA95: 085711148741 | AB95: CCTV DEPRE APR 25 | AC95: 47484 | BW95: O
B96: 93 | C96: 37 | D96: BELUM AKUSISI FINANCE | E96: OUTDOOR | F96: GENERAL AFFAIR | G96: IT LEGAL DEPT | H96: MESIN SCRAP | I96: 1205001 | J96: PIK1CAM037 | K96: 172.17.101.54 | L96: - | M96: 2025 | N96: =M96+5 -> 2030 | O96: =N96+1 -> 2031 | P96: ACTIVE | Q96: ZONA 1 | R96: - | S96: - | T96: - | U96: - | V96: PILAR TEKNOLOGI SOLUSI | W96: 072/PO/HR&GA/GA/VI/2025 | X96: 45809 | Y96: =X96+2195 -> 48004 | Z96: ARGAN | AA96: 085711148741 | AB96: CCTV DEPRE JUN 25 | AC96: 47515 | BX96: O
C97: 62 | D97: - | E97: - | F97: - | G97: - | H97: NO CAM | I97: 1205001 | J97: - | K97: - | L97: - | M97: - | N97: - | O97: - | P97: - | Q97: - | R97: - | S97: - | T97: - | U97: -

Sheet Sheet1
A1: User | G1: IP ADDRESS MAIN
A2: NO | B2: NO.ASSET | C2: TYPE | D2: NAMA | E2: NIK | F2: HOSTNAME | H2: SUPPLIER | I2: NO PO | J2: TAHUN BELI | K2: BULAN DEPRESIASI | L2: PIC SUPPLIER | M2: KONTAK SUPPLIER | N2: REMARKS
A3: 1 | B3: FI-00991 | C3: DOME | D3: OFFICE ADM 1 | E3: 1205001 | F3: PIK1CAM011 | G3: 172.17.101.31 | H3: PILAR TEKNOLOGI SOLUSI | I3: 075/PO/HR&GA/GA/V/2024 | J3: 45413 | K3: 47608 | L3: ARGAN | M3: 085711148741 | N3: CCTV ADD MEI 24
A4: 2 | B4: FI-00992 | C4: DOME | D4: OFFICE ADM 2 | E4: 1205001 | F4: PIK1CAM012 | G4: 172.17.101.5 | H4: PILAR TEKNOLOGI SOLUSI | I4: 075/PO/HR&GA/GA/V/2024 | J4: 45413 | K4: 47608 | L4: ARGAN | M4: 085711148741 | N4: CCTV ADD MEI 24
A5: 3 | B5: FI-00993 | C5: DOME | D5: SERVER ROOM | E5: 1205001 | F5: PIK1CAM013 | G5: 172.17.11.43 | H5: PILAR TEKNOLOGI SOLUSI | I5: 075/PO/HR&GA/GA/V/2024 | J5: 45413 | K5: 47608 | L5: ARGAN | M5: 085711148741 | N5: CCTV ADD MEI 24
A6: 4 | B6: FI-00999 | C6: OUTDOOR | D6: PARKIR MOBIL 1 | E6: 1205001 | F6: PIK1CAM001 | G6: 172.17.101.42 | H6: PILAR TEKNOLOGI SOLUSI | I6: 027/PO/HR&GA/GA/V/2024 | J6: 45383 | K6: 47578 | L6: ARGAN | M6: 085711148741 | N6: CCTV DEPRE APR 24
A7: 5 | B7: FI-01000 | C7: OUTDOOR | D7: LOBY LUAR | E7: 1205001 | F7: PIK1CAM002 | G7: 172.17.101.14 | H7: PILAR TEKNOLOGI SOLUSI | I7: 027/PO/HR&GA/GA/V/2024 | J7: 45383 | K7: 47578 | L7: ARGAN | M7: 085711148741 | N7: CCTV DEPRE APR 24
A8: 6 | B8: FI-01007 | C8: DOME | D8: LOBBY DALAM | E8: 1205001 | F8: PIK1CAM009 | G8: 172.17.101.4 | H8: PILAR TEKNOLOGI SOLUSI | I8: 039/PO/HR&GA/GA/VIII/2024 | J8: 45505 | K8: 47700 | L8: ARGAN | M8: 085711148741 | N8: CCTV DEPRE AGUS 24
A9: 7 | B9: FI-01008 | C9: DOME | D9: LORONG QLTY | E9: 1205001 | F9: PIK1CAM034 | G9: 172.17.101.63 | H9: PILAR TEKNOLOGI SOLUSI | I9: 039/PO/HR&GA/GA/VIII/2024 | J9: 45505 | K9: 47700 | L9: ARGAN | M9: 085711148741 | N9: CCTV DEPRE AGUS 24
A10: 8 | B10: FI-01009 | C10: OUTDOOR | D10: DEPAN POSKO | E10: 1205001 | F10: PIK1CAM003 | G10: 172.17.101.10 | H10: PILAR TEKNOLOGI SOLUSI | I10: 076/PO/HR&GA/GA/V/2024 | J10: 45413 | K10: 47608 | L10: ARGAN | M10: 085711148741 | N10: CCTV DEPRE MEI 24
A11: 9 | B11: FI-01010 | C11: OUTDOOR | D11: PARKIR MOBIL 3 | E11: 1205001 | F11: PIK1CAM006 | G11: 172.17.101.41 | H11: PILAR TEKNOLOGI SOLUSI | I11: 076/PO/HR&GA/GA/V/2024 | J11: 45413 | K11: 47608 | L11: ARGAN | M11: 085711148741 | N11: CCTV DEPRE MEI 24
A12: 10 | B12: FI-01027 | C12: DOME | D12: LORONG OFFICE 1 | E12: 1205001 | F12: PIK1CAM014 | G12: 172.17.101.19 | H12: PILAR TEKNOLOGI SOLUSI | I12: 065/PO/HR&GA/GA/IX/2024 | J12: 45536 | K12: 47731 | L12: ARGAN | M12: 085711148741 | N12: CCTV DEPRE SEP 24
A13: 11 | B13: FI-01028 | C13: DOME | D13: OFFICE PROD | E13: 1205001 | F13: PIK1CAM016 | G13: 172.17.101.21 | H13: PILAR TEKNOLOGI SOLUSI | I13: 065/PO/HR&GA/GA/IX/2024 | J13: 45536 | K13: 47731 | L13: ARGAN | M13: 085711148741 | N13: CCTV DEPRE SEP 24
A14: 12 | B14: FI-01044 | C14: DOME | D14: OFFICE QLTY 2 | E14: 1205001 | F14: PIK1CAM033 | G14: 172.17.101.64 | H14: PILAR TEKNOLOGI SOLUSI | I14: 020/PO/HR&GA/GA/XI/2024 | J14: 45597 | K14: 47792 | L14: ARGAN | M14: 085711148741 | N14: CCTV DEPRE NOV 24
... A37: 35 | B37: BELUM AKUSISI | C37: OUTDOOR | D37: JALAN POS 1 | E37: 1205001 | F37: PIK1CAM041 | G37: 172.17.101.62 | H37: PILAR TEKNOLOGI SOLUSI | I37: 029/PO/HR&GA/GA/VIII/2025 | J37: 45870 | K37: 48065 | L37: ARGAN | M37: 085711148741 | N37: CCTV DEPRE AGUS 25
A38: 36 | B38: FI-00185 | C38: OUTDOOR | D38: LOADING 2 | E38: 1205001 | F38: PIK1CAM029 | G38: 172.17.101.23 | H38: SECOM INDONESIA | I38: 22/HRGA/PO/IX/2014 | J38: 42004 | K38: =+J38+2190 -> 44194 | L38: CAHYO | M38: 0857-7112-2277 | N38: 014/PO/HR&GA/GA/XI/2025 | O38: NOT REPLACE
A39: 37 | B39: FI-00186 | C39: OUTDOOR | D39: LOADING 3 | E39: 1205001 | F39: PIK1CAM030 | G39: 172.17.101.30 | H39: SECOM INDONESIA | I39: 22/HRGA/PO/IX/2014 | J39: 42004 | K39: =+J39+2190 -> 44194 | L39: CAHYO | M39: 0857-7112-2277 | N39: 010/PO/HR&GA/GA/XII/2025 | O39: NOT REPLACE
A40: 38 | B40: FI-00498 | C40: OUTDOOR | D40: LORONG MUSHOLA 1 | E40: 1205001 | F40: PIK1CAM060 | G40: 172.17.101.59 | H40: SECOM INDONESIA | I40: '026/PO/HR&GA/GA/I/2019 | J40: 43707 | K40: =+J40+2190 -> 45897 | L40: CAHYO | M40: 0857-7112-2277 | N40: 010/PO/HR&GA/GA/XII/2025 | O40: NOT REPLACE
A41: 39 | B41: FI-00498 | C41: OUTDOOR | D41: ABSENSI MALE | E41: 1205001 | F41: PIK1CAM049 | G41: 172.17.101.55 | H41: SECOM INDONESIA | I41: '026/PO/HR&GA/GA/I/2019 | J41: 43707 | K41: =+J41+2190 -> 45897 | L41: CAHYO | M41: 0857-7112-2277 | N41: 010/PO/HR&GA/GA/XII/2025 | O41: NOT REPLACE
